Workbook

Sheet Instructions
B1: Verifying Franchise Sales from BI:
B2: See spreadsheet with instructions here:
B3: Z:\Shared\Accounting\Franchise Accounting\Weekly Billing\Franchise Sales\2021
B6: Putting together Franchise Royalty Calculator:
B7: Rates from Tracker | C7: Add any new franchise locations & rate info to the bottom of the sheet.
D8: !! - Make sure if you add/remove franchisee's you check that the WF Template has the correct account informatio/amount pulling correctly
B9: Calculations | C9: Update cell O5 with the first date of the franchise week you are working on
C10: In B-F, copypasta data from the Franchise Sales from Tableau
D11: !! - Make sure you verified the data first! (see "Verifying Franchise Sales from Tableau" above)
D12: !! - Make sure you remove any remaining data from the previous week's listing (Scroll to bottom and check on dates vs billing week)
D13: !! - Confirm Check figure in Column F agrees to Franchise Sales file for net sales
C14: Update check figures formulas to current franchise sales week file
C15: The calculations in G-M should auto-populate. If they do not, make sure the "Rates from Tracker" tab is updated with the stores that are erroring out.
C16: Column P will also show a store count for each day - make sure this ties to your open store count from the "Rates from Tracker"
D17: Note: Northwestern University and DTW Airport is billed via a separate method (store does not use Brink as their POS)
B19: Summary | C19: Update cell B3 with the end date of the franchise week you are working on
C20: Refresh Pivot
C21: Update V.I.'s tax amount
B23: Debit Memo Info | C23: If there any new locations, add a row to the bottom of the sheet
C24: See below "To Create AR Invoice in SAP" instructions
B28: To Create AR Invoice in SAP:
B29: Debit Memo Info - tab
B31: Manage Debit Memo Requests - SAP
C32: Create Debit Memo Request
C33: DR / 1750 / 10 / 00
H43: 1753 CAD
B60: Filter on Franchisee (in Debit Memo Info Tab in order of summary franchisee)
B61: Sold to Party = Franchisee
B62: Cust. Reference = Date range of billing (ex. 1/14/19-1/20/19)
B63: Billing Date = last day of billing (ex. 1/20/19)
B64: Billing Block = blank
B92: Go to "Sales" tab
B93: **Billing Block should be BLANK
B94: Order Reason = Sales Call
B96: Create line items for "Continuingfee" and "Marketingfee", one for each line for the franchisee
B97: Quantity = 1
B98: Copy over Item Descriptions into corresponding line items
B130: Use this below to copy, paste in 'Material'and 'Target Quantiy' while creating invoice
B132: CONTINUINGFEE | C132: MARKETINGFEE | D132: 1 | F132: ppr0
B133: CONTINUINGFEE | C133: MARKETINGFEE | D133: 1
B134: CONTINUINGFEE | C134: MARKETINGFEE | D134: 1
B135: CONTINUINGFEE | C135: MARKETINGFEE | D135: 1
B136: CONTINUINGFEE | C136: MARKETINGFEE | D136: 1
B137: CONTINUINGFEE | C137: MARKETINGFEE | D137: 1
B138: CONTINUINGFEE | C138: MARKETINGFEE | D138: 1
B139: CONTINUINGFEE | C139: MARKETINGFEE | D139: 1
B140: CONTINUINGFEE | C140: MARKETINGFEE | D140: 1
B141: CONTINUINGFEE | C141: MARKETINGFEE | D141: 1
B142: CONTINUINGFEE | C142: MARKETINGFEE | D142: 1
B143: CONTINUINGFEE | C143: MARKETINGFEE | D143: 1
B144: CONTINUINGFEE | C144: MARKETINGFEE | D144: 1
... B146: CONTINUINGFEE | C146: MARKETINGFEE | D146: 1
B149: Click checkbox to left of the first line item
B150: Click "item conditions" (dollar bill icon above the line items, next to the icon that looks like test tubes)
B151: Back up to first Sales Document Item
B152: CnTy = ppr0 at the bottom after 'Profit Margin'
B153: Paste in corresponding item amount
B179: Hit back button
B180: Verify that Net Value matches Total (column H) on sheet
B181: If it doesn't match, adjust in "Rounding" column on Summary tab (should not be more than ~5 cents)
B183: Hit save in SAP
B185: Go to "Create Billing Documents" tile to create & post the invoices you created. After posting each invoice, the "Output Items" section will allow you to download a PDF copy (click the PDF icon under the "Display" column)
B220: If you need to view an invoice again after it has already been posted, go to "Manage Billing Documents" tile. This will show all billing documents that have been created so you can cancel/post/etc.
B228: **** If you need to delete an invoice before you post it, here are the instuctions:
... B265: Select ' Sales Document' and click on 'Delete' under that.

Sheet Rates from Tracker
A3: Franchise Locations & Royalty Info | I3: Royalty Fee End Dates
A4: Location | B4: Debit Memo Location | C4: Franchisee | D4: Principal Name | E4: Founders/Non-Founders | F4: Open Date | G4: Marketing/Royalty Fee Start | H4: Marketing & Royalty Fee End | I4: 2.5% | J4: Start Period | K4: End Period - 2% | L4: 2% | M4: End Period - 3% | N4: 3% | O4: End Period - 4% | P4: 4% | Q4: End Period - 5% | R4: 5% | S4: End Period - 6% | T4: 6% | U4: Column1
A5: Asheville | B5: Asheville | C5: RTHT Investments LLC | D5: Goldman | E5: Founders | F5: 42646 | G5: 42647 | H5: 46320 | J5: PERIOD 11 2016 | K5: PERIOD 11 2017 | L5: 43037 | M5: PERIOD 11 2018 | N5: 43408 | O5: PERIOD 11 2019 | P5: 43772 | Q5: PERIOD 11 2026 | R5: 46320 | S5: PERIOD 11 2026
A6: Auburn Village | B6: Auburn Village | C6: Exceed Group Auburn Village | D6: Chawla | E6: Non-Founders | F6: 42891 | G6: 42892 | H6: 46544 | J6: PERIOD 6 2017 | K6: PERIOD 6 2018 | L6: 43268 | M6: PERIOD 6 2019 | N6: 43632 | O6: PERIOD 6 2020 | P6: 43996 | Q6: PERIOD 6 2027 | R6: 46544 | S6: PERIOD 6 2027
A7: Berewick | B7: Berewick | C7: RTHT Investments LLC | D7: Goldman | E7: Non-Founders | F7: 42968 | G7: 42969 | H7: 46628 | I7: 43008 | J7: PERIOD 9 2017 | Q7: PERIOD 9 2027 | R7: 46628 | S7: PERIOD 9 2027
A8: Blue Springs | B8: Blue Springs | C8: Paceline Partners, LLC (KS/MO) | D8: Womack | E8: Non-Founders | F8: 42847 | G8: 42848 | H8: 46516 | I8: 42930 | J8: PERIOD 5 2017 | Q8: PERIOD 5 2027 | R8: 46516 | S8: PERIOD 5 2027
A9: Brighton | B9: Brighton | C9: TSFR Pizza LLC | D9: Schostak | E9: Founders | F9: 42361 | G9: 42362 | H9: 46012 | J9: PERIOD 13 2015 | K9: PERIOD 13 2016 | L9: 42729 | M9: PERIOD 13 2017 | N9: 43100 | O9: PERIOD 13 2018 | P9: 43464 | Q9: PERIOD 13 2025 | R9: 46012 | S9: PERIOD 13 2025
A10: Canton | B10: Canton | C10: TSFR Pizza LLC | D10: Schostak | E10: Founders | F10: 42755 | G10: 42756 | H10: 46404 | J10: PERIOD 1 2017 | K10: PERIOD 1 2018 | L10: 43128 | M10: PERIOD 1 2019 | N10: 43492 | O10: PERIOD 1 2020 | P10: 43856 | Q10: PERIOD 1 2027 | R10: 46404 | S10: PERIOD 1 2027
A11: Carolina Forest | B11: Carolina Forest | C11: Rolling Dough LLC | D11: Connolly | E11: Founders | F11: 42879 | G11: 42880 | H11: 46544 | J11: PERIOD 6 2017 | K11: PERIOD 6 2018 | L11: 43268 | M11: PERIOD 6 2019 | N11: 43632 | O11: PERIOD 6 2020 | P11: 43996 | Q11: PERIOD 6 2027 | R11: 46544 | S11: PERIOD 6 2027
A12: Castle Rock | B12: Castle Rock | C12: Best Pizza LLC | D12: Merullo | E12: Founders | F12: 42373 | G12: 42374 | H12: 46040 | J12: PERIOD 1 2016 | K12: PERIOD 1 2017 | L12: 42757 | M12: PERIOD 1 2018 | N12: 43128 | O12: PERIOD 1 2019 | P12: 43492 | Q12: PERIOD 1 2026 | R12: 46040 | S12: PERIOD 1 2026
A13: Centre Avenue | B13: Centre Avenue | C13: Best Pizza LLC | D13: Merullo | E13: Founders | F13: 42667 | G13: 42668 | H13: 46320 | J13: PERIOD 11 2016 | K13: PERIOD 11 2017 | L13: 43037 | M13: PERIOD 11 2018 | N13: 43408 | O13: PERIOD 11 2019 | P13: 43772 | Q13: PERIOD 11 2026 | R13: 46320 | S13: PERIOD 11 2026
A14: Chesterfield Township | B14: Chesterfield Township | C14: TSFR Pizza LLC | D14: Schostak | E14: Founders | F14: 42749 | G14: 42750 | H14: 46404 | J14: PERIOD 1 2017 | K14: PERIOD 1 2018 | L14: 43128 | M14: PERIOD 1 2019 | N14: 43492 | O14: PERIOD 1 2020 | P14: 43856 | Q14: PERIOD 1 2027 | R14: 46404 | S14: PERIOD 1 2027
A15: Chico | B15: Chico | C15: Exceed Group Chico | D15: Chawla | E15: Non-Founders | F15: 42646 | G15: 42647 | H15: 46320 | J15: PERIOD 11 2016 | K15: PERIOD 11 2017 | L15: 43037 | M15: PERIOD 11 2018 | N15: 43408 | O15: PERIOD 11 2019 | P15: 43772 | Q15: PERIOD 11 2026 | R15: 46320 | S15: PERIOD 11 2026
A16: Dublin Commons | B16: Dublin Commons | C16: Best Pizza LLC | D16: Merullo | E16: Non-Founders | F16: 42983 | G16: 42984 | H16: 46656 | I16: 43008 | J16: PERIOD 10 2017 | Q16: PERIOD 10 2027 | R16: 46656 | S16: PERIOD 10 2027
A17: Englewood | B17: Englewood #5 | C17: Cool Dough Development, LLC | D17: Denning | E17: Non-Founders | F17: 42865 | G17: 42866 | H17: 46516 | I17: 42948 | J17: PERIOD 5 2017 | Q17: PERIOD 5 2027 | R17: 46516 | S17: PERIOD 5 2027
A18: Evansville | B18: Evansville #11 | C18: Cool Dough Development, LLC | D18: Denning | E18: Non-Founders | F18: 42949 | G18: 42950 | H18: 46600 | I18: 43032 | J18: PERIOD 8 2017 | Q18: PERIOD 8 2027 | R18: 46600 | S18: PERIOD 8 2027
A19: Falcon Landing | B19: Falcon Landing | C19: Best Pizza LLC | D19: Merullo | E19: Founders | F19: 42292 | G19: 42293 | H19: 45956 | J19: PERIOD 11 2015 | K19: PERIOD 11 2016 | L19: 42673 | M19: PERIOD 11 2017 | N19: 43037 | O19: PERIOD 11 2018 | P19: 43408 | Q19: PERIOD 11 2025 | R19: 45956 | S19: PERIOD 11 2025
A20: Fayetteville | B20: Fayetteville | C20: RTHT Investments LLC | D20: Goldman | E20: Founders | F20: 42324 | G20: 42325 | H20: 45984 | J20: PERIOD 12 2015 | K20: PERIOD 12 2016 | L20: 42701 | M20: PERIOD 12 2017 | N20: 43065 | O20: PERIOD 12 2018 | P20: 43436 | Q20: PERIOD 12 2025 | R20: 45984 | S20: PERIOD 12 2025
A21: Forest Trace | B21: Forest Trace | C21: Best Pizza LLC | D21: Merullo | E21: Founders | F21: 42662 | G21: 42663 | H21: 46320 | J21: PERIOD 11 2016 | K21: PERIOD 11 2017 | L21: 43037 | M21: PERIOD 11 2018 | N21: 43408 | O21: PERIOD 11 2019 | P21: 43772 | Q21: PERIOD 11 2026 | R21: 46320 | S21: PERIOD 11 2026
A22: Gahanna | B22: Gahanna | C22: Paceline Partners, LLC (OH) | D22: Womack | E22: Non-Founders | F22: 42662 | G22: 42663 | H22: 46320 | I22: 42745 | J22: PERIOD 11 2016 | Q22: PERIOD 11 2026 | R22: 46320 | S22: PERIOD 11 2026
A23: Hamburg | B23: Hamburg #6 | C23: Cool Dough Development, LLC | D23: Denning | E23: Non-Founders | F23: 42641 | G23: 42642 | H23: 46292 | I23: 42724 | J23: PERIOD 10 2016 | Q23: PERIOD 10 2026 | R23: 46292 | S23: PERIOD 10 2026
A24: Hikes Point | B24: Hikes Point #1 | C24: Cool Dough Development, LLC | D24: Denning | E24: Non-Founders | F24: 42571 | G24: 42572 | H24: 46236 | I24: 42654 | J24: PERIOD 8 2016 | Q24: PERIOD 8 2026 | R24: 46236 | S24: PERIOD 8 2026
A25: Howe Bout Arden | B25: Howe Bout Arden | C25: Exceed Group Howe Bout Arden | D25: Chawla | E25: Non-Founders | F25: 42404 | G25: 42405 | H25: 46068 | J25: PERIOD 2 2016 | K25: PERIOD 2 2017 | L25: 42785 | M25: PERIOD 2 2018 | N25: 43156 | O25: PERIOD 2 2019 | P25: 43520 | Q25: PERIOD 2 2026 | R25: 46068 | S25: PERIOD 2 2026
A26: Kennesaw | B26: Kennesaw | C26: Southern Pie LLC | D26: Hill/Hayden | E26: Non-Founders | F26: 42891 | G26: 42892 | H26: 46544 | I26: 42974 | J26: PERIOD 6 2017 | Q26: PERIOD 6 2027 | R26: 46544 | S26: PERIOD 6 2027
A27: King & Calhoun | B27: King & Calhoun | C27: Rolling Dough LLC | D27: Connolly | E27: Founders | F27: 42427 | G27: 42428 | H27: 46096 | J27: PERIOD 3 2016 | K27: PERIOD 3 2017 | L27: 42813 | M27: PERIOD 3 2018 | N27: 43184 | O27: PERIOD 3 2019 | P27: 43548 | Q27: PERIOD 3 2026 | R27: 46096 | S27: PERIOD 3 2026 | U27: Closed
A28: Liberty Triangle | B28: Liberty Triangle | C28: Paceline Partners, LLC (KS/MO) | D28: Womack | E28: Non-Founders | F28: 42634 | G28: 42635 | H28: 46292 | I28: 42717 | J28: PERIOD 10 2016 | Q28: PERIOD 10 2026 | R28: 46292 | S28: PERIOD 10 2026
A29: LIVONIA | B29: LIVONIA | C29: TSFR Pizza LLC | D29: Schostak | E29: Founders | F29: 42178 | G29: 42179 | H29: 45844 | J29: PERIOD 7 2015 | K29: PERIOD 7 2016 | L29: 42561 | M29: PERIOD 7 2017 | N29: 42925 | O29: PERIOD 7 2018 | P29: 43296 | Q29: PERIOD 7 2025 | R29: 45844 | S29: PERIOD 7 2025
A30: Matthews | B30: Matthews | C30: RTHT Investments LLC | D30: Goldman | E30: Non-Founders | F30: 42913 | G30: 42914 | H30: 46572 | J30: PERIOD 7 2017 | K30: PERIOD 7 2018 | M30: PERIOD 7 2019 | O30: PERIOD 7 2020 | Q30: PERIOD 7 2027 | R30: 46572 | S30: PERIOD 7 2027
A31: McCaslin Marketplace | B31: McCaslin Marketplace | C31: Best Pizza LLC | D31: Merullo | E31: Founders | F31: 42641 | G31: 42642 | H31: 46292 | J31: PERIOD 10 2016 | K31: PERIOD 10 2017 | L31: 43009 | M31: PERIOD 10 2018 | N31: 43380 | O31: PERIOD 10 2019 | P31: 43744 | Q31: PERIOD 10 2026 | R31: 46292 | S31: PERIOD 10 2026
A32: Millbrook Road | B32: Millbrook Road | C32: RTHT Investments LLC | D32: Goldman | E32: Founders | F32: 42234 | G32: 42235 | H32: 45900 | J32: PERIOD 9 2015 | K32: PERIOD 9 2016 | L32: 42617 | M32: PERIOD 9 2017 | N32: 42981 | O32: PERIOD 9 2018 | P32: 43352 | Q32: PERIOD 9 2025 | R32: 45900 | S32: PERIOD 9 2025
A33: Morse Road | B33: Morse Road | C33: Paceline Partners, LLC (OH) | D33: Womack | E33: Non-Founders | F33: 42826 | G33: 42827 | H33: 46488 | I33: 42909 | J33: PERIOD 4 2017 | Q33: PERIOD 4 2027 | R33: 46488 | S33: PERIOD 4 2027
A34: NE Columbia | B34: NE Columbia | C34: Rolling Dough LLC | D34: Connolly | E34: Founders | F34: 42820 | G34: 42821 | H34: 46488 | J34: PERIOD 4 2017 | K34: PERIOD 4 2018 | L34: 43212 | M34: PERIOD 4 2019 | N34: 43576 | O34: PERIOD 4 2020 | P34: 43940 | Q34: PERIOD 4 2027 | R34: 46488 | S34: PERIOD 4 2027
A35: North Charleston | B35: North Charleston | C35: Rolling Dough LLC | D35: Connolly | E35: Founders | F35: 42642 | G35: 42643 | H35: 46292 | J35: PERIOD 10 2016 | K35: PERIOD 10 2017 | L35: 43009 | M35: PERIOD 10 2018 | N35: 43380 | O35: PERIOD 10 2019 | P35: 43744 | Q35: PERIOD 10 2026 | R35: 46292 | S35: PERIOD 10 2026
A36: North Myrtle Beach | B36: North Myrtle Beach | C36: Rolling Dough LLC | D36: Connolly | E36: Founders | F36: 42468 | G36: 42469 | H36: 46124 | J36: PERIOD 4 2016 | K36: PERIOD 4 2017 | L36: 42841 | M36: PERIOD 4 2018 | N36: 43212 | O36: PERIOD 4 2019 | P36: 43576 | Q36: PERIOD 4 2026 | R36: 46124 | S36: PERIOD 4 2026
A37: Northville | B37: Northville | C37: TSFR Pizza LLC | D37: Schostak | E37: Founders | F37: 42231 | G37: 42232 | H37: 45900 | J37: PERIOD 9 2015 | K37: PERIOD 9 2016 | L37: 42617 | M37: PERIOD 9 2017 | N37: 42981 | O37: PERIOD 9 2018 | P37: 43352 | Q37: PERIOD 9 2025 | R37: 45900 | S37: PERIOD 9 2025
A38: Oakley | B38: Oakley #2 | C38: Cool Dough Development, LLC | D38: Denning | E38: Non-Founders | F38: 42662 | G38: 42663 | H38: 46320 | I38: 42745 | J38: PERIOD 11 2016 | Q38: PERIOD 11 2026 | R38: 46320 | S38: PERIOD 11 2026
A39: Owensboro | B39: Owensboro #8 | C39: Cool Dough Development, LLC | D39: Denning | E39: Non-Founders | F39: 42781 | G39: 42782 | H39: 46432 | I39: 42864 | J39: PERIOD 2 2017 | Q39: PERIOD 2 2027 | R39: 46432 | S39: PERIOD 2 2027
A40: Park Meadows | B40: Park Meadows | C40: Best Pizza LLC | D40: Merullo | E40: Founders | F40: 41892 | G40: 41893 | H40: 45564 | J40: PERIOD 10 2014 | K40: PERIOD 10 2015 | L40: 42281 | M40: PERIOD 10 2016 | N40: 42645 | O40: PERIOD 10 2017 | P40: 43009 | Q40: PERIOD 10 2024 | R40: 45564 | S40: PERIOD 10 2024
A41: Polaris | B41: Polaris | C41: Paceline Partners, LLC (OH) | D41: Womack | E41: Non-Founders | F41: 42748 | G41: 42749 | H41: 46404 | I41: 42831 | J41: PERIOD 1 2017 | Q41: PERIOD 1 2027 | R41: 46404 | S41: PERIOD 1 2027
A42: Raymore | B42: Raymore | C42: Paceline Partners, LLC (KS/MO) | D42: Womack | E42: Non-Founders | F42: 42942 | G42: 42943 | H42: 46600 | I42: 43025 | J42: PERIOD 8 2017 | Q42: PERIOD 8 2027 | R42: 46600 | S42: PERIOD 8 2027
A43: REDDING | B43: REDDING | C43: Exceed Group REDDING | D43: Chawla | E43: Non-Founders | F43: 42129.292 | Q43: PERIOD 5 2025 | R43: 45788 | S43: PERIOD 5 2025
A44: Redfield Promenade | B44: Redfield Promenade | C44: Exceed Group Redfield Promenade | D44: Chawla | E44: Non-Founders | F44: 42954 | G44: 42955 | H44: 46628 | J44: PERIOD 9 2017 | K44: PERIOD 9 2018 | L44: 43352 | M44: PERIOD 9 2019 | N44: 43716 | O44: PERIOD 9 2020 | P44: 44080 | Q44: PERIOD 9 2027 | R44: 46628 | S44: PERIOD 9 2027
A45: Rivergate | B45: Rivergate | C45: RTHT Investments LLC | D45: Goldman | E45: Founders | F45: 42283 | G45: 42284 | H45: 45956 | J45: PERIOD 11 2015 | K45: PERIOD 11 2016 | L45: 42673 | M45: PERIOD 11 2017 | N45: 43037 | O45: PERIOD 11 2018 | P45: 43408 | Q45: PERIOD 11 2025 | R45: 45956 | S45: PERIOD 11 2025
A46: Rochester Hills | B46: Rochester Hills | C46: TSFR Pizza LLC | D46: Schostak | E46: Founders | F46: 42322 | G46: 42323 | H46: 45984 | J46: PERIOD 12 2015 | K46: PERIOD 12 2016 | L46: 42701 | M46: PERIOD 12 2017 | N46: 43065 | O46: PERIOD 12 2018 | P46: 43436 | Q46: PERIOD 12 2025 | R46: 45984 | S46: PERIOD 12 2025
A47: ROCKLIN | B47: ROCKLIN | C47: Exceed Group ROCKLIN | D47: Chawla | E47: Non-Founders | F47: 42160.292 | G47: 42161.292 | H47: 45816 | J47: PERIOD 6 2015 | K47: PERIOD 6 2016 | L47: 42533 | M47: PERIOD 6 2017 | N47: 42897 | O47: PERIOD 6 2018 | P47: 43268 | Q47: PERIOD 6 2025 | R47: 45816 | S47: PERIOD 6 2025
A48: South Academy Highlands | B48: S Academy Highlands | C48: Best Pizza LLC | D48: Merullo | E48: Non-Founders | F48: 42968 | G48: 42969 | H48: 46628 | J48: PERIOD 9 2017 | K48: PERIOD 9 2018 | M48: PERIOD 9 2019 | O48: PERIOD 9 2020 | Q48: PERIOD 9 2027 | R48: 46628 | S48: PERIOD 9 2027
A49: Sawmill Road | B49: Sawmill Road | C49: Paceline Partners, LLC (OH) | D49: Womack | E49: Non-Founders | F49: 42928 | G49: 42929 | H49: 46600 | I49: 43011 | J49: PERIOD 8 2017 | Q49: PERIOD 8 2027 | R49: 46600 | S49: PERIOD 8 2027
A50: Shelby Township | B50: Shelby Township | C50: TSFR Pizza LLC | D50: Schostak | E50: Founders | F50: 42798 | G50: 42799 | H50: 46460 | J50: PERIOD 3 2017 | K50: PERIOD 3 2018 | L50: 43184 | M50: PERIOD 3 2019 | N50: 43548 | O50: PERIOD 3 2020 | P50: 43912 | Q50: PERIOD 3 2027 | R50: 46460 | S50: PERIOD 3 2027 | U50: Closed
A51: South Myrtle Beach | B51: South Myrtle Beach | C51: Rolling Dough LLC | D51: Connolly | E51: Founders | F51: 42707 | G51: 42708 | H51: 46376 | J51: PERIOD 13 2016 | K51: PERIOD 13 2017 | L51: 43100 | M51: PERIOD 13 2018 | N51: 43464 | O51: PERIOD 13 2019 | P51: 43828 | Q51: PERIOD 13 2026 | R51: 46376 | S51: PERIOD 13 2026
A52: Olathe | B52: Olathe | C52: Paceline Partners, LLC (KS/MO) | D52: Womack | E52: Non-Founders | F52: 42711 | G52: 42712 | H52: 46376 | I52: 42794 | J52: PERIOD 13 2016 | Q52: PERIOD 13 2026 | R52: 46376 | S52: PERIOD 13 2026
A53: Tates Creek | B53: Tates Creek #7 | C53: Cool Dough Development, LLC | D53: Denning | E53: Non-Founders | F53: 42914 | G53: 42915 | H53: 46572 | I53: 42997 | J53: PERIOD 7 2017 | Q53: PERIOD 7 2027 | R53: 46572 | S53: PERIOD 7 2027
A54: Wake Forest | B54: Wake Forest | C54: RTHT Investments LLC | D54: Goldman | E54: Founders | F54: 42856 | G54: 42857 | H54: 46516 | J54: PERIOD 5 2017 | K54: PERIOD 5 2018 | L54: 43240 | M54: PERIOD 5 2019 | N54: 43604 | O54: PERIOD 5 2020 | P54: 43968 | Q54: PERIOD 5 2027 | R54: 46516 | S54: PERIOD 5 2027
A55: West Chester | B55: West Chester #3 | C55: Cool Dough Development, LLC | D55: Denning | E55: Non-Founders | F55: 42718 | G55: 42719 | H55: 46376 | I55: 42801 | J55: PERIOD 13 2016 | Q55: PERIOD 13 2026 | R55: 46376 | S55: PERIOD 13 2026
A56: Westminster Promenade | B56: Westminster Promenade | C56: Best Pizza LLC | D56: Merullo | E56: Non-Founders | F56: 42961 | G56: 42962 | H56: 46628 | J56: PERIOD 9 2017 | K56: PERIOD 9 2018 | M56: PERIOD 9 2019 | O56: PERIOD 9 2020 | Q56: PERIOD 9 2027 | R56: 46628 | S56: PERIOD 9 2027
A57: Westwood Plaza | B57: Westwood Plaza | C57: Rolling Dough LLC | D57: Connolly | E57: Founders | F57: 42599 | G57: 42600 | H57: 46264 | J57: PERIOD 9 2016 | K57: PERIOD 9 2017 | L57: 42981 | M57: PERIOD 9 2018 | N57: 43352 | O57: PERIOD 9 2019 | P57: 43716 | Q57: PERIOD 9 2026 | R57: 46264 | S57: PERIOD 9 2026
A58: Woodhaven | B58: Woodhaven | C58: TSFR Pizza LLC | D58: Schostak | E58: Founders | F58: 42350 | G58: 42351 | H58: 46012 | J58: PERIOD 13 2015 | K58: PERIOD 13 2016 | L58: 42729 | M58: PERIOD 13 2017 | N58: 43100 | O58: PERIOD 13 2018 | P58: 43464 | Q58: PERIOD 13 2025 | R58: 46012 | S58: PERIOD 13 2025
A59: Woodhill | B59: Woodhill | C59: Rolling Dough LLC | D59: Connolly | E59: Founders | F59: 42549 | G59: 42550 | H59: 46208 | J59: PERIOD 7 2016 | K59: PERIOD 7 2017 | L59: 42925 | M59: PERIOD 7 2018 | N59: 43296 | O59: PERIOD 7 2019 | P59: 43660 | Q59: PERIOD 7 2026 | R59: 46208 | S59: PERIOD 7 2026
A60: Woodland | B60: Woodland | C60: Exceed Group Woodland | D60: Chawla | E60: Non-Founders | F60: 42793 | G60: 42794 | H60: 46460 | J60: PERIOD 3 2017 | K60: PERIOD 3 2018 | L60: 43184 | M60: PERIOD 3 2019 | N60: 43548 | O60: PERIOD 3 2020 | P60: 43912 | Q60: PERIOD 3 2027 | R60: 46460 | S60: PERIOD 3 2027
A61: Cornerstone | B61: Cornerstone #4 | C61: Cool Dough Development, LLC | D61: Denning | E61: Non-Founders | F61: 42998 | G61: 42999 | H61: 46656 | I61: 43081 | J61: PERIOD 10 2017 | Q61: PERIOD 10 2027 | R61: 46656 | S61: PERIOD 10 2027 | U61: Closed 9/13
A62: Pickerington | B62: Pickerington | C62: Paceline Partners, LLC (OH) | D62: Womack | E62: Non-Founders | F62: 42998 | G62: 42999 | H62: 46656 | I62: 43081 | J62: PERIOD 10 2017 | Q62: PERIOD 10 2027 | R62: 46656 | S62: PERIOD 10 2027
A63: Highlands Ranch | B63: Highlands Ranch | C63: Best Pizza LLC | D63: Merullo | E63: Non-Founders | F63: 43010 | G63: 43011 | H63: 46684 | I63: 43093 | J63: PERIOD 11 2017 | Q63: PERIOD 11 2027 | R63: 46684 | S63: PERIOD 11 2027
A64: Decatur | B64: Decatur | C64: DAZ9 | D64: Neal Patel | E64: Non-Founders | F64: 43010 | G64: 43011 | H64: 46684 | I64: 43093 | J64: PERIOD 11 2017 | Q64: PERIOD 11 2027 | R64: 46684 | S64: PERIOD 11 2027
A65: Antioch Crossing | B65: Antioch Crossing | C65: Paceline Partners, LLC (KS/MO) | D65: Womack | E65: Non-Founders | F65: 43012 | G65: 43013 | H65: 46684 | I65: 43095 | J65: PERIOD 11 2017 | Q65: PERIOD 11 2027 | R65: 46684 | S65: PERIOD 11 2027
A66: Diamond Circle | B66: Diamond Circle | C66: Best Pizza LLC | D66: Merullo | E66: Non-Founders | F66: 43031 | G66: 43032 | H66: 46684 | I66: 43114 | J66: PERIOD 11 2017 | Q66: PERIOD 11 2027 | R66: 46684 | S66: PERIOD 11 2027
A67: Parkland | B67: Parkland | C67: Food for Thought Restaurant Group LLC | D67: Levan (BBX Capital) | E67: Non-Founders | F67: 43032 | G67: 43033 | H67: 46684 | J67: PERIOD 11 2017 | K67: PERIOD 11 2018 | M67: PERIOD 11 2019 | O67: PERIOD 11 2020 | Q67: PERIOD 11 2027 | R67: 46684 | S67: PERIOD 11 2027 | U67: Converted to CO 9/30
A68: Polaris Pointe | B68: Polaris Pointe | C68: Best Pizza LLC | D68: Merullo | E68: Non-Founders | F68: 43038 | G68: 43039 | H68: 46712 | I68: 43121 | J68: PERIOD 12 2017 | Q68: PERIOD 12 2027 | R68: 46712 | S68: PERIOD 12 2027
A69: Northfield Commons | B69: Northfield Commons | C69: Best Pizza LLC | D69: Merullo | E69: Non-Founders | F69: 43055 | G69: 43056 | H69: 46712 | I69: 43138 | J69: PERIOD 12 2017 | Q69: PERIOD 12 2027 | R69: 46712 | S69: PERIOD 12 2027
A70: Keystone | B70: Keystone | C70: Paceline Partners, LLC (OH) | D70: Womack | E70: Non-Founders | F70: 43055 | G70: 43056 | H70: 46712 | I70: 43138 | J70: PERIOD 12 2017 | Q70: PERIOD 12 2027 | R70: 46712 | S70: PERIOD 12 2027
A71: 26 & Van Dyke | B71: 26 & Van Dyke | C71: TSFR Pizza LLC | D71: Schostak | E71: Founders | F71: 43056 | G71: 43057 | H71: 46712 | J71: PERIOD 12 2017 | K71: PERIOD 12 2018 | L71: 43436 | M71: PERIOD 12 2019 | N71: 43800 | O71: PERIOD 12 2020 | P71: 44164 | Q71: PERIOD 12 2027 | R71: 46712 | S71: PERIOD 12 2027
A72: Dawsonville | B72: Dawsonville | C72: Southern Pie LLC | D72: Hill/Hayden | E72: Non-Founders | F72: 43059 | G72: 43060 | H72: 46712 | I72: 43142 | J72: PERIOD 12 2017 | Q72: PERIOD 12 2027 | R72: 46712 | S72: PERIOD 12 2027
A73: Greeley | B73: Greeley | C73: Best Pizza LLC | D73: Merullo | E73: Non-Founders | F73: 43060 | G73: 43061 | H73: 46712 | I73: 43143 | J73: PERIOD 12 2017 | Q73: PERIOD 12 2027 | R73: 46712 | S73: PERIOD 12 2027
A74: Cherry Grove | B74: Cherry Grove #10 | C74: Cool Dough Development, LLC | D74: Denning | E74: Non-Founders | F74: 43082 | G74: 43083 | H74: 46740 | I74: 43165 | J74: PERIOD 13 2017 | Q74: PERIOD 13 2027 | R74: 46740 | S74: PERIOD 13 2027
A75: Lexington | B75: Lexington | C75: Rolling Dough LLC | D75: Connolly | E75: Non-Founders | F75: 43082 | G75: 43083 | H75: 46740 | I75: 43165 | J75: PERIOD 13 2017 | Q75: PERIOD 13 2027 | R75: 46740 | S75: PERIOD 13 2027
A76: Bartram Village - OG | B76: Bartram Village - OG | C76: Food for Thought Restaurant Group LLC | D76: Levan (BBX Capital) | E76: Non-Founders | F76: 42614 | G76: 43088 | H76: 43088 | I76: 46740 | S76: 46740
A77: Sandy Springs | B77: Sandy Springs | C77: Southern Pie LLC | D77: Hill/Hayden | E77: Non-Founders | F77: 43115 | G77: 43116 | H77: 46768 | I77: 43198 | J77: PERIOD 1 2018 | Q77: PERIOD 1 2028 | R77: 46768 | S77: PERIOD 1 2028
A78: Coral Springs | B78: Coral Springs | C78: Food for Thought Restaurant Group LLC | D78: Levan (BBX Capital) | E78: Non-Founders | F78: 43137 | G78: 43138 | H78: 46796 | J78: PERIOD 2 2018 | K78: PERIOD 2 2019 | M78: PERIOD 2 2020 | O78: PERIOD 2 2021 | Q78: PERIOD 2 2028 | R78: 46796 | S78: PERIOD 2 2028 | U78: Converted to CO 9/30
A79: Indian Trail | B79: Indian Trail | C79: RTHT Investments LLC | D79: Goldman | E79: Non-Founders | F79: 43143 | G79: 43144 | H79: 46796 | J79: PERIOD 2 2018 | K79: PERIOD 2 2019 | M79: PERIOD 2 2020 | O79: PERIOD 2 2021 | Q79: PERIOD 2 2028 | R79: 46796 | S79: PERIOD 2 2028
A80: Augusta Exchange | B80: Augusta Exchange | C80: Rolling Dough LLC | D80: Connolly | E80: Non-Founders | F80: 43159 | G80: 43160 | H80: 46824 | I80: 43242 | J80: PERIOD 3 2018 | Q80: PERIOD 3 2028 | R80: 46824 | S80: PERIOD 3 2028
A81: Hall Road | B81: Hall Road | C81: TSFR Pizza LLC | D81: Schostak | E81: Non-Founders | F81: 43183 | G81: 43184 | H81: 46824 | J81: PERIOD 3 2018 | K81: PERIOD 3 2019 | M81: PERIOD 3 2020 | O81: PERIOD 3 2021 | Q81: PERIOD 3 2028 | R81: 46824 | S81: PERIOD 3 2028
A82: The Palms | B82: The Palms | C82: Food for Thought Restaurant Group LLC | D82: Levan (BBX Capital) | E82: Non-Founders | F82: 43200 | G82: 43201 | H82: 46852 | I82: 43283 | J82: PERIOD 4 2018 | Q82: PERIOD 4 2028 | R82: 46852 | S82: PERIOD 4 2028 | U82: Converted to CO 9/30
A83: West Sacramento | B83: West Sacramento | C83: Exceed Group West Sacramento | D83: Chawla | E83: Non-Founders | F83: 43213 | Q83: PERIOD 5 2028 | R83: 46880 | S83: PERIOD 5 2028
A84: Madison | B84: Madison | C84: APizza Delight Inc | D84: Patel | E84: Non-Founders | F84: 43234 | G84: 43235 | H84: 46880 | J84: PERIOD 5 2018 | K84: PERIOD 5 2019 | M84: PERIOD 5 2020 | O84: PERIOD 5 2021 | Q84: PERIOD 5 2028 | R84: 46880 | S84: PERIOD 5 2028
A85: Troy | B85: Troy | C85: TSFR Pizza LLC | D85: Schostak | E85: Non-Founders | F85: 43242 | G85: 43243 | H85: 46908 | J85: PERIOD 6 2018 | K85: PERIOD 6 2019 | M85: PERIOD 6 2020 | O85: PERIOD 6 2021 | Q85: PERIOD 6 2028 | R85: 46908 | S85: PERIOD 6 2028
A86: Food Truck | B86: Food Truck | C86: Food for Thought Restaurant Group LLC | D86: Levan (BBX Capital) | E86: Non-Founders | F86: 43252 | G86: 43253 | H86: 46908 | J86: PERIOD 6 2018 | K86: PERIOD 6 2019 | M86: PERIOD 6 2020 | O86: PERIOD 6 2021 | Q86: PERIOD 6 2028 | R86: 46908 | S86: PERIOD 6 2028 | U86: Closed
A87: Rancho Cordova | B87: Rancho Cordova | C87: Exceed Group Rancho Cordova | D87: Chawla | E87: Non-Founders | F87: 43269 | G87: 43270 | H87: 46936 | Q87: PERIOD 7 2028 | R87: 46936 | S87: PERIOD 7 2028
A88: Waverly | B88: Waverly | C88: RTHT Investments LLC | D88: Goldman | E88: Non-Founders | F88: 43276 | G88: 43277 | H88: 46936 | J88: PERIOD 7 2018 | K88: PERIOD 7 2019 | M88: PERIOD 7 2020 | O88: PERIOD 7 2021 | Q88: PERIOD 7 2028 | R88: 46936 | S88: PERIOD 7 2028
A89: Chamblee | B89: Chamblee | C89: Southern Pie LLC | D89: Hill/Hayden | E89: Non-Founders | F89: 43318 | G89: 43319 | H89: 46964 | I89: 43401 | J89: PERIOD 8 2018 | Q89: PERIOD 8 2028 | R89: 46964 | S89: PERIOD 8 2028
A90: The Standard | B90: The Standard | C90: Food for Thought Restaurant Group LLC | D90: Levan (BBX Capital) | E90: Non-Founders | F90: 43329 | G90: 43330 | H90: 46992 | I90: 43412 | J90: PERIOD 9 2018 | Q90: PERIOD 9 2028 | R90: 46992 | S90: PERIOD 9 2028 | U90: Closed 9/29
A91: Ralston Creek | B91: Ralston Creek | C91: Best Pizza LLC | D91: Merullo | E91: Non-Founders | F91: 43334 | G91: 43335 | H91: 46992 | I91: 43417 | J91: PERIOD 9 2018 | Q91: PERIOD 9 2028 | R91: 46992 | S91: PERIOD 9 2028
A92: Mooresville | B92: Mooresville | C92: RTHT Investments LLC | D92: Goldman | E92: Non-Founders | F92: 43374 | G92: 43375 | H92: 47020 | J92: PERIOD 10 2018 | K92: PERIOD 10 2019 | M92: PERIOD 10 2020 | O92: PERIOD 10 2021 | Q92: PERIOD 10 2028 | R92: 47020 | S92: PERIOD 10 2028
A93: Mobile | B93: Mobile | C93: MAA MELDI 3980 Inc | D93: Neal Patel | E93: Non-Founders | F93: 43381 | G93: 43382 | H93: 47048 | J93: PERIOD 11 2018 | K93: PERIOD 11 2019 | M93: PERIOD 11 2020 | O93: PERIOD 11 2021 | Q93: PERIOD 11 2028 | R93: 47048 | S93: PERIOD 11 2028
A94: Lutz | B94: Lutz | C94: Food for Thought Restaurant Group LLC | D94: Levan (BBX Capital) | E94: Non-Founders | F94: 43382 | G94: 43383 | H94: 47048 | I94: 43465 | J94: PERIOD 11 2018 | Q94: PERIOD 11 2028 | R94: 47048 | S94: PERIOD 11 2028 | U94: Converted to CO 9/30
A95: Georgetown | B95: Georgetown | C95: Cool Dough Development, LLC | D95: Denning | E95: Founders | F95: 43397 | G95: 43398 | H95: 47048 | J95: PERIOD 11 2018 | K95: PERIOD 11 2019 | L95: 43772 | M95: PERIOD 11 2020 | N95: 44136 | O95: PERIOD 11 2021 | P95: 44500 | Q95: PERIOD 11 2028 | R95: 47048 | S95: PERIOD 11 2028
A96: Northwestern University | B96: Northwestern University | C96: Compass Group USA, Inc. | D96: Compass/Chartwells | E96: Non-Founders | F96: 43399 | G96: 43400 | H96: 47048 | J96: PERIOD 11 2018 | K96: PERIOD 11 2019 | M96: PERIOD 11 2020 | O96: PERIOD 11 2021 | Q96: PERIOD 11 2028 | R96: 47048 | S96: PERIOD 11 2028 | U96: Billed separately
A97: Southgate | B97: Southgate | C97: TSFR Pizza LLC | D97: Schostak | E97: Non-Founders | F97: 43440 | G97: 43441 | H97: 47104 | J97: PERIOD 13 2018 | K97: PERIOD 13 2019 | M97: PERIOD 13 2020 | O97: PERIOD 13 2021 | Q97: PERIOD 13 2028 | R97: 47104 | S97: PERIOD 13 2028 | U97: Closed 9/13
A98: Pines & Hiatus | B98: Pines & Hiatus | C98: Food for Thought Restaurant Group LLC | D98: Levan (BBX Capital) | E98: Non-Founders | F98: 43445 | G98: 43446 | H98: 47104 | I98: 43465 | J98: PERIOD 13 2018 | Q98: PERIOD 13 2028 | R98: 47104 | S98: PERIOD 13 2028 | U98: Converted to CO 9/30
A99: Kalamazoo | B99: Kalamazoo | C99: TSFR Pizza LLC | D99: Schostak | E99: Non-Founders | F99: 43449 | G99: 43450 | H99: 47104 | J99: PERIOD 13 2018 | K99: PERIOD 13 2019 | M99: PERIOD 13 2020 | O99: PERIOD 13 2021 | Q99: PERIOD 13 2028 | R99: 47104 | S99: PERIOD 13 2028
A100: Vineland Pointe | B100: Vineland Pointe | C100: Food for Thought Restaurant Group LLC | D100: Levan (BBX Capital) | E100: Non-Founders | F100: 43487 | G100: =Table44[[#This Row],[Open Date]] -> 43487 | H100: 47132 | I100: 43555 | J100: PERIOD 1 2019 | Q100: PERIOD 1 2029 | R100: 47132 | S100: PERIOD 1 2029 | U100: Converted to CO 9/30
A101: Crown Point | B101: Crown Point | C101: Best Pizza LLC | D101: Merullo | E101: Non-Founders | F101: 43488 | G101: =Table44[[#This Row],[Open Date]] -> 43488 | H101: 47132 | I101: 43571 | J101: PERIOD 1 2019 | Q101: PERIOD 1 2029 | R101: 47132 | S101: PERIOD 1 2029
A102: Ballantyne | B102: Ballantyne | C102: RTHT Investments LLC | D102: Goldman | E102: Non-Founders | F102: 43515 | G102: =Table44[[#This Row],[Open Date]] -> 43515 | H102: 47160 | J102: PERIOD 2 2019 | K102: PERIOD 2 2020 | M102: PERIOD 2 2021 | O102: PERIOD 2 2022 | Q102: PERIOD 2 2029 | R102: 47160 | S102: PERIOD 2 2029
...

Sheet Food Truck Sales - To Date
A1: Date | B1: Sum of MOD # | C1: Store | D1: Gross Sales | E1: Net Sales
A2: 43252 | C2: Food Truck - Florida | D2: 331.85 | E2: 144.85
A3: 43262 | C3: Food Truck - Florida | D3: 500.56 | E3: 500.56
A4: 43263 | C4: Food Truck - Florida | D4: 650.28 | E4: 650.28
A5: 43266 | C5: Food Truck - Florida | D5: 882.2 | E5: 0
A6: 43267 | C6: Food Truck - Florida | D6: 1612.02 | E6: 1498.02
A7: 43280 | C7: Food Truck - Florida | D7: 1604 | E7: 1604
A8: 43288 | C8: Food Truck - Florida | D8: 39.64 | E8: 39.64
A9: 43302 | C9: Food Truck - Florida | D9: 607.22 | E9: 607.22
A10: 43321 | C10: Food Truck - Florida | D10: 1684.2 | E10: 1684.2
A11: 43350 | C11: Food Truck - Florida | D11: 686.55 | E11: 686.55
A12: 43351 | C12: Food Truck - Florida | D12: 718.17 | E12: 702.13
A13: 43357 | C13: Food Truck - Florida | D13: 1652.12 | E13: 1652.12
... A16: 43379 | C16: Food Truck - Florida | D16: 897.93 | E16: 897.93
A17: 43387 | B17: 504 | C17: Food Truck - Florida | D17: 495.86 | E17: 495.86
A18: 43389 | B18: 504 | C18: Food Truck - Florida | D18: 433.08 | E18: 368.12
A19: 43398 | B19: 504 | C19: Food Truck - Florida | D19: 589.29 | E19: 571.36
A20: 43399 | B20: 504 | C20: Food Truck - Florida | D20: 2147.85 | E20: 2131.81
A21: 43400 | B21: 504 | C21: Food Truck - Florida | D21: 17.77 | E21: 17.77
A22: 43407 | B22: 504 | C22: Food Truck - Florida | D22: 1956.1 | E22: 1956.1
A23: 43408 | B23: 504 | C23: Food Truck - Florida | D23: 1286.07 | E23: 1165.77
A24: 43420 | B24: 504 | C24: Food Truck - Florida | D24: 1150.74 | E24: 1150.74
A25: 43424 | B25: 504 | C25: Food Truck - Florida | D25: 667.55 | E25: 667.55
A26: 43429 | B26: 504 | C26: Food Truck - Florida | D26: 561.4 | E26: 449.12
A27: 43430 | B27: 504 | C27: Food Truck - Florida | D27: 312.78 | E27: 312.78
A28: 43432 | B28: 504 | C28: Food Truck - Florida | D28: 127.86 | E28: 79.74
... A60: 43526 | B60: 504 | C60: Food Truck - Florida | D60: 1007.93 | E60: 873.29
A61: Total | D61: =SUBTOTAL(109,Table1[Gross Sales]) -> 46717.74 | E61: =SUBTOTAL(109,Table1[Net Sales]) -> 40271.14

Sheet Calculations
C1: =IF(SUM(A5:A424)>0,"CHECK BILLING DATES","GOOD") -> GOOD | D1: Check Figures | E1: =SUM(E5:E1048576)-SUM('[1]Tableau Data'!$D:$D) -> #REF! | F1: =SUM(F5:F1048576)-SUM('[1]Tableau Data'!$E:$E) -> #REF! | L1: Check figure for # of lines | M1: =COUNTA(M5:M590)-COUNTA(D5:D590) -> 0
D2: Discrepancy should be tates creek fees as we abated them as of 10/31/22
B3: Tableau/Brink Data | G3: Calculations
B4: Date | C4: Sum of MOD # | D4: Store | E4: Column1 | F4: Column2 | G4: Location | H4: Franchisee | I4: Principal Name | J4: Marketing Fee | K4: Royalty Rate | L4: Royalty Fee | M4: Total | O4: Date | P4: # Stores | Q4: Comments
A5: =IF(Table11[[#This Row],[Date]]=0,"",IF(Table11[[#This Row],[Date]]<(Summary!$B$3-6),1,"")) | B5: 46271 | C5: 21 | D5: Park Meadows | E5: 3283.05 | F5: 3113.23 | G5: =VLOOKUP(Table11[[#This Row],[Store]],'Rates from Tracker'!A:B,2,0) -> Park Meadows | H5: =VLOOKUP(D5,'Rates from Tracker'!A:C,3,0) -> Best Pizza LLC | I5: =VLOOKUP(Table11[[#This Row],[Franchisee]],'Rates from Tracker'!C:D,2,0) -> Merullo | J5: =ROUND(IF(Table11[[#This Row],[Location]]="Belmont Market",Table11[[#This Row],[Column2]]*0.01,IF(Table11[[#This Row],[Location]]="Country Club Centre",Table11[[#This Row],[Column2]]*0.01,IF(Table11[[#This Row],[Location]]="Naval Air Station Norfolk",Table11[[#This Row],[Column2]]*0.005,F5*0.02))),2) -> 62.26 | K5: =IF(Table11[[#This Row],[Location]]="Creekwalk",0.02,IF(Table11[[#This Row],[Location]]="Country Club Centre",0.01,IF(Table11[[#This Row],[Location]]="Lenexa",0.02,IF(Table11[[#This Row],[Location]]="Belmont Market",0.02,IF(Table11[[#This Row],[Location]]="Naval Air Station Norfolk",0.02,IF(Table11[[#This Row],[Location]]="Madison",0.01,IF(Table11[[#This Row],[Location]]="Mobile",0.01,IF(Table11[[#This Row],[Location]]="Decatur",0.01,IF(Table11[[#This Row],[Location]]="Woods Cross",0.01,IF(Table11[[#This Row],[Location]]="Park City",0.01,IF(Table11[[#This Row],[Location]]="Riverdale",0.01,IF(Table11[[#This Row],[Location]]="Riverton",0.01,IF(Table11[[#This Row],[Location]]="Layton",0.01,IF(Table11[[#This Row],[Location]]="Bend",0.01,IF(Table11[[#This Row],[Location]]="Bend",0.01,IF(Table11[[#This Row],[Location]]="Oakway",0.01,IF(Table11[[#This Row],[Location]]="North Medford",0.01,IF(Table11[[#This Row],[Location]]="South Eugene",0.01,IF(Table11[[#This Row],[Location]]="American Fork",0.01,IF(Table11[[#This Row],[Location]]="Sugar House",0.01,IF(Table11[[#This Row],[Location]]="Bend North",0.01,IF(Table11[[#This Row],[Location]]="South Medford",0.01,IF(Table11[[#This Row],[Location]]="Saratoga Springs",0.01,IF(Table11[[#This Row],[Location]]="Fort Union",0.01,IF(Table11[[#This Row],[Location]]="South Jordan",0.01,IF(Table11[[#This Row],[Location]]="Grants Pass",0.01,IF(Table11[[#This Row],[Location]]="Pocatello",0.01,IF(Table11[[#This Row],[Location]]="Spanish Fork",0.01,IF(Table11[[#This Row],[Location]]="Downtown Boise",0.01,IF(Table11[[#This Row],[Location]]="Boise Town Square",0.01,IF(Table11[[#This Row],[Location]]="Ammon",0.01,IF(Table11[[#This Row],[Location]]="Roseburg",0.01,IF(Table11[[#This Row],[Location]]="Springfield-Oregon",0.01,0.05))))))))))))))))))))))))))))))))) -> 0.05 | L5: =ROUND(F5*K5,2) -> 155.66 | M5: =J5+L5 -> 217.92 | O5: 46265 | P5: =COUNTIF(B:B,O5) -> 76
A6: =IF(Table11[[#This Row],[Date]]=0,"",IF(Table11[[#This Row],[Date]]<(Summary!$B$3-6),1,"")) | B6: 46271 | C6: 47 | D6: Redding | E6: 5116.92 | F6: 4816.47 | G6: =VLOOKUP(Table11[[#This Row],[Store]],'Rates from Tracker'!A:B,2,0) -> REDDING | H6: =VLOOKUP(D6,'Rates from Tracker'!A:C,3,0) -> Exceed Group REDDING | I6: =VLOOKUP(Table11[[#This Row],[Franchisee]],'Rates from Tracker'!C:D,2,0) -> Chawla | J6: =ROUND(IF(Table11[[#This Row],[Location]]="Belmont Market",Table11[[#This Row],[Column2]]*0.01,IF(Table11[[#This Row],[Location]]="Country Club Centre",Table11[[#This Row],[Column2]]*0.01,IF(Table11[[#This Row],[Location]]="Naval Air Station Norfolk",Table11[[#This Row],[Column2]]*0.005,F6*0.02))),2) -> 96.33 | K6: =IF(Table11[[#This Row],[Location]]="Creekwalk",0.02,IF(Table11[[#This Row],[Location]]="Country Club Centre",0.01,IF(Table11[[#This Row],[Location]]="Lenexa",0.02,IF(Table11[[#This Row],[Location]]="Belmont Market",0.02,IF(Table11[[#This Row],[Location]]="Naval Air Station Norfolk",0.02,IF(Table11[[#This Row],[Location]]="Madison",0.01,IF(Table11[[#This Row],[Location]]="Mobile",0.01,IF(Table11[[#This Row],[Location]]="Decatur",0.01,IF(Table11[[#This Row],[Location]]="Woods Cross",0.01,IF(Table11[[#This Row],[Location]]="Park City",0.01,IF(Table11[[#This Row],[Location]]="Riverdale",0.01,IF(Table11[[#This Row],[Location]]="Riverton",0.01,IF(Table11[[#This Row],[Location]]="Layton",0.01,IF(Table11[[#This Row],[Location]]="Bend",0.01,IF(Table11[[#This Row],[Location]]="Bend",0.01,IF(Table11[[#This Row],[Location]]="Oakway",0.01,IF(Table11[[#This Row],[Location]]="North Medford",0.01,IF(Table11[[#This Row],[Location]]="South Eugene",0.01,IF(Table11[[#This Row],[Location]]="American Fork",0.01,IF(Table11[[#This Row],[Location]]="Sugar House",0.01,IF(Table11[[#This Row],[Location]]="Bend North",0.01,IF(Table11[[#This Row],[Location]]="South Medford",0.01,IF(Table11[[#This Row],[Location]]="Saratoga Springs",0.01,IF(Table11[[#This Row],[Location]]="Fort Union",0.01,IF(Table11[[#This Row],[Location]]="South Jordan",0.01,IF(Table11[[#This Row],[Location]]="Grants Pass",0.01,IF(Table11[[#This Row],[Location]]="Pocatello",0.01,IF(Table11[[#This Row],[Location]]="Spanish Fork",0.01,IF(Table11[[#This Row],[Location]]="Downtown Boise",0.01,IF(Table11[[#This Row],[Location]]="Boise Town Square",0.01,IF(Table11[[#This Row],[Location]]="Ammon",0.01,IF(Table11[[#This Row],[Location]]="Roseburg",0.01,IF(Table11[[#This Row],[Location]]="Springfield-Oregon",0.01,0.05))))))))))))))))))))))))))))))))) -> 0.05 | L6: =ROUND(F6*K6,2) -> 240.82 | M6: =J6+L6 -> 337.15 | O6: =O5+1 -> 46266 | P6: =COUNTIF(B:B,O6) -> 76
A7: =IF(Table11[[#This Row],[Date]]=0,"",IF(Table11[[#This Row],[Date]]<(Summary!$B$3-6),1,"")) | B7: 46271 | C7: 55 | D7: Rocklin | E7: 3552.05 | F7: 3144.19 | G7: =VLOOKUP(Table11[[#This Row],[Store]],'Rates from Tracker'!A:B,2,0) -> ROCKLIN | H7: =VLOOKUP(D7,'Rates from Tracker'!A:C,3,0) -> Exceed Group ROCKLIN | I7: =VLOOKUP(Table11[[#This Row],[Franchisee]],'Rates from Tracker'!C:D,2,0) -> Chawla | J7: =ROUND(IF(Table11[[#This Row],[Location]]="Belmont Market",Table11[[#This Row],[Column2]]*0.01,IF(Table11[[#This Row],[Location]]="Country Club Centre",Table11[[#This Row],[Column2]]*0.01,IF(Table11[[#This Row],[Location]]="Naval Air Station Norfolk",Table11[[#This Row],[Column2]]*0.005,F7*0.02))),2) -> 62.88 | K7: =IF(Table11[[#This Row],[Location]]="Creekwalk",0.02,IF(Table11[[#This Row],[Location]]="Country Club Centre",0.01,IF(Table11[[#This Row],[Location]]="Lenexa",0.02,IF(Table11[[#This Row],[Location]]="Belmont Market",0.02,IF(Table11[[#This Row],[Location]]="Naval Air Station Norfolk",0.02,IF(Table11[[#This Row],[Location]]="Madison",0.01,IF(Table11[[#This Row],[Location]]="Mobile",0.01,IF(Table11[[#This Row],[Location]]="Decatur",0.01,IF(Table11[[#This Row],[Location]]="Woods Cross",0.01,IF(Table11[[#This Row],[Location]]="Park City",0.01,IF(Table11[[#This Row],[Location]]="Riverdale",0.01,IF(Table11[[#This Row],[Location]]="Riverton",0.01,IF(Table11[[#This Row],[Location]]="Layton",0.01,IF(Table11[[#This Row],[Location]]="Bend",0.01,IF(Table11[[#This Row],[Location]]="Bend",0.01,IF(Table11[[#This Row],[Location]]="Oakway",0.01,IF(Table11[[#This Row],[Location]]="North Medford",0.01,IF(Table11[[#This Row],[Location]]="South Eugene",0.01,IF(Table11[[#This Row],[Location]]="American Fork",0.01,IF(Table11[[#This Row],[Location]]="Sugar House",0.01,IF(Table11[[#This Row],[Location]]="Bend North",0.01,IF(Table11[[#This Row],[Location]]="South Medford",0.01,IF(Table11[[#This Row],[Location]]="Saratoga Springs",0.01,IF(Table11[[#This Row],[Location]]="Fort Union",0.01,IF(Table11[[#This Row],[Location]]="South Jordan",0.01,IF(Table11[[#This Row],[Location]]="Grants Pass",0.01,IF(Table11[[#This Row],[Location]]="Pocatello",0.01,IF(Table11[[#This Row],[Location]]="Spanish Fork",0.01,IF(Table11[[#This Row],[Location]]="Downtown Boise",0.01,IF(Table11[[#This Row],[Location]]="Boise Town Square",0.01,IF(Table11[[#This Row],[Location]]="Ammon",0.01,IF(Table11[[#This Row],[Location]]="Roseburg",0.01,IF(Table11[[#This Row],[Location]]="Springfield-Oregon",0.01,0.05))))))))))))))))))))))))))))))))) -> 0.05 | L7: =ROUND(F7*K7,2) -> 157.21 | M7: =J7+L7 -> 220.09 | O7: =O6+1 -> 46267 | P7: =COUNTIF(B:B,O7) -> 76
A8: =IF(Table11[[#This Row],[Date]]=0,"",IF(Table11[[#This Row],[Date]]<(Summary!$B$3-6),1,"")) | B8: 46271 | C8: 56 | D8: Livonia | E8: 2880.02 | F8: 2726.86 | G8: =VLOOKUP(Table11[[#This Row],[Store]],'Rates from Tracker'!A:B,2,0) -> LIVONIA | H8: =VLOOKUP(D8,'Rates from Tracker'!A:C,3,0) -> TSFR Pizza LLC | I8: =VLOOKUP(Table11[[#This Row],[Franchisee]],'Rates from Tracker'!C:D,2,0) -> Schostak | J8: =ROUND(IF(Table11[[#This Row],[Location]]="Belmont Market",Table11[[#This Row],[Column2]]*0.01,IF(Table11[[#This Row],[Location]]="Country Club Centre",Table11[[#This Row],[Column2]]*0.01,IF(Table11[[#This Row],[Location]]="Naval Air Station Norfolk",Table11[[#This Row],[Column2]]*0.005,F8*0.02))),2) -> 54.54 | K8: =IF(Table11[[#This Row],[Location]]="Creekwalk",0.02,IF(Table11[[#This Row],[Location]]="Country Club Centre",0.01,IF(Table11[[#This Row],[Location]]="Lenexa",0.02,IF(Table11[[#This Row],[Location]]="Belmont Market",0.02,IF(Table11[[#This Row],[Location]]="Naval Air Station Norfolk",0.02,IF(Table11[[#This Row],[Location]]="Madison",0.01,IF(Table11[[#This Row],[Location]]="Mobile",0.01,IF(Table11[[#This Row],[Location]]="Decatur",0.01,IF(Table11[[#This Row],[Location]]="Woods Cross",0.01,IF(Table11[[#This Row],[Location]]="Park City",0.01,IF(Table11[[#This Row],[Location]]="Riverdale",0.01,IF(Table11[[#This Row],[Location]]="Riverton",0.01,IF(Table11[[#This Row],[Location]]="Layton",0.01,IF(Table11[[#This Row],[Location]]="Bend",0.01,IF(Table11[[#This Row],[Location]]="Bend",0.01,IF(Table11[[#This Row],[Location]]="Oakway",0.01,IF(Table11[[#This Row],[Location]]="North Medford",0.01,IF(Table11[[#This Row],[Location]]="South Eugene",0.01,IF(Table11[[#This Row],[Location]]="American Fork",0.01,IF(Table11[[#This Row],[Location]]="Sugar House",0.01,IF(Table11[[#This Row],[Location]]="Bend North",0.01,IF(Table11[[#This Row],[Location]]="South Medford",0.01,IF(Table11[[#This Row],[Location]]="Saratoga Springs",0.01,IF(Table11[[#This Row],[Location]]="Fort Union",0.01,IF(Table11[[#This Row],[Location]]="South Jordan",0.01,IF(Table11[[#This Row],[Location]]="Grants Pass",0.01,IF(Table11[[#This Row],[Location]]="Pocatello",0.01,IF(Table11[[#This Row],[Location]]="Spanish Fork",0.01,IF(Table11[[#This Row],[Location]]="Downtown Boise",0.01,IF(Table11[[#This Row],[Location]]="Boise Town Square",0.01,IF(Table11[[#This Row],[Location]]="Ammon",0.01,IF(Table11[[#This Row],[Location]]="Roseburg",0.01,IF(Table11[[#This Row],[Location]]="Springfield-Oregon",0.01,0.05))))))))))))))))))))))))))))))))) -> 0.05 | L8: =ROUND(F8*K8,2) -> 136.34 | M8: =J8+L8 -> 190.88 | O8: =O7+1 -> 46268 | P8: =COUNTIF(B:B,O8) -> 76
A9: =IF(Table11[[#This Row],[Date]]=0,"",IF(Table11[[#This Row],[Date]]<(Summary!$B$3-6),1,"")) | B9: 46271 | C9: 77 | D9: Falcon Landing | E9: 3632.62 | F9: 3442.4 | G9: =VLOOKUP(Table11[[#This Row],[Store]],'Rates from Tracker'!A:B,2,0) -> Falcon Landing | H9: =VLOOKUP(D9,'Rates from Tracker'!A:C,3,0) -> Best Pizza LLC | I9: =VLOOKUP(Table11[[#This Row],[Franchisee]],'Rates from Tracker'!C:D,2,0) -> Merullo | J9: =ROUND(IF(Table11[[#This Row],[Location]]="Belmont Market",Table11[[#This Row],[Column2]]*0.01,IF(Table11[[#This Row],[Location]]="Country Club Centre",Table11[[#This Row],[Column2]]*0.01,IF(Table11[[#This Row],[Location]]="Naval Air Station Norfolk",Table11[[#This Row],[Column2]]*0.005,F9*0.02))),2) -> 68.85 | K9: =IF(Table11[[#This Row],[Location]]="Creekwalk",0.02,IF(Table11[[#This Row],[Location]]="Country Club Centre",0.01,IF(Table11[[#This Row],[Location]]="Lenexa",0.02,IF(Table11[[#This Row],[Location]]="Belmont Market",0.02,IF(Table11[[#This Row],[Location]]="Naval Air Station Norfolk",0.02,IF(Table11[[#This Row],[Location]]="Madison",0.01,IF(Table11[[#This Row],[Location]]="Mobile",0.01,IF(Table11[[#This Row],[Location]]="Decatur",0.01,IF(Table11[[#This Row],[Location]]="Woods Cross",0.01,IF(Table11[[#This Row],[Location]]="Park City",0.01,IF(Table11[[#This Row],[Location]]="Riverdale",0.01,IF(Table11[[#This Row],[Location]]="Riverton",0.01,IF(Table11[[#This Row],[Location]]="Layton",0.01,IF(Table11[[#This Row],[Location]]="Bend",0.01,IF(Table11[[#This Row],[Location]]="Bend",0.01,IF(Table11[[#This Row],[Location]]="Oakway",0.01,IF(Table11[[#This Row],[Location]]="North Medford",0.01,IF(Table11[[#This Row],[Location]]="South Eugene",0.01,IF(Table11[[#This Row],[Location]]="American Fork",0.01,IF(Table11[[#This Row],[Location]]="Sugar House",0.01,IF(Table11[[#This Row],[Location]]="Bend North",0.01,IF(Table11[[#This Row],[Location]]="South Medford",0.01,IF(Table11[[#This Row],[Location]]="Saratoga Springs",0.01,IF(Table11[[#This Row],[Location]]="Fort Union",0.01,IF(Table11[[#This Row],[Location]]="South Jordan",0.01,IF(Table11[[#This Row],[Location]]="Grants Pass",0.01,IF(Table11[[#This Row],[Location]]="Pocatello",0.01,IF(Table11[[#This Row],[Location]]="Spanish Fork",0.01,IF(Table11[[#This Row],[Location]]="Downtown Boise",0.01,IF(Table11[[#This Row],[Location]]="Boise Town Square",0.01,IF(Table11[[#This Row],[Location]]="Ammon",0.01,IF(Table11[[#This Row],[Location]]="Roseburg",0.01,IF(Table11[[#This Row],[Location]]="Springfield-Oregon",0.01,0.05))))))))))))))))))))))))))))))))) -> 0.05 | L9: =ROUND(F9*K9,2) -> 172.12 | M9: =J9+L9 -> 240.97 | O9: =O8+1 -> 46269 | P9: =COUNTIF(B:B,O9) -> 76
A10: =IF(Table11[[#This Row],[Date]]=0,"",IF(Table11[[#This Row],[Date]]<(Summary!$B$3-6),1,"")) | B10: 46271 | C10: 93 | D10: Brighton | E10: 2888.65 | F10: 2752.57 | G10: =VLOOKUP(Table11[[#This Row],[Store]],'Rates from Tracker'!A:B,2,0) -> Brighton | H10: =VLOOKUP(D10,'Rates from Tracker'!A:C,3,0) -> TSFR Pizza LLC | I10: =VLOOKUP(Table11[[#This Row],[Franchisee]],'Rates from Tracker'!C:D,2,0) -> Schostak | J10: =ROUND(IF(Table11[[#This Row],[Location]]="Belmont Market",Table11[[#This Row],[Column2]]*0.01,IF(Table11[[#This Row],[Location]]="Country Club Centre",Table11[[#This Row],[Column2]]*0.01,IF(Table11[[#This Row],[Location]]="Naval Air Station Norfolk",Table11[[#This Row],[Column2]]*0.005,F10*0.02))),2) -> 55.05 | K10: =IF(Table11[[#This Row],[Location]]="Creekwalk",0.02,IF(Table11[[#This Row],[Location]]="Country Club Centre",0.01,IF(Table11[[#This Row],[Location]]="Lenexa",0.02,IF(Table11[[#This Row],[Location]]="Belmont Market",0.02,IF(Table11[[#This Row],[Location]]="Naval Air Station Norfolk",0.02,IF(Table11[[#This Row],[Location]]="Madison",0.01,IF(Table11[[#This Row],[Location]]="Mobile",0.01,IF(Table11[[#This Row],[Location]]="Decatur",0.01,IF(Table11[[#This Row],[Location]]="Woods Cross",0.01,IF(Table11[[#This Row],[Location]]="Park City",0.01,IF(Table11[[#This Row],[Location]]="Riverdale",0.01,IF(Table11[[#This Row],[Location]]="Riverton",0.01,IF(Table11[[#This Row],[Location]]="Layton",0.01,IF(Table11[[#This Row],[Location]]="Bend",0.01,IF(Table11[[#This Row],[Location]]="Bend",0.01,IF(Table11[[#This Row],[Location]]="Oakway",0.01,IF(Table11[[#This Row],[Location]]="North Medford",0.01,IF(Table11[[#This Row],[Location]]="South Eugene",0.01,IF(Table11[[#This Row],[Location]]="American Fork",0.01,IF(Table11[[#This Row],[Location]]="Sugar House",0.01,IF(Table11[[#This Row],[Location]]="Bend North",0.01,IF(Table11[[#This Row],[Location]]="South Medford",0.01,IF(Table11[[#This Row],[Location]]="Saratoga Springs",0.01,IF(Table11[[#This Row],[Location]]="Fort Union",0.01,IF(Table11[[#This Row],[Location]]="South Jordan",0.01,IF(Table11[[#This Row],[Location]]="Grants Pass",0.01,IF(Table11[[#This Row],[Location]]="Pocatello",0.01,IF(Table11[[#This Row],[Location]]="Spanish Fork",0.01,IF(Table11[[#This Row],[Location]]="Downtown Boise",0.01,IF(Table11[[#This Row],[Location]]="Boise Town Square",0.01,IF(Table11[[#This Row],[Location]]="Ammon",0.01,IF(Table11[[#This Row],[Location]]="Roseburg",0.01,IF(Table11[[#This Row],[Location]]="Springfield-Oregon",0.01,0.05))))))))))))))))))))))))))))))))) -> 0.05 | L10: =ROUND(F10*K10,2) -> 137.63 | M10: =J10+L10 -> 192.68 | O10: =O9+1 -> 46270 | P10: =COUNTIF(B:B,O10) -> 76
A11: =IF(Table11[[#This Row],[Date]]=0,"",IF(Table11[[#This Row],[Date]]<(Summary!$B$3-6),1,"")) | B11: 46271 | C11: 94 | D11: Castle Rock | E11: 5324.11 | F11: 5025.38 | G11: =VLOOKUP(Table11[[#This Row],[Store]],'Rates from Tracker'!A:B,2,0) -> Castle Rock | H11: =VLOOKUP(D11,'Rates from Tracker'!A:C,3,0) -> Best Pizza LLC | I11: =VLOOKUP(Table11[[#This Row],[Franchisee]],'Rates from Tracker'!C:D,2,0) -> Merullo | J11: =ROUND(IF(Table11[[#This Row],[Location]]="Belmont Market",Table11[[#This Row],[Column2]]*0.01,IF(Table11[[#This Row],[Location]]="Country Club Centre",Table11[[#This Row],[Column2]]*0.01,IF(Table11[[#This Row],[Location]]="Naval Air Station Norfolk",Table11[[#This Row],[Column2]]*0.005,F11*0.02))),2) -> 100.51 | K11: =IF(Table11[[#This Row],[Location]]="Creekwalk",0.02,IF(Table11[[#This Row],[Location]]="Country Club Centre",0.01,IF(Table11[[#This Row],[Location]]="Lenexa",0.02,IF(Table11[[#This Row],[Location]]="Belmont Market",0.02,IF(Table11[[#This Row],[Location]]="Naval Air Station Norfolk",0.02,IF(Table11[[#This Row],[Location]]="Madison",0.01,IF(Table11[[#This Row],[Location]]="Mobile",0.01,IF(Table11[[#This Row],[Location]]="Decatur",0.01,IF(Table11[[#This Row],[Location]]="Woods Cross",0.01,IF(Table11[[#This Row],[Location]]="Park City",0.01,IF(Table11[[#This Row],[Location]]="Riverdale",0.01,IF(Table11[[#This Row],[Location]]="Riverton",0.01,IF(Table11[[#This Row],[Location]]="Layton",0.01,IF(Table11[[#This Row],[Location]]="Bend",0.01,IF(Table11[[#This Row],[Location]]="Bend",0.01,IF(Table11[[#This Row],[Location]]="Oakway",0.01,IF(Table11[[#This Row],[Location]]="North Medford",0.01,IF(Table11[[#This Row],[Location]]="South Eugene",0.01,IF(Table11[[#This Row],[Location]]="American Fork",0.01,IF(Table11[[#This Row],[Location]]="Sugar House",0.01,IF(Table11[[#This Row],[Location]]="Bend North",0.01,IF(Table11[[#This Row],[Location]]="South Medford",0.01,IF(Table11[[#This Row],[Location]]="Saratoga Springs",0.01,IF(Table11[[#This Row],[Location]]="Fort Union",0.01,IF(Table11[[#This Row],[Location]]="South Jordan",0.01,IF(Table11[[#This Row],[Location]]="Grants Pass",0.01,IF(Table11[[#This Row],[Location]]="Pocatello",0.01,IF(Table11[[#This Row],[Location]]="Spanish Fork",0.01,IF(Table11[[#This Row],[Location]]="Downtown Boise",0.01,IF(Table11[[#This Row],[Location]]="Boise Town Square",0.01,IF(Table11[[#This Row],[Location]]="Ammon",0.01,IF(Table11[[#This Row],[Location]]="Roseburg",0.01,IF(Table11[[#This Row],[Location]]="Springfield-Oregon",0.01,0.05))))))))))))))))))))))))))))))))) -> 0.05 | L11: =ROUND(F11*K11,2) -> 251.27 | M11: =J11+L11 -> 351.78 | O11: =O10+1 -> 46271 | P11: =COUNTIF(B:B,O11) -> 76
A12: =IF(Table11[[#This Row],[Date]]=0,"",IF(Table11[[#This Row],[Date]]<(Summary!$B$3-6),1,"")) | B12: 46271 | C12: 100 | D12: Howe Bout Arden | E12: 5082.85 | F12: 4745.48 | G12: =VLOOKUP(Table11[[#This Row],[Store]],'Rates from Tracker'!A:B,2,0) -> Howe Bout Arden | H12: =VLOOKUP(D12,'Rates from Tracker'!A:C,3,0) -> Exceed Group Howe Bout Arden | I12: =VLOOKUP(Table11[[#This Row],[Franchisee]],'Rates from Tracker'!C:D,2,0) -> Chawla | J12: =ROUND(IF(Table11[[#This Row],[Location]]="Belmont Market",Table11[[#This Row],[Column2]]*0.01,IF(Table11[[#This Row],[Location]]="Country Club Centre",Table11[[#This Row],[Column2]]*0.01,IF(Table11[[#This Row],[Location]]="Naval Air Station Norfolk",Table11[[#This Row],[Column2]]*0.005,F12*0.02))),2) -> 94.91 | K12: =IF(Table11[[#This Row],[Location]]="Creekwalk",0.02,IF(Table11[[#This Row],[Location]]="Country Club Centre",0.01,IF(Table11[[#This Row],[Location]]="Lenexa",0.02,IF(Table11[[#This Row],[Location]]="Belmont Market",0.02,IF(Table11[[#This Row],[Location]]="Naval Air Station Norfolk",0.02,IF(Table11[[#This Row],[Location]]="Madison",0.01,IF(Table11[[#This Row],[Location]]="Mobile",0.01,IF(Table11[[#This Row],[Location]]="Decatur",0.01,IF(Table11[[#This Row],[Location]]="Woods Cross",0.01,IF(Table11[[#This Row],[Location]]="Park City",0.01,IF(Table11[[#This Row],[Location]]="Riverdale",0.01,IF(Table11[[#This Row],[Location]]="Riverton",0.01,IF(Table11[[#This Row],[Location]]="Layton",0.01,IF(Table11[[#This Row],[Location]]="Bend",0.01,IF(Table11[[#This Row],[Location]]="Bend",0.01,IF(Table11[[#This Row],[Location]]="Oakway",0.01,IF(Table11[[#This Row],[Location]]="North Medford",0.01,IF(Table11[[#This Row],[Location]]="South Eugene",0.01,IF(Table11[[#This Row],[Location]]="American Fork",0.01,IF(Table11[[#This Row],[Location]]="Sugar House",0.01,IF(Table11[[#This Row],[Location]]="Bend North",0.01,IF(Table11[[#This Row],[Location]]="South Medford",0.01,IF(Table11[[#This Row],[Location]]="Saratoga Springs",0.01,IF(Table11[[#This Row],[Location]]="Fort Union",0.01,IF(Table11[[#This Row],[Location]]="South Jordan",0.01,IF(Table11[[#This Row],[Location]]="Grants Pass",0.01,IF(Table11[[#This Row],[Location]]="Pocatello",0.01,IF(Table11[[#This Row],[Location]]="Spanish Fork",0.01,IF(Table11[[#This Row],[Location]]="Downtown Boise",0.01,IF(Table11[[#This Row],[Location]]="Boise Town Square",0.01,IF(Table11[[#This Row],[Location]]="Ammon",0.01,IF(Table11[[#This Row],[Location]]="Roseburg",0.01,IF(Table11[[#This Row],[Location]]="Springfield-Oregon",0.01,0.05))))))))))))))))))))))))))))))))) -> 0.05 | L12: =ROUND(F12*K12,2) -> 237.27 | M12: =J12+L12 -> 332.18
A13: =IF(Table11[[#This Row],[Date]]=0,"",IF(Table11[[#This Row],[Date]]<(Summary!$B$3-6),1,"")) | B13: 46271 | C13: 126 | D13: Bend | E13: 3182.31 | F13: 2931.76 | G13: =VLOOKUP(Table11[[#This Row],[Store]],'Rates from Tracker'!A:B,2,0) -> Bend | H13: =VLOOKUP(D13,'Rates from Tracker'!A:C,3,0) -> SSR Holdings LLC | I13: =VLOOKUP(Table11[[#This Row],[Franchisee]],'Rates from Tracker'!C:D,2,0) -> Bikram | J13: =ROUND(IF(Table11[[#This Row],[Location]]="Belmont Market",Table11[[#This Row],[Column2]]*0.01,IF(Table11[[#This Row],[Location]]="Country Club Centre",Table11[[#This Row],[Column2]]*0.01,IF(Table11[[#This Row],[Location]]="Naval Air Station Norfolk",Table11[[#This Row],[Column2]]*0.005,F13*0.02))),2) -> 58.64 | K13: =IF(Table11[[#This Row],[Location]]="Creekwalk",0.02,IF(Table11[[#This Row],[Location]]="Country Club Centre",0.01,IF(Table11[[#This Row],[Location]]="Lenexa",0.02,IF(Table11[[#This Row],[Location]]="Belmont Market",0.02,IF(Table11[[#This Row],[Location]]="Naval Air Station Norfolk",0.02,IF(Table11[[#This Row],[Location]]="Madison",0.01,IF(Table11[[#This Row],[Location]]="Mobile",0.01,IF(Table11[[#This Row],[Location]]="Decatur",0.01,IF(Table11[[#This Row],[Location]]="Woods Cross",0.01,IF(Table11[[#This Row],[Location]]="Park City",0.01,IF(Table11[[#This Row],[Location]]="Riverdale",0.01,IF(Table11[[#This Row],[Location]]="Riverton",0.01,IF(Table11[[#This Row],[Location]]="Layton",0.01,IF(Table11[[#This Row],[Location]]="Bend",0.01,IF(Table11[[#This Row],[Location]]="Bend",0.01,IF(Table11[[#This Row],[Location]]="Oakway",0.01,IF(Table11[[#This Row],[Location]]="North Medford",0.01,IF(Table11[[#This Row],[Location]]="South Eugene",0.01,IF(Table11[[#This Row],[Location]]="American Fork",0.01,IF(Table11[[#This Row],[Location]]="Sugar House",0.01,IF(Table11[[#This Row],[Location]]="Bend North",0.01,IF(Table11[[#This Row],[Location]]="South Medford",0.01,IF(Table11[[#This Row],[Location]]="Saratoga Springs",0.01,IF(Table11[[#This Row],[Location]]="Fort Union",0.01,IF(Table11[[#This Row],[Location]]="South Jordan",0.01,IF(Table11[[#This Row],[Location]]="Grants Pass",0.01,IF(Table11[[#This Row],[Location]]="Pocatello",0.01,IF(Table11[[#This Row],[Location]]="Spanish Fork",0.01,IF(Table11[[#This Row],[Location]]="Downtown Boise",0.01,IF(Table11[[#This Row],[Location]]="Boise Town Square",0.01,IF(Table11[[#This Row],[Location]]="Ammon",0.01,IF(Table11[[#This Row],[Location]]="Roseburg",0.01,IF(Table11[[#This Row],[Location]]="Springfield-Oregon",0.01,0.05))))))))))))))))))))))))))))))))) -> 0.01 | L13: =ROUND(F13*K13,2) -> 29.32 | M13: =J13+L13 -> 87.96
A14: =IF(Table11[[#This Row],[Date]]=0,"",IF(Table11[[#This Row],[Date]]<(Summary!$B$3-6),1,"")) | B14: 46271 | C14: 133 | D14: Woodhill | E14: 3183.93 | F14: 3013.15 | G14: =VLOOKUP(Table11[[#This Row],[Store]],'Rates from Tracker'!A:B,2,0) -> Woodhill | H14: =VLOOKUP(D14,'Rates from Tracker'!A:C,3,0) -> Rolling Dough LLC | I14: =VLOOKUP(Table11[[#This Row],[Franchisee]],'Rates from Tracker'!C:D,2,0) -> Connolly | J14: =ROUND(IF(Table11[[#This Row],[Location]]="Belmont Market",Table11[[#This Row],[Column2]]*0.01,IF(Table11[[#This Row],[Location]]="Country Club Centre",Table11[[#This Row],[Column2]]*0.01,IF(Table11[[#This Row],[Location]]="Naval Air Station Norfolk",Table11[[#This Row],[Column2]]*0.005,F14*0.02))),2) -> 60.26 | K14: =IF(Table11[[#This Row],[Location]]="Creekwalk",0.02,IF(Table11[[#This Row],[Location]]="Country Club Centre",0.01,IF(Table11[[#This Row],[Location]]="Lenexa",0.02,IF(Table11[[#This Row],[Location]]="Belmont Market",0.02,IF(Table11[[#This Row],[Location]]="Naval Air Station Norfolk",0.02,IF(Table11[[#This Row],[Location]]="Madison",0.01,IF(Table11[[#This Row],[Location]]="Mobile",0.01,IF(Table11[[#This Row],[Location]]="Decatur",0.01,IF(Table11[[#This Row],[Location]]="Woods Cross",0.01,IF(Table11[[#This Row],[Location]]="Park City",0.01,IF(Table11[[#This Row],[Location]]="Riverdale",0.01,IF(Table11[[#This Row],[Location]]="Riverton",0.01,IF(Table11[[#This Row],[Location]]="Layton",0.01,IF(Table11[[#This Row],[Location]]="Bend",0.01,IF(Table11[[#This Row],[Location]]="Bend",0.01,IF(Table11[[#This Row],[Location]]="Oakway",0.01,IF(Table11[[#This Row],[Location]]="North Medford",0.01,IF(Table11[[#This Row],[Location]]="South Eugene",0.01,IF(Table11[[#This Row],[Location]]="American Fork",0.01,IF(Table11[[#This Row],[Location]]="Sugar House",0.01,IF(Table11[[#This Row],[Location]]="Bend North",0.01,IF(Table11[[#This Row],[Location]]="South Medford",0.01,IF(Table11[[#This Row],[Location]]="Saratoga Springs",0.01,IF(Table11[[#This Row],[Location]]="Fort Union",0.01,IF(Table11[[#This Row],[Location]]="South Jordan",0.01,IF(Table11[[#This Row],[Location]]="Grants Pass",0.01,IF(Table11[[#This Row],[Location]]="Pocatello",0.01,IF(Table11[[#This Row],[Location]]="Spanish Fork",0.01,IF(Table11[[#This Row],[Location]]="Downtown Boise",0.01,IF(Table11[[#This Row],[Location]]="Boise Town Square",0.01,IF(Table11[[#This Row],[Location]]="Ammon",0.01,IF(Table11[[#This Row],[Location]]="Roseburg",0.01,IF(Table11[[#This Row],[Location]]="Springfield-Oregon",0.01,0.05))))))))))))))))))))))))))))))))) -> 0.05 | L14: =ROUND(F14*K14,2) -> 150.66 | M14: =J14+L14 -> 210.92
A15: =IF(Table11[[#This Row],[Date]]=0,"",IF(Table11[[#This Row],[Date]]<(Summary!$B$3-6),1,"")) | B15: 46271 | C15: 149 | D15: Westwood Plaza | E15: 3048.46 | F15: 2802.61 | G15: =VLOOKUP(Table11[[#This Row],[Store]],'Rates from Tracker'!A:B,2,0) -> Westwood Plaza | H15: =VLOOKUP(D15,'Rates from Tracker'!A:C,3,0) -> Rolling Dough LLC | I15: =VLOOKUP(Table11[[#This Row],[Franchisee]],'Rates from Tracker'!C:D,2,0) -> Connolly | J15: =ROUND(IF(Table11[[#This Row],[Location]]="Belmont Market",Table11[[#This Row],[Column2]]*0.01,IF(Table11[[#This Row],[Location]]="Country Club Centre",Table11[[#This Row],[Column2]]*0.01,IF(Table11[[#This Row],[Location]]="Naval Air Station Norfolk",Table11[[#This Row],[Column2]]*0.005,F15*0.02))),2) -> 56.05 | K15: =IF(Table11[[#This Row],[Location]]="Creekwalk",0.02,IF(Table11[[#This Row],[Location]]="Country Club Centre",0.01,IF(Table11[[#This Row],[Location]]="Lenexa",0.02,IF(Table11[[#This Row],[Location]]="Belmont Market",0.02,IF(Table11[[#This Row],[Location]]="Naval Air Station Norfolk",0.02,IF(Table11[[#This Row],[Location]]="Madison",0.01,IF(Table11[[#This Row],[Location]]="Mobile",0.01,IF(Table11[[#This Row],[Location]]="Decatur",0.01,IF(Table11[[#This Row],[Location]]="Woods Cross",0.01,IF(Table11[[#This Row],[Location]]="Park City",0.01,IF(Table11[[#This Row],[Location]]="Riverdale",0.01,IF(Table11[[#This Row],[Location]]="Riverton",0.01,IF(Table11[[#This Row],[Location]]="Layton",0.01,IF(Table11[[#This Row],[Location]]="Bend",0.01,IF(Table11[[#This Row],[Location]]="Bend",0.01,IF(Table11[[#This Row],[Location]]="Oakway",0.01,IF(Table11[[#This Row],[Location]]="North Medford",0.01,IF(Table11[[#This Row],[Location]]="South Eugene",0.01,IF(Table11[[#This Row],[Location]]="American Fork",0.01,IF(Table11[[#This Row],[Location]]="Sugar House",0.01,IF(Table11[[#This Row],[Location]]="Bend North",0.01,IF(Table11[[#This Row],[Location]]="South Medford",0.01,IF(Table11[[#This Row],[Location]]="Saratoga Springs",0.01,IF(Table11[[#This Row],[Location]]="Fort Union",0.01,IF(Table11[[#This Row],[Location]]="South Jordan",0.01,IF(Table11[[#This Row],[Location]]="Grants Pass",0.01,IF(Table11[[#This Row],[Location]]="Pocatello",0.01,IF(Table11[[#This Row],[Location]]="Spanish Fork",0.01,IF(Table11[[#This Row],[Location]]="Downtown Boise",0.01,IF(Table11[[#This Row],[Location]]="Boise Town Square",0.01,IF(Table11[[#This Row],[Location]]="Ammon",0.01,IF(Table11[[#This Row],[Location]]="Roseburg",0.01,IF(Table11[[#This Row],[Location]]="Springfield-Oregon",0.01,0.05))))))))))))))))))))))))))))))))) -> 0.05 | L15: =ROUND(F15*K15,2) -> 140.13 | M15: =J15+L15 -> 196.18
A16: =IF(Table11[[#This Row],[Date]]=0,"",IF(Table11[[#This Row],[Date]]<(Summary!$B$3-6),1,"")) | B16: 46271 | C16: 157 | D16: Hamburg | E16: 3925.65 | F16: 3795 | G16: =VLOOKUP(Table11[[#This Row],[Store]],'Rates from Tracker'!A:B,2,0) -> Hamburg #6 | H16: =VLOOKUP(D16,'Rates from Tracker'!A:C,3,0) -> Cool Dough Development, LLC | I16: =VLOOKUP(Table11[[#This Row],[Franchisee]],'Rates from Tracker'!C:D,2,0) -> Denning | J16: =ROUND(IF(Table11[[#This Row],[Location]]="Belmont Market",Table11[[#This Row],[Column2]]*0.01,IF(Table11[[#This Row],[Location]]="Country Club Centre",Table11[[#This Row],[Column2]]*0.01,IF(Table11[[#This Row],[Location]]="Naval Air Station Norfolk",Table11[[#This Row],[Column2]]*0.005,F16*0.02))),2) -> 75.9 | K16: =IF(Table11[[#This Row],[Location]]="Creekwalk",0.02,IF(Table11[[#This Row],[Location]]="Country Club Centre",0.01,IF(Table11[[#This Row],[Location]]="Lenexa",0.02,IF(Table11[[#This Row],[Location]]="Belmont Market",0.02,IF(Table11[[#This Row],[Location]]="Naval Air Station Norfolk",0.02,IF(Table11[[#This Row],[Location]]="Madison",0.01,IF(Table11[[#This Row],[Location]]="Mobile",0.01,IF(Table11[[#This Row],[Location]]="Decatur",0.01,IF(Table11[[#This Row],[Location]]="Woods Cross",0.01,IF(Table11[[#This Row],[Location]]="Park City",0.01,IF(Table11[[#This Row],[Location]]="Riverdale",0.01,IF(Table11[[#This Row],[Location]]="Riverton",0.01,IF(Table11[[#This Row],[Location]]="Layton",0.01,IF(Table11[[#This Row],[Location]]="Bend",0.01,IF(Table11[[#This Row],[Location]]="Bend",0.01,IF(Table11[[#This Row],[Location]]="Oakway",0.01,IF(Table11[[#This Row],[Location]]="North Medford",0.01,IF(Table11[[#This Row],[Location]]="South Eugene",0.01,IF(Table11[[#This Row],[Location]]="American Fork",0.01,IF(Table11[[#This Row],[Location]]="Sugar House",0.01,IF(Table11[[#This Row],[Location]]="Bend North",0.01,IF(Table11[[#This Row],[Location]]="South Medford",0.01,IF(Table11[[#This Row],[Location]]="Saratoga Springs",0.01,IF(Table11[[#This Row],[Location]]="Fort Union",0.01,IF(Table11[[#This Row],[Location]]="South Jordan",0.01,IF(Table11[[#This Row],[Location]]="Grants Pass",0.01,IF(Table11[[#This Row],[Location]]="Pocatello",0.01,IF(Table11[[#This Row],[Location]]="Spanish Fork",0.01,IF(Table11[[#This Row],[Location]]="Downtown Boise",0.01,IF(Table11[[#This Row],[Location]]="Boise Town Square",0.01,IF(Table11[[#This Row],[Location]]="Ammon",0.01,IF(Table11[[#This Row],[Location]]="Roseburg",0.01,IF(Table11[[#This Row],[Location]]="Springfield-Oregon",0.01,0.05))))))))))))))))))))))))))))))))) -> 0.05 | L16: =ROUND(F16*K16,2) -> 189.75 | M16: =J16+L16 -> 265.65
A17: =IF(Table11[[#This Row],[Date]]=0,"",IF(Table11[[#This Row],[Date]]<(Summary!$B$3-6),1,"")) | B17: 46271 | C17: 158 | D17: McCaslin Marketplace | E17: 3471.46 | F17: 3287.16 | G17: =VLOOKUP(Table11[[#This Row],[Store]],'Rates from Tracker'!A:B,2,0) -> McCaslin Marketplace | H17: =VLOOKUP(D17,'Rates from Tracker'!A:C,3,0) -> Best Pizza LLC | I17: =VLOOKUP(Table11[[#This Row],[Franchisee]],'Rates from Tracker'!C:D,2,0) -> Merullo | J17: =ROUND(IF(Table11[[#This Row],[Location]]="Belmont Market",Table11[[#This Row],[Column2]]*0.01,IF(Table11[[#This Row],[Location]]="Country Club Centre",Table11[[#This Row],[Column2]]*0.01,IF(Table11[[#This Row],[Location]]="Naval Air Station Norfolk",Table11[[#This Row],[Column2]]*0.005,F17*0.02))),2) -> 65.74 | K17: =IF(Table11[[#This Row],[Location]]="Creekwalk",0.02,IF(Table11[[#This Row],[Location]]="Country Club Centre",0.01,IF(Table11[[#This Row],[Location]]="Lenexa",0.02,IF(Table11[[#This Row],[Location]]="Belmont Market",0.02,IF(Table11[[#This Row],[Location]]="Naval Air Station Norfolk",0.02,IF(Table11[[#This Row],[Location]]="Madison",0.01,IF(Table11[[#This Row],[Location]]="Mobile",0.01,IF(Table11[[#This Row],[Location]]="Decatur",0.01,IF(Table11[[#This Row],[Location]]="Woods Cross",0.01,IF(Table11[[#This Row],[Location]]="Park City",0.01,IF(Table11[[#This Row],[Location]]="Riverdale",0.01,IF(Table11[[#This Row],[Location]]="Riverton",0.01,IF(Table11[[#This Row],[Location]]="Layton",0.01,IF(Table11[[#This Row],[Location]]="Bend",0.01,IF(Table11[[#This Row],[Location]]="Bend",0.01,IF(Table11[[#This Row],[Location]]="Oakway",0.01,IF(Table11[[#This Row],[Location]]="North Medford",0.01,IF(Table11[[#This Row],[Location]]="South Eugene",0.01,IF(Table11[[#This Row],[Location]]="American Fork",0.01,IF(Table11[[#This Row],[Location]]="Sugar House",0.01,IF(Table11[[#This Row],[Location]]="Bend North",0.01,IF(Table11[[#This Row],[Location]]="South Medford",0.01,IF(Table11[[#This Row],[Location]]="Saratoga Springs",0.01,IF(Table11[[#This Row],[Location]]="Fort Union",0.01,IF(Table11[[#This Row],[Location]]="South Jordan",0.01,IF(Table11[[#This Row],[Location]]="Grants Pass",0.01,IF(Table11[[#This Row],[Location]]="Pocatello",0.01,IF(Table11[[#This Row],[Location]]="Spanish Fork",0.01,IF(Table11[[#This Row],[Location]]="Downtown Boise",0.01,IF(Table11[[#This Row],[Location]]="Boise Town Square",0.01,IF(Table11[[#This Row],[Location]]="Ammon",0.01,IF(Table11[[#This Row],[Location]]="Roseburg",0.01,IF(Table11[[#This Row],[Location]]="Springfield-Oregon",0.01,0.05))))))))))))))))))))))))))))))))) -> 0.05 | L17: =ROUND(F17*K17,2) -> 164.36 | M17: =J17+L17 -> 230.1
A18: =IF(Table11[[#This Row],[Date]]=0,"",IF(Table11[[#This Row],[Date]]<(Summary!$B$3-6),1,"")) | B18: 46271 | C18: 159 | D18: North Charleston | E18: 2076.13 | F18: 1861.01 | G18: =VLOOKUP(Table11[[#This Row],[Store]],'Rates from Tracker'!A:B,2,0) -> North Charleston | H18: =VLOOKUP(D18,'Rates from Tracker'!A:C,3,0) -> Rolling Dough LLC | I18: =VLOOKUP(Table11[[#This Row],[Franchisee]],'Rates from Tracker'!C:D,2,0) -> Connolly | J18: =ROUND(IF(Table11[[#This Row],[Location]]="Belmont Market",Table11[[#This Row],[Column2]]*0.01,IF(Table11[[#This Row],[Location]]="Country Club Centre",Table11[[#This Row],[Column2]]*0.01,IF(Table11[[#This Row],[Location]]="Naval Air Station Norfolk",Table11[[#This Row],[Column2]]*0.005,F18*0.02))),2) -> 37.22 | K18: =IF(Table11[[#This Row],[Location]]="Creekwalk",0.02,IF(Table11[[#This Row],[Location]]="Country Club Centre",0.01,IF(Table11[[#This Row],[Location]]="Lenexa",0.02,IF(Table11[[#This Row],[Location]]="Belmont Market",0.02,IF(Table11[[#This Row],[Location]]="Naval Air Station Norfolk",0.02,IF(Table11[[#This Row],[Location]]="Madison",0.01,IF(Table11[[#This Row],[Location]]="Mobile",0.01,IF(Table11[[#This Row],[Location]]="Decatur",0.01,IF(Table11[[#This Row],[Location]]="Woods Cross",0.01,IF(Table11[[#This Row],[Location]]="Park City",0.01,IF(Table11[[#This Row],[Location]]="Riverdale",0.01,IF(Table11[[#This Row],[Location]]="Riverton",0.01,IF(Table11[[#This Row],[Location]]="Layton",0.01,IF(Table11[[#This Row],[Location]]="Bend",0.01,IF(Table11[[#This Row],[Location]]="Bend",0.01,IF(Table11[[#This Row],[Location]]="Oakway",0.01,IF(Table11[[#This Row],[Location]]="North Medford",0.01,IF(Table11[[#This Row],[Location]]="South Eugene",0.01,IF(Table11[[#This Row],[Location]]="American Fork",0.01,IF(Table11[[#This Row],[Location]]="Sugar House",0.01,IF(Table11[[#This Row],[Location]]="Bend North",0.01,IF(Table11[[#This Row],[Location]]="South Medford",0.01,IF(Table11[[#This Row],[Location]]="Saratoga Springs",0.01,IF(Table11[[#This Row],[Location]]="Fort Union",0.01,IF(Table11[[#This Row],[Location]]="South Jordan",0.01,IF(Table11[[#This Row],[Location]]="Grants Pass",0.01,IF(Table11[[#This Row],[Location]]="Pocatello",0.01,IF(Table11[[#This Row],[Location]]="Spanish Fork",0.01,IF(Table11[[#This Row],[Location]]="Downtown Boise",0.01,IF(Table11[[#This Row],[Location]]="Boise Town Square",0.01,IF(Table11[[#This Row],[Location]]="Ammon",0.01,IF(Table11[[#This Row],[Location]]="Roseburg",0.01,IF(Table11[[#This Row],[Location]]="Springfield-Oregon",0.01,0.05))))))))))))))))))))))))))))))))) -> 0.05 | L18: =ROUND(F18*K18,2) -> 93.05 | M18: =J18+L18 -> 130.27
A19: =IF(Table11[[#This Row],[Date]]=0,"",IF(Table11[[#This Row],[Date]]<(Summary!$B$3-6),1,"")) | B19: 46271 | C19: 161 | D19: Chico | E19: 4851.83 | F19: 4503.28 | G19: =VLOOKUP(Table11[[#This Row],[Store]],'Rates from Tracker'!A:B,2,0) -> Chico | H19: =VLOOKUP(D19,'Rates from Tracker'!A:C,3,0) -> Exceed Group Chico | I19: =VLOOKUP(Table11[[#This Row],[Franchisee]],'Rates from Tracker'!C:D,2,0) -> Chawla | J19: =ROUND(IF(Table11[[#This Row],[Location]]="Belmont Market",Table11[[#This Row],[Column2]]*0.01,IF(Table11[[#This Row],[Location]]="Country Club Centre",Table11[[#This Row],[Column2]]*0.01,IF(Table11[[#This Row],[Location]]="Naval Air Station Norfolk",Table11[[#This Row],[Column2]]*0.005,F19*0.02))),2) -> 90.07 | K19: =IF(Table11[[#This Row],[Location]]="Creekwalk",0.02,IF(Table11[[#This Row],[Location]]="Country Club Centre",0.01,IF(Table11[[#This Row],[Location]]="Lenexa",0.02,IF(Table11[[#This Row],[Location]]="Belmont Market",0.02,IF(Table11[[#This Row],[Location]]="Naval Air Station Norfolk",0.02,IF(Table11[[#This Row],[Location]]="Madison",0.01,IF(Table11[[#This Row],[Location]]="Mobile",0.01,IF(Table11[[#This Row],[Location]]="Decatur",0.01,IF(Table11[[#This Row],[Location]]="Woods Cross",0.01,IF(Table11[[#This Row],[Location]]="Park City",0.01,IF(Table11[[#This Row],[Location]]="Riverdale",0.01,IF(Table11[[#This Row],[Location]]="Riverton",0.01,IF(Table11[[#This Row],[Location]]="Layton",0.01,IF(Table11[[#This Row],[Location]]="Bend",0.01,IF(Table11[[#This Row],[Location]]="Bend",0.01,IF(Table11[[#This Row],[Location]]="Oakway",0.01,IF(Table11[[#This Row],[Location]]="North Medford",0.01,IF(Table11[[#This Row],[Location]]="South Eugene",0.01,IF(Table11[[#This Row],[Location]]="American Fork",0.01,IF(Table11[[#This Row],[Location]]="Sugar House",0.01,IF(Table11[[#This Row],[Location]]="Bend North",0.01,IF(Table11[[#This Row],[Location]]="South Medford",0.01,IF(Table11[[#This Row],[Location]]="Saratoga Springs",0.01,IF(Table11[[#This Row],[Location]]="Fort Union",0.01,IF(Table11[[#This Row],[Location]]="South Jordan",0.01,IF(Table11[[#This Row],[Location]]="Grants Pass",0.01,IF(Table11[[#This Row],[Location]]="Pocatello",0.01,IF(Table11[[#This Row],[Location]]="Spanish Fork",0.01,IF(Table11[[#This Row],[Location]]="Downtown Boise",0.01,IF(Table11[[#This Row],[Location]]="Boise Town Square",0.01,IF(Table11[[#This Row],[Location]]="Ammon",0.01,IF(Table11[[#This Row],[Location]]="Roseburg",0.01,IF(Table11[[#This Row],[Location]]="Springfield-Oregon",0.01,0.05))))))))))))))))))))))))))))))))) -> 0.05 | L19: =ROUND(F19*K19,2) -> 225.16 | M19: =J19+L19 -> 315.23
A20: =IF(Table11[[#This Row],[Date]]=0,"",IF(Table11[[#This Row],[Date]]<(Summary!$B$3-6),1,"")) | B20: 46271 | C20: 163 | D20: Forest Trace | E20: 4862.07 | F20: 4406.8 | G20: =VLOOKUP(Table11[[#This Row],[Store]],'Rates from Tracker'!A:B,2,0) -> Forest Trace | H20: =VLOOKUP(D20,'Rates from Tracker'!A:C,3,0) -> Best Pizza LLC | I20: =VLOOKUP(Table11[[#This Row],[Franchisee]],'Rates from Tracker'!C:D,2,0) -> Merullo | J20: =ROUND(IF(Table11[[#This Row],[Location]]="Belmont Market",Table11[[#This Row],[Column2]]*0.01,IF(Table11[[#This Row],[Location]]="Country Club Centre",Table11[[#This Row],[Column2]]*0.01,IF(Table11[[#This Row],[Location]]="Naval Air Station Norfolk",Table11[[#This Row],[Column2]]*0.005,F20*0.02))),2) -> 88.14 | K20: =IF(Table11[[#This Row],[Location]]="Creekwalk",0.02,IF(Table11[[#This Row],[Location]]="Country Club Centre",0.01,IF(Table11[[#This Row],[Location]]="Lenexa",0.02,IF(Table11[[#This Row],[Location]]="Belmont Market",0.02,IF(Table11[[#This Row],[Location]]="Naval Air Station Norfolk",0.02,IF(Table11[[#This Row],[Location]]="Madison",0.01,IF(Table11[[#This Row],[Location]]="Mobile",0.01,IF(Table11[[#This Row],[Location]]="Decatur",0.01,IF(Table11[[#This Row],[Location]]="Woods Cross",0.01,IF(Table11[[#This Row],[Location]]="Park City",0.01,IF(Table11[[#This Row],[Location]]="Riverdale",0.01,IF(Table11[[#This Row],[Location]]="Riverton",0.01,IF(Table11[[#This Row],[Location]]="Layton",0.01,IF(Table11[[#This Row],[Location]]="Bend",0.01,IF(Table11[[#This Row],[Location]]="Bend",0.01,IF(Table11[[#This Row],[Location]]="Oakway",0.01,IF(Table11[[#This Row],[Location]]="North Medford",0.01,IF(Table11[[#This Row],[Location]]="South Eugene",0.01,IF(Table11[[#This Row],[Location]]="American Fork",0.01,IF(Table11[[#This Row],[Location]]="Sugar House",0.01,IF(Table11[[#This Row],[Location]]="Bend North",0.01,IF(Table11[[#This Row],[Location]]="South Medford",0.01,IF(Table11[[#This Row],[Location]]="Saratoga Springs",0.01,IF(Table11[[#This Row],[Location]]="Fort Union",0.01,IF(Table11[[#This Row],[Location]]="South Jordan",0.01,IF(Table11[[#This Row],[Location]]="Grants Pass",0.01,IF(Table11[[#This Row],[Location]]="Pocatello",0.01,IF(Table11[[#This Row],[Location]]="Spanish Fork",0.01,IF(Table11[[#This Row],[Location]]="Downtown Boise",0.01,IF(Table11[[#This Row],[Location]]="Boise Town Square",0.01,IF(Table11[[#This Row],[Location]]="Ammon",0.01,IF(Table11[[#This Row],[Location]]="Roseburg",0.01,IF(Table11[[#This Row],[Location]]="Springfield-Oregon",0.01,0.05))))))))))))))))))))))))))))))))) -> 0.05 | L20: =ROUND(F20*K20,2) -> 220.34 | M20: =J20+L20 -> 308.48
A21: =IF(Table11[[#This Row],[Date]]=0,"",IF(Table11[[#This Row],[Date]]<(Summary!$B$3-6),1,"")) | B21: 46271 | C21: 166 | D21: Centre Avenue | E21: 3286.23 | F21: 3005.73 | G21: =VLOOKUP(Table11[[#This Row],[Store]],'Rates from Tracker'!A:B,2,0) -> Centre Avenue | H21: =VLOOKUP(D21,'Rates from Tracker'!A:C,3,0) -> Best Pizza LLC | I21: =VLOOKUP(Table11[[#This Row],[Franchisee]],'Rates from Tracker'!C:D,2,0) -> Merullo | J21: =ROUND(IF(Table11[[#This Row],[Location]]="Belmont Market",Table11[[#This Row],[Column2]]*0.01,IF(Table11[[#This Row],[Location]]="Country Club Centre",Table11[[#This Row],[Column2]]*0.01,IF(Table11[[#This Row],[Location]]="Naval Air Station Norfolk",Table11[[#This Row],[Column2]]*0.005,F21*0.02))),2) -> 60.11 | K21: =IF(Table11[[#This Row],[Location]]="Creekwalk",0.02,IF(Table11[[#This Row],[Location]]="Country Club Centre",0.01,IF(Table11[[#This Row],[Location]]="Lenexa",0.02,IF(Table11[[#This Row],[Location]]="Belmont Market",0.02,IF(Table11[[#This Row],[Location]]="Naval Air Station Norfolk",0.02,IF(Table11[[#This Row],[Location]]="Madison",0.01,IF(Table11[[#This Row],[Location]]="Mobile",0.01,IF(Table11[[#This Row],[Location]]="Decatur",0.01,IF(Table11[[#This Row],[Location]]="Woods Cross",0.01,IF(Table11[[#This Row],[Location]]="Park City",0.01,IF(Table11[[#This Row],[Location]]="Riverdale",0.01,IF(Table11[[#This Row],[Location]]="Riverton",0.01,IF(Table11[[#This Row],[Location]]="Layton",0.01,IF(Table11[[#This Row],[Location]]="Bend",0.01,IF(Table11[[#This Row],[Location]]="Bend",0.01,IF(Table11[[#This Row],[Location]]="Oakway",0.01,IF(Table11[[#This Row],[Location]]="North Medford",0.01,IF(Table11[[#This Row],[Location]]="South Eugene",0.01,IF(Table11[[#This Row],[Location]]="American Fork",0.01,IF(Table11[[#This Row],[Location]]="Sugar House",0.01,IF(Table11[[#This Row],[Location]]="Bend North",0.01,IF(Table11[[#This Row],[Location]]="South Medford",0.01,IF(Table11[[#This Row],[Location]]="Saratoga Springs",0.01,IF(Table11[[#This Row],[Location]]="Fort Union",0.01,IF(Table11[[#This Row],[Location]]="South Jordan",0.01,IF(Table11[[#This Row],[Location]]="Grants Pass",0.01,IF(Table11[[#This Row],[Location]]="Pocatello",0.01,IF(Table11[[#This Row],[Location]]="Spanish Fork",0.01,IF(Table11[[#This Row],[Location]]="Downtown Boise",0.01,IF(Table11[[#This Row],[Location]]="Boise Town Square",0.01,IF(Table11[[#This Row],[Location]]="Ammon",0.01,IF(Table11[[#This Row],[Location]]="Roseburg",0.01,IF(Table11[[#This Row],[Location]]="Springfield-Oregon",0.01,0.05))))))))))))))))))))))))))))))))) -> 0.05 | L21: =ROUND(F21*K21,2) -> 150.29 | M21: =J21+L21 -> 210.4
A22: =IF(Table11[[#This Row],[Date]]=0,"",IF(Table11[[#This Row],[Date]]<(Summary!$B$3-6),1,"")) | B22: 46271 | C22: 172 | D22: Oakway | E22: 3945.29 | F22: 3768.29 | G22: =VLOOKUP(Table11[[#This Row],[Store]],'Rates from Tracker'!A:B,2,0) -> Oakway | H22: =VLOOKUP(D22,'Rates from Tracker'!A:C,3,0) -> SSR Holdings LLC | I22: =VLOOKUP(Table11[[#This Row],[Franchisee]],'Rates from Tracker'!C:D,2,0) -> Bikram | J22: =ROUND(IF(Table11[[#This Row],[Location]]="Belmont Market",Table11[[#This Row],[Column2]]*0.01,IF(Table11[[#This Row],[Location]]="Country Club Centre",Table11[[#This Row],[Column2]]*0.01,IF(Table11[[#This Row],[Location]]="Naval Air Station Norfolk",Table11[[#This Row],[Column2]]*0.005,F22*0.02))),2) -> 75.37 | K22: =IF(Table11[[#This Row],[Location]]="Creekwalk",0.02,IF(Table11[[#This Row],[Location]]="Country Club Centre",0.01,IF(Table11[[#This Row],[Location]]="Lenexa",0.02,IF(Table11[[#This Row],[Location]]="Belmont Market",0.02,IF(Table11[[#This Row],[Location]]="Naval Air Station Norfolk",0.02,IF(Table11[[#This Row],[Location]]="Madison",0.01,IF(Table11[[#This Row],[Location]]="Mobile",0.01,IF(Table11[[#This Row],[Location]]="Decatur",0.01,IF(Table11[[#This Row],[Location]]="Woods Cross",0.01,IF(Table11[[#This Row],[Location]]="Park City",0.01,IF(Table11[[#This Row],[Location]]="Riverdale",0.01,IF(Table11[[#This Row],[Location]]="Riverton",0.01,IF(Table11[[#This Row],[Location]]="Layton",0.01,IF(Table11[[#This Row],[Location]]="Bend",0.01,IF(Table11[[#This Row],[Location]]="Bend",0.01,IF(Table11[[#This Row],[Location]]="Oakway",0.01,IF(Table11[[#This Row],[Location]]="North Medford",0.01,IF(Table11[[#This Row],[Location]]="South Eugene",0.01,IF(Table11[[#This Row],[Location]]="American Fork",0.01,IF(Table11[[#This Row],[Location]]="Sugar House",0.01,IF(Table11[[#This Row],[Location]]="Bend North",0.01,IF(Table11[[#This Row],[Location]]="South Medford",0.01,IF(Table11[[#This Row],[Location]]="Saratoga Springs",0.01,IF(Table11[[#This Row],[Location]]="Fort Union",0.01,IF(Table11[[#This Row],[Location]]="South Jordan",0.01,IF(Table11[[#This Row],[Location]]="Grants Pass",0.01,IF(Table11[[#This Row],[Location]]="Pocatello",0.01,IF(Table11[[#This Row],[Location]]="Spanish Fork",0.01,IF(Table11[[#This Row],[Location]]="Downtown Boise",0.01,IF(Table11[[#This Row],[Location]]="Boise Town Square",0.01,IF(Table11[[#This Row],[Location]]="Ammon",0.01,IF(Table11[[#This Row],[Location]]="Roseburg",0.01,IF(Table11[[#This Row],[Location]]="Springfield-Oregon",0.01,0.05))))))))))))))))))))))))))))))))) -> 0.01 | L22: =ROUND(F22*K22,2) -> 37.68 | M22: =J22+L22 -> 113.05
A23: =IF(Table11[[#This Row],[Date]]=0,"",IF(Table11[[#This Row],[Date]]<(Summary!$B$3-6),1,"")) | B23: 46271 | C23: 204 | D23: North Medford | E23: 4109.29 | F23: 3814.91 | G23: =VLOOKUP(Table11[[#This Row],[Store]],'Rates from Tracker'!A:B,2,0) -> North Medford | H23: =VLOOKUP(D23,'Rates from Tracker'!A:C,3,0) -> SSR Holdings LLC | I23: =VLOOKUP(Table11[[#This Row],[Franchisee]],'Rates from Tracker'!C:D,2,0) -> Bikram | J23: =ROUND(IF(Table11[[#This Row],[Location]]="Belmont Market",Table11[[#This Row],[Column2]]*0.01,IF(Table11[[#This Row],[Location]]="Country Club Centre",Table11[[#This Row],[Column2]]*0.01,IF(Table11[[#This Row],[Location]]="Naval Air Station Norfolk",Table11[[#This Row],[Column2]]*0.005,F23*0.02))),2) -> 76.3 | K23: =IF(Table11[[#This Row],[Location]]="Creekwalk",0.02,IF(Table11[[#This Row],[Location]]="Country Club Centre",0.01,IF(Table11[[#This Row],[Location]]="Lenexa",0.02,IF(Table11[[#This Row],[Location]]="Belmont Market",0.02,IF(Table11[[#This Row],[Location]]="Naval Air Station Norfolk",0.02,IF(Table11[[#This Row],[Location]]="Madison",0.01,IF(Table11[[#This Row],[Location]]="Mobile",0.01,IF(Table11[[#This Row],[Location]]="Decatur",0.01,IF(Table11[[#This Row],[Location]]="Woods Cross",0.01,IF(Table11[[#This Row],[Location]]="Park City",0.01,IF(Table11[[#This Row],[Location]]="Riverdale",0.01,IF(Table11[[#This Row],[Location]]="Riverton",0.01,IF(Table11[[#This Row],[Location]]="Layton",0.01,IF(Table11[[#This Row],[Location]]="Bend",0.01,IF(Table11[[#This Row],[Location]]="Bend",0.01,IF(Table11[[#This Row],[Location]]="Oakway",0.01,IF(Table11[[#This Row],[Location]]="North Medford",0.01,IF(Table11[[#This Row],[Location]]="South Eugene",0.01,IF(Table11[[#This Row],[Location]]="American Fork",0.01,IF(Table11[[#This Row],[Location]]="Sugar House",0.01,IF(Table11[[#This Row],[Location]]="Bend North",0.01,IF(Table11[[#This Row],[Location]]="South Medford",0.01,IF(Table11[[#This Row],[Location]]="Saratoga Springs",0.01,IF(Table11[[#This Row],[Location]]="Fort Union",0.01,IF(Table11[[#This Row],[Location]]="South Jordan",0.01,IF(Table11[[#This Row],[Location]]="Grants Pass",0.01,IF(Table11[[#This Row],[Location]]="Pocatello",0.01,IF(Table11[[#This Row],[Location]]="Spanish Fork",0.01,IF(Table11[[#This Row],[Location]]="Downtown Boise",0.01,IF(Table11[[#This Row],[Location]]="Boise Town Square",0.01,IF(Table11[[#This Row],[Location]]="Ammon",0.01,IF(Table11[[#This Row],[Location]]="Roseburg",0.01,IF(Table11[[#This Row],[Location]]="Springfield-Oregon",0.01,0.05))))))))))))))))))))))))))))))))) -> 0.01 | L23: =ROUND(F23*K23,2) -> 38.15 | M23: =J23+L23 -> 114.45
... A429: =IF(Table11[[#This Row],[Date]]=0,"",IF(Table11[[#This Row],[Date]]<(Summary!$B$3-6),1,"")) | B429: 46266 | C429: 334 | D429: Layton | E429: 1636.01 | F429: 1620.33 | G429: =VLOOKUP(Table11[[#This Row],[Store]],'Rates from Tracker'!A:B,2,0) -> Layton | H429: =VLOOKUP(D429,'Rates from Tracker'!A:C,3,0) -> SSR Holdings LLC | I429: =VLOOKUP(Table11[[#This Row],[Franchisee]],'Rates from Tracker'!C:D,2,0) -> Bikram | J429: =ROUND(IF(Table11[[#This Row],[Location]]="Belmont Market",Table11[[#This Row],[Column2]]*0.01,IF(Table11[[#This Row],[Location]]="Country Club Centre",Table11[[#This Row],[Column2]]*0.01,IF(Table11[[#This Row],[Location]]="Naval Air Station Norfolk",Table11[[#This Row],[Column2]]*0.005,F429*0.02))),2) -> 32.41 | K429: =IF(Table11[[#This Row],[Location]]="Creekwalk",0.02,IF(Table11[[#This Row],[Location]]="Country Club Centre",0.01,IF(Table11[[#This Row],[Location]]="Lenexa",0.02,IF(Table11[[#This Row],[Location]]="Belmont Market",0.02,IF(Table11[[#This Row],[Location]]="Naval Air Station Norfolk",0.02,IF(Table11[[#This Row],[Location]]="Madison",0.01,IF(Table11[[#This Row],[Location]]="Mobile",0.01,IF(Table11[[#This Row],[Location]]="Decatur",0.01,IF(Table11[[#This Row],[Location]]="Woods Cross",0.01,IF(Table11[[#This Row],[Location]]="Park City",0.01,IF(Table11[[#This Row],[Location]]="Riverdale",0.01,IF(Table11[[#This Row],[Location]]="Riverton",0.01,IF(Table11[[#This Row],[Location]]="Layton",0.01,IF(Table11[[#This Row],[Location]]="Bend",0.01,IF(Table11[[#This Row],[Location]]="Bend",0.01,IF(Table11[[#This Row],[Location]]="Oakway",0.01,IF(Table11[[#This Row],[Location]]="North Medford",0.01,IF(Table11[[#This Row],[Location]]="South Eugene",0.01,IF(Table11[[#This Row],[Location]]="American Fork",0.01,IF(Table11[[#This Row],[Location]]="Sugar House",0.01,IF(Table11[[#This Row],[Location]]="Bend North",0.01,IF(Table11[[#This Row],[Location]]="South Medford",0.01,IF(Table11[[#This Row],[Location]]="Saratoga Springs",0.01,IF(Table11[[#This Row],[Location]]="Fort Union",0.01,IF(Table11[[#This Row],[Location]]="South Jordan",0.01,IF(Table11[[#This Row],[Location]]="Grants Pass",0.01,IF(Table11[[#This Row],[Location]]="Pocatello",0.01,IF(Table11[[#This Row],[Location]]="Spanish Fork",0.01,IF(Table11[[#This Row],[Location]]="Downtown Boise",0.01,IF(Table11[[#This Row],[Location]]="Boise Town Square",0.01,IF(Table11[[#This Row],[Location]]="Ammon",0.01,IF(Table11[[#This Row],[Location]]="Roseburg",0.01,IF(Table11[[#This Row],[Location]]="Springfield-Oregon",0.01,0.05))))))))))))))))))))))))))))))))) -> 0.01 | L429: =ROUND(F429*K429,2) -> 16.2 | M429: =J429+L429 -> 48.61
B430: 46266 | C430: 338 | D430: Augusta Exchange | E430: 2521.23 | F430: 2353.85 | G430: =VLOOKUP(Table11[[#This Row],[Store]],'Rates from Tracker'!A:B,2,0) -> Augusta Exchange | H430: =VLOOKUP(D430,'Rates from Tracker'!A:C,3,0) -> Rolling Dough LLC | I430: =VLOOKUP(Table11[[#This Row],[Franchisee]],'Rates from Tracker'!C:D,2,0) -> Connolly | J430: =ROUND(IF(Table11[[#This Row],[Location]]="Belmont Market",Table11[[#This Row],[Column2]]*0.01,IF(Table11[[#This Row],[Location]]="Country Club Centre",Table11[[#This Row],[Column2]]*0.01,IF(Table11[[#This Row],[Location]]="Naval Air Station Norfolk",Table11[[#This Row],[Column2]]*0.005,F430*0.02))),2) -> 47.08 | K430: =IF(Table11[[#This Row],[Location]]="Creekwalk",0.02,IF(Table11[[#This Row],[Location]]="Country Club Centre",0.01,IF(Table11[[#This Row],[Location]]="Lenexa",0.02,IF(Table11[[#This Row],[Location]]="Belmont Market",0.02,IF(Table11[[#This Row],[Location]]="Naval Air Station Norfolk",0.02,IF(Table11[[#This Row],[Location]]="Madison",0.01,IF(Table11[[#This Row],[Location]]="Mobile",0.01,IF(Table11[[#This Row],[Location]]="Decatur",0.01,IF(Table11[[#This Row],[Location]]="Woods Cross",0.01,IF(Table11[[#This Row],[Location]]="Park City",0.01,IF(Table11[[#This Row],[Location]]="Riverdale",0.01,IF(Table11[[#This Row],[Location]]="Riverton",0.01,IF(Table11[[#This Row],[Location]]="Layton",0.01,IF(Table11[[#This Row],[Location]]="Bend",0.01,IF(Table11[[#This Row],[Location]]="Bend",0.01,IF(Table11[[#This Row],[Location]]="Oakway",0.01,IF(Table11[[#This Row],[Location]]="North Medford",0.01,IF(Table11[[#This Row],[Location]]="South Eugene",0.01,IF(Table11[[#This Row],[Location]]="American Fork",0.01,IF(Table11[[#This Row],[Location]]="Sugar House",0.01,IF(Table11[[#This Row],[Location]]="Bend North",0.01,IF(Table11[[#This Row],[Location]]="South Medford",0.01,IF(Table11[[#This Row],[Location]]="Saratoga Springs",0.01,IF(Table11[[#This Row],[Location]]="Fort Union",0.01,IF(Table11[[#This Row],[Location]]="South Jordan",0.01,IF(Table11[[#This Row],[Location]]="Grants Pass",0.01,IF(Table11[[#This Row],[Location]]="Pocatello",0.01,IF(Table11[[#This Row],[Location]]="Spanish Fork",0.01,IF(Table11[[#This Row],[Location]]="Downtown Boise",0.01,IF(Table11[[#This Row],[Location]]="Boise Town Square",0.01,IF(Table11[[#This Row],[Location]]="Ammon",0.01,IF(Table11[[#This Row],[Location]]="Roseburg",0.01,IF(Table11[[#This Row],[Location]]="Springfield-Oregon",0.01,0.05))))))))))))))))))))))))))))))))) -> 0.05 | L430: =ROUND(F430*K430,2) -> 117.69 | M430: =J430+L430 -> 164.77
B431: 46266 | C431: 348 | D431: Bend North | E431: 3121.21 | F431: 3047.96 | G431: =VLOOKUP(Table11[[#This Row],[Store]],'Rates from Tracker'!A:B,2,0) -> Bend North | H431: =VLOOKUP(D431,'Rates from Tracker'!A:C,3,0) -> SSR Holdings LLC | I431: =VLOOKUP(Table11[[#This Row],[Franchisee]],'Rates from Tracker'!C:D,2,0) -> Bikram | J431: =ROUND(IF(Table11[[#This Row],[Location]]="Belmont Market",Table11[[#This Row],[Column2]]*0.01,IF(Table11[[#This Row],[Location]]="Country Club Centre",Table11[[#This Row],[Column2]]*0.01,IF(Table11[[#This Row],[Location]]="Naval Air Station Norfolk",Table11[[#This Row],[Column2]]*0.005,F431*0.02))),2) -> 60.96 | K431: =IF(Table11[[#This Row],[Location]]="Creekwalk",0.02,IF(Table11[[#This Row],[Location]]="Country Club Centre",0.01,IF(Table11[[#This Row],[Location]]="Lenexa",0.02,IF(Table11[[#This Row],[Location]]="Belmont Market",0.02,IF(Table11[[#This Row],[Location]]="Naval Air Station Norfolk",0.02,IF(Table11[[#This Row],[Location]]="Madison",0.01,IF(Table11[[#This Row],[Location]]="Mobile",0.01,IF(Table11[[#This Row],[Location]]="Decatur",0.01,IF(Table11[[#This Row],[Location]]="Woods Cross",0.01,IF(Table11[[#This Row],[Location]]="Park City",0.01,IF(Table11[[#This Row],[Location]]="Riverdale",0.01,IF(Table11[[#This Row],[Location]]="Riverton",0.01,IF(Table11[[#This Row],[Location]]="Layton",0.01,IF(Table11[[#This Row],[Location]]="Bend",0.01,IF(Table11[[#This Row],[Location]]="Bend",0.01,IF(Table11[[#This Row],[Location]]="Oakway",0.01,IF(Table11[[#This Row],[Location]]="North Medford",0.01,IF(Table11[[#This Row],[Location]]="South Eugene",0.01,IF(Table11[[#This Row],[Location]]="American Fork",0.01,IF(Table11[[#This Row],[Location]]="Sugar House",0.01,IF(Table11[[#This Row],[Location]]="Bend North",0.01,IF(Table11[[#This Row],[Location]]="South Medford",0.01,IF(Table11[[#This Row],[Location]]="Saratoga Springs",0.01,IF(Table11[[#This Row],[Location]]="Fort Union",0.01,IF(Table11[[#This Row],[Location]]="South Jordan",0.01,IF(Table11[[#This Row],[Location]]="Grants Pass",0.01,IF(Table11[[#This Row],[Location]]="Pocatello",0.01,IF(Table11[[#This Row],[Location]]="Spanish Fork",0.01,IF(Table11[[#This Row],[Location]]="Downtown Boise",0.01,IF(Table11[[#This Row],[Location]]="Boise Town Square",0.01,IF(Table11[[#This Row],[Location]]="Ammon",0.01,IF(Table11[[#This Row],[Location]]="Roseburg",0.01,IF(Table11[[#This Row],[Location]]="Springfield-Oregon",0.01,0.05))))))))))))))))))))))))))))))))) -> 0.01 | L431: =ROUND(F431*K431,2) -> 30.48 | M431: =J431+L431 -> 91.44
B432: 46266 | C432: 349 | D432: South Medford | E432: 2198.73 | F432: 2145.9 | G432: =VLOOKUP(Table11[[#This Row],[Store]],'Rates from Tracker'!A:B,2,0) -> South Medford | H432: =VLOOKUP(D432,'Rates from Tracker'!A:C,3,0) -> SSR Holdings LLC | I432: =VLOOKUP(Table11[[#This Row],[Franchisee]],'Rates from Tracker'!C:D,2,0) -> Bikram | J432: =ROUND(IF(Table11[[#This Row],[Location]]="Belmont Market",Table11[[#This Row],[Column2]]*0.01,IF(Table11[[#This Row],[Location]]="Country Club Centre",Table11[[#This Row],[Column2]]*0.01,IF(Table11[[#This Row],[Location]]="Naval Air Station Norfolk",Table11[[#This Row],[Column2]]*0.005,F432*0.02))),2) -> 42.92 | K432: =IF(Table11[[#This Row],[Location]]="Creekwalk",0.02,IF(Table11[[#This Row],[Location]]="Country Club Centre",0.01,IF(Table11[[#This Row],[Location]]="Lenexa",0.02,IF(Table11[[#This Row],[Location]]="Belmont Market",0.02,IF(Table11[[#This Row],[Location]]="Naval Air Station Norfolk",0.02,IF(Table11[[#This Row],[Location]]="Madison",0.01,IF(Table11[[#This Row],[Location]]="Mobile",0.01,IF(Table11[[#This Row],[Location]]="Decatur",0.01,IF(Table11[[#This Row],[Location]]="Woods Cross",0.01,IF(Table11[[#This Row],[Location]]="Park City",0.01,IF(Table11[[#This Row],[Location]]="Riverdale",0.01,IF(Table11[[#This Row],[Location]]="Riverton",0.01,IF(Table11[[#This Row],[Location]]="Layton",0.01,IF(Table11[[#This Row],[Location]]="Bend",0.01,IF(Table11[[#This Row],[Location]]="Bend",0.01,IF(Table11[[#This Row],[Location]]="Oakway",0.01,IF(Table11[[#This Row],[Location]]="North Medford",0.01,IF(Table11[[#This Row],[Location]]="South Eugene",0.01,IF(Table11[[#This Row],[Location]]="American Fork",0.01,IF(Table11[[#This Row],[Location]]="Sugar House",0.01,IF(Table11[[#This Row],[Location]]="Bend North",0.01,IF(Table11[[#This Row],[Location]]="South Medford",0.01,IF(Table11[[#This Row],[Location]]="Saratoga Springs",0.01,IF(Table11[[#This Row],[Location]]="Fort Union",0.01,IF(Table11[[#This Row],[Location]]="South Jordan",0.01,IF(Table11[[#This Row],[Location]]="Grants Pass",0.01,IF(Table11[[#This Row],[Location]]="Pocatello",0.01,IF(Table11[[#This Row],[Location]]="Spanish Fork",0.01,IF(Table11[[#This Row],[Location]]="Downtown Boise",0.01,IF(Table11[[#This Row],[Location]]="Boise Town Square",0.01,IF(Table11[[#This Row],[Location]]="Ammon",0.01,IF(Table11[[#This Row],[Location]]="Roseburg",0.01,IF(Table11[[#This Row],[Location]]="Springfield-Oregon",0.01,0.05))))))))))))))))))))))))))))))))) -> 0.01 | L432: =ROUND(F432*K432,2) -> 21.46 | M432: =J432+L432 -> 64.38
B433: 46266 | C433: 352 | D433: Georgetown | E433: 1606.25 | F433: 1438.84 | G433: =VLOOKUP(Table11[[#This Row],[Store]],'Rates from Tracker'!A:B,2,0) -> Georgetown | H433: =VLOOKUP(D433,'Rates from Tracker'!A:C,3,0) -> Cool Dough Development, LLC | I433: =VLOOKUP(Table11[[#This Row],[Franchisee]],'Rates from Tracker'!C:D,2,0) -> Denning | J433: =ROUND(IF(Table11[[#This Row],[Location]]="Belmont Market",Table11[[#This Row],[Column2]]*0.01,IF(Table11[[#This Row],[Location]]="Country Club Centre",Table11[[#This Row],[Column2]]*0.01,IF(Table11[[#This Row],[Location]]="Naval Air Station Norfolk",Table11[[#This Row],[Column2]]*0.005,F433*0.02))),2) -> 28.78 | K433: =IF(Table11[[#This Row],[Location]]="Creekwalk",0.02,IF(Table11[[#This Row],[Location]]="Country Club Centre",0.01,IF(Table11[[#This Row],[Location]]="Lenexa",0.02,IF(Table11[[#This Row],[Location]]="Belmont Market",0.02,IF(Table11[[#This Row],[Location]]="Naval Air Station Norfolk",0.02,IF(Table11[[#This Row],[Location]]="Madison",0.01,IF(Table11[[#This Row],[Location]]="Mobile",0.01,IF(Table11[[#This Row],[Location]]="Decatur",0.01,IF(Table11[[#This Row],[Location]]="Woods Cross",0.01,IF(Table11[[#This Row],[Location]]="Park City",0.01,IF(Table11[[#This Row],[Location]]="Riverdale",0.01,IF(Table11[[#This Row],[Location]]="Riverton",0.01,IF(Table11[[#This Row],[Location]]="Layton",0.01,IF(Table11[[#This Row],[Location]]="Bend",0.01,IF(Table11[[#This Row],[Location]]="Bend",0.01,IF(Table11[[#This Row],[Location]]="Oakway",0.01,IF(Table11[[#This Row],[Location]]="North Medford",0.01,IF(Table11[[#This Row],[Location]]="South Eugene",0.01,IF(Table11[[#This Row],[Location]]="American Fork",0.01,IF(Table11[[#This Row],[Location]]="Sugar House",0.01,IF(Table11[[#This Row],[Location]]="Bend North",0.01,IF(Table11[[#This Row],[Location]]="South Medford",0.01,IF(Table11[[#This Row],[Location]]="Saratoga Springs",0.01,IF(Table11[[#This Row],[Location]]="Fort Union",0.01,IF(Table11[[#This Row],[Location]]="South Jordan",0.01,IF(Table11[[#This Row],[Location]]="Grants Pass",0.01,IF(Table11[[#This Row],[Location]]="Pocatello",0.01,IF(Table11[[#This Row],[Location]]="Spanish Fork",0.01,IF(Table11[[#This Row],[Location]]="Downtown Boise",0.01,IF(Table11[[#This Row],[Location]]="Boise Town Square",0.01,IF(Table11[[#This Row],[Location]]="Ammon",0.01,IF(Table11[[#This Row],[Location]]="Roseburg",0.01,IF(Table11[[#This Row],[Location]]="Springfield-Oregon",0.01,0.05))))))))))))))))))))))))))))))))) -> 0.05 | L433: =ROUND(F433*K433,2) -> 71.94 | M433: =J433+L433 -> 100.72
B434: 46266 | C434: 366 | D434: Saratoga Springs | E434: 2039.51 | F434: 2013.26 | G434: =VLOOKUP(Table11[[#This Row],[Store]],'Rates from Tracker'!A:B,2,0) -> Saratoga Springs | H434: =VLOOKUP(D434,'Rates from Tracker'!A:C,3,0) -> SSR Holdings LLC | I434: =VLOOKUP(Table11[[#This Row],[Franchisee]],'Rates from Tracker'!C:D,2,0) -> Bikram | J434: =ROUND(IF(Table11[[#This Row],[Location]]="Belmont Market",Table11[[#This Row],[Column2]]*0.01,IF(Table11[[#This Row],[Location]]="Country Club Centre",Table11[[#This Row],[Column2]]*0.01,IF(Table11[[#This Row],[Location]]="Naval Air Station Norfolk",Table11[[#This Row],[Column2]]*0.005,F434*0.02))),2) -> 40.27 | K434: =IF(Table11[[#This Row],[Location]]="Creekwalk",0.02,IF(Table11[[#This Row],[Location]]="Country Club Centre",0.01,IF(Table11[[#This Row],[Location]]="Lenexa",0.02,IF(Table11[[#This Row],[Location]]="Belmont Market",0.02,IF(Table11[[#This Row],[Location]]="Naval Air Station Norfolk",0.02,IF(Table11[[#This Row],[Location]]="Madison",0.01,IF(Table11[[#This Row],[Location]]="Mobile",0.01,IF(Table11[[#This Row],[Location]]="Decatur",0.01,IF(Table11[[#This Row],[Location]]="Woods Cross",0.01,IF(Table11[[#This Row],[Location]]="Park City",0.01,IF(Table11[[#This Row],[Location]]="Riverdale",0.01,IF(Table11[[#This Row],[Location]]="Riverton",0.01,IF(Table11[[#This Row],[Location]]="Layton",0.01,IF(Table11[[#This Row],[Location]]="Bend",0.01,IF(Table11[[#This Row],[Location]]="Bend",0.01,IF(Table11[[#This Row],[Location]]="Oakway",0.01,IF(Table11[[#This Row],[Location]]="North Medford",0.01,IF(Table11[[#This Row],[Location]]="South Eugene",0.01,IF(Table11[[#This Row],[Location]]="American Fork",0.01,IF(Table11[[#This Row],[Location]]="Sugar House",0.01,IF(Table11[[#This Row],[Location]]="Bend North",0.01,IF(Table11[[#This Row],[Location]]="South Medford",0.01,IF(Table11[[#This Row],[Location]]="Saratoga Springs",0.01,IF(Table11[[#This Row],[Location]]="Fort Union",0.01,IF(Table11[[#This Row],[Location]]="South Jordan",0.01,IF(Table11[[#This Row],[Location]]="Grants Pass",0.01,IF(Table11[[#This Row],[Location]]="Pocatello",0.01,IF(Table11[[#This Row],[Location]]="Spanish Fork",0.01,IF(Table11[[#This Row],[Location]]="Downtown Boise",0.01,IF(Table11[[#This Row],[Location]]="Boise Town Square",0.01,IF(Table11[[#This Row],[Location]]="Ammon",0.01,IF(Table11[[#This Row],[Location]]="Roseburg",0.01,IF(Table11[[#This Row],[Location]]="Springfield-Oregon",0.01,0.05))))))))))))))))))))))))))))))))) -> 0.01 | L434: =ROUND(F434*K434,2) -> 20.13 | M434: =J434+L434 -> 60.4
B435: 46266 | C435: 384 | D435: Ralston Creek | E435: 2930.66 | F435: 2846.37 | G435: =VLOOKUP(Table11[[#This Row],[Store]],'Rates from Tracker'!A:B,2,0) -> Ralston Creek | H435: =VLOOKUP(D435,'Rates from Tracker'!A:C,3,0) -> Best Pizza LLC | I435: =VLOOKUP(Table11[[#This Row],[Franchisee]],'Rates from Tracker'!C:D,2,0) -> Merullo | J435: =ROUND(IF(Table11[[#This Row],[Location]]="Belmont Market",Table11[[#This Row],[Column2]]*0.01,IF(Table11[[#This Row],[Location]]="Country Club Centre",Table11[[#This Row],[Column2]]*0.01,IF(Table11[[#This Row],[Location]]="Naval Air Station Norfolk",Table11[[#This Row],[Column2]]*0.005,F435*0.02))),2) -> 56.93 | K435: =IF(Table11[[#This Row],[Location]]="Creekwalk",0.02,IF(Table11[[#This Row],[Location]]="Country Club Centre",0.01,IF(Table11[[#This Row],[Location]]="Lenexa",0.02,IF(Table11[[#This Row],[Location]]="Belmont Market",0.02,IF(Table11[[#This Row],[Location]]="Naval Air Station Norfolk",0.02,IF(Table11[[#This Row],[Location]]="Madison",0.01,IF(Table11[[#This Row],[Location]]="Mobile",0.01,IF(Table11[[#This Row],[Location]]="Decatur",0.01,IF(Table11[[#This Row],[Location]]="Woods Cross",0.01,IF(Table11[[#This Row],[Location]]="Park City",0.01,IF(Table11[[#This Row],[Location]]="Riverdale",0.01,IF(Table11[[#This Row],[Location]]="Riverton",0.01,IF(Table11[[#This Row],[Location]]="Layton",0.01,IF(Table11[[#This Row],[Location]]="Bend",0.01,IF(Table11[[#This Row],[Location]]="Bend",0.01,IF(Table11[[#This Row],[Location]]="Oakway",0.01,IF(Table11[[#This Row],[Location]]="North Medford",0.01,IF(Table11[[#This Row],[Location]]="South Eugene",0.01,IF(Table11[[#This Row],[Location]]="American Fork",0.01,IF(Table11[[#This Row],[Location]]="Sugar House",0.01,IF(Table11[[#This Row],[Location]]="Bend North",0.01,IF(Table11[[#This Row],[Location]]="South Medford",0.01,IF(Table11[[#This Row],[Location]]="Saratoga Springs",0.01,IF(Table11[[#This Row],[Location]]="Fort Union",0.01,IF(Table11[[#This Row],[Location]]="South Jordan",0.01,IF(Table11[[#This Row],[Location]]="Grants Pass",0.01,IF(Table11[[#This Row],[Location]]="Pocatello",0.01,IF(Table11[[#This Row],[Location]]="Spanish Fork",0.01,IF(Table11[[#This Row],[Location]]="Downtown Boise",0.01,IF(Table11[[#This Row],[Location]]="Boise Town Square",0.01,IF(Table11[[#This Row],[Location]]="Ammon",0.01,IF(Table11[[#This Row],[Location]]="Roseburg",0.01,IF(Table11[[#This Row],[Location]]="Springfield-Oregon",0.01,0.05))))))))))))))))))))))))))))))))) -> 0.05 | L435: =ROUND(F435*K435,2) -> 142.32 | M435: =J435+L435 -> 199.25
B436: 46266 | C436: 413 | D436: Madison | E436: 1118.23 | F436: 1088.78 | G436: =VLOOKUP(Table11[[#This Row],[Store]],'Rates from Tracker'!A:B,2,0) -> Madison | H436: =VLOOKUP(D436,'Rates from Tracker'!A:C,3,0) -> APizza Delight Inc | I436: =VLOOKUP(Table11[[#This Row],[Franchisee]],'Rates from Tracker'!C:D,2,0) -> Patel | J436: =ROUND(IF(Table11[[#This Row],[Location]]="Belmont Market",Table11[[#This Row],[Column2]]*0.01,IF(Table11[[#This Row],[Location]]="Country Club Centre",Table11[[#This Row],[Column2]]*0.01,IF(Table11[[#This Row],[Location]]="Naval Air Station Norfolk",Table11[[#This Row],[Column2]]*0.005,F436*0.02))),2) -> 21.78 | K436: =IF(Table11[[#This Row],[Location]]="Creekwalk",0.02,IF(Table11[[#This Row],[Location]]="Country Club Centre",0.01,IF(Table11[[#This Row],[Location]]="Lenexa",0.02,IF(Table11[[#This Row],[Location]]="Belmont Market",0.02,IF(Table11[[#This Row],[Location]]="Naval Air Station Norfolk",0.02,IF(Table11[[#This Row],[Location]]="Madison",0.01,IF(Table11[[#This Row],[Location]]="Mobile",0.01,IF(Table11[[#This Row],[Location]]="Decatur",0.01,IF(Table11[[#This Row],[Location]]="Woods Cross",0.01,IF(Table11[[#This Row],[Location]]="Park City",0.01,IF(Table11[[#This Row],[Location]]="Riverdale",0.01,IF(Table11[[#This Row],[Location]]="Riverton",0.01,IF(Table11[[#This Row],[Location]]="Layton",0.01,IF(Table11[[#This Row],[Location]]="Bend",0.01,IF(Table11[[#This Row],[Location]]="Bend",0.01,IF(Table11[[#This Row],[Location]]="Oakway",0.01,IF(Table11[[#This Row],[Location]]="North Medford",0.01,IF(Table11[[#This Row],[Location]]="South Eugene",0.01,IF(Table11[[#This Row],[Location]]="American Fork",0.01,IF(Table11[[#This Row],[Location]]="Sugar House",0.01,IF(Table11[[#This Row],[Location]]="Bend North",0.01,IF(Table11[[#This Row],[Location]]="South Medford",0.01,IF(Table11[[#This Row],[Location]]="Saratoga Springs",0.01,IF(Table11[[#This Row],[Location]]="Fort Union",0.01,IF(Table11[[#This Row],[Location]]="South Jordan",0.01,IF(Table11[[#This Row],[Location]]="Grants Pass",0.01,IF(Table11[[#This Row],[Location]]="Pocatello",0.01,IF(Table11[[#This Row],[Location]]="Spanish Fork",0.01,IF(Table11[[#This Row],[Location]]="Downtown Boise",0.01,IF(Table11[[#This Row],[Location]]="Boise Town Square",0.01,IF(Table11[[#This Row],[Location]]="Ammon",0.01,IF(Table11[[#This Row],[Location]]="Roseburg",0.01,IF(Table11[[#This Row],[Location]]="Springfield-Oregon",0.01,0.05))))))))))))))))))))))))))))))))) -> 0.01 | L436: =ROUND(F436*K436,2) -> 10.89 | M436: =J436+L436 -> 32.67
B437: 46266 | C437: 421 | D437: Fort Union | E437: 2193.08 | F437: 2162.8 | G437: =VLOOKUP(Table11[[#This Row],[Store]],'Rates from Tracker'!A:B,2,0) -> Fort Union | H437: =VLOOKUP(D437,'Rates from Tracker'!A:C,3,0) -> SSR Holdings LLC | I437: =VLOOKUP(Table11[[#This Row],[Franchisee]],'Rates from Tracker'!C:D,2,0) -> Bikram | J437: =ROUND(IF(Table11[[#This Row],[Location]]="Belmont Market",Table11[[#This Row],[Column2]]*0.01,IF(Table11[[#This Row],[Location]]="Country Club Centre",Table11[[#This Row],[Column2]]*0.01,IF(Table11[[#This Row],[Location]]="Naval Air Station Norfolk",Table11[[#This Row],[Column2]]*0.005,F437*0.02))),2) -> 43.26 | K437: =IF(Table11[[#This Row],[Location]]="Creekwalk",0.02,IF(Table11[[#This Row],[Location]]="Country Club Centre",0.01,IF(Table11[[#This Row],[Location]]="Lenexa",0.02,IF(Table11[[#This Row],[Location]]="Belmont Market",0.02,IF(Table11[[#This Row],[Location]]="Naval Air Station Norfolk",0.02,IF(Table11[[#This Row],[Location]]="Madison",0.01,IF(Table11[[#This Row],[Location]]="Mobile",0.01,IF(Table11[[#This Row],[Location]]="Decatur",0.01,IF(Table11[[#This Row],[Location]]="Woods Cross",0.01,IF(Table11[[#This Row],[Location]]="Park City",0.01,IF(Table11[[#This Row],[Location]]="Riverdale",0.01,IF(Table11[[#This Row],[Location]]="Riverton",0.01,IF(Table11[[#This Row],[Location]]="Layton",0.01,IF(Table11[[#This Row],[Location]]="Bend",0.01,IF(Table11[[#This Row],[Location]]="Bend",0.01,IF(Table11[[#This Row],[Location]]="Oakway",0.01,IF(Table11[[#This Row],[Location]]="North Medford",0.01,IF(Table11[[#This Row],[Location]]="South Eugene",0.01,IF(Table11[[#This Row],[Location]]="American Fork",0.01,IF(Table11[[#This Row],[Location]]="Sugar House",0.01,IF(Table11[[#This Row],[Location]]="Bend North",0.01,IF(Table11[[#This Row],[Location]]="South Medford",0.01,IF(Table11[[#This Row],[Location]]="Saratoga Springs",0.01,IF(Table11[[#This Row],[Location]]="Fort Union",0.01,IF(Table11[[#This Row],[Location]]="South Jordan",0.01,IF(Table11[[#This Row],[Location]]="Grants Pass",0.01,IF(Table11[[#This Row],[Location]]="Pocatello",0.01,IF(Table11[[#This Row],[Location]]="Spanish Fork",0.01,IF(Table11[[#This Row],[Location]]="Downtown Boise",0.01,IF(Table11[[#This Row],[Location]]="Boise Town Square",0.01,IF(Table11[[#This Row],[Location]]="Ammon",0.01,IF(Table11[[#This Row],[Location]]="Roseburg",0.01,IF(Table11[[#This Row],[Location]]="Springfield-Oregon",0.01,0.05))))))))))))))))))))))))))))))))) -> 0.01 | L437: =ROUND(F437*K437,2) -> 21.63 | M437: =J437+L437 -> 64.89
B438: 46266 | C438: 425 | D438: Crown Point | E438: 2322.04 | F438: 2243.97 | G438: =VLOOKUP(Table11[[#This Row],[Store]],'Rates from Tracker'!A:B,2,0) -> Crown Point | H438: =VLOOKUP(D438,'Rates from Tracker'!A:C,3,0) -> Best Pizza LLC | I438: =VLOOKUP(Table11[[#This Row],[Franchisee]],'Rates from Tracker'!C:D,2,0) -> Merullo | J438: =ROUND(IF(Table11[[#This Row],[Location]]="Belmont Market",Table11[[#This Row],[Column2]]*0.01,IF(Table11[[#This Row],[Location]]="Country Club Centre",Table11[[#This Row],[Column2]]*0.01,IF(Table11[[#This Row],[Location]]="Naval Air Station Norfolk",Table11[[#This Row],[Column2]]*0.005,F438*0.02))),2) -> 44.88 | K438: =IF(Table11[[#This Row],[Location]]="Creekwalk",0.02,IF(Table11[[#This Row],[Location]]="Country Club Centre",0.01,IF(Table11[[#This Row],[Location]]="Lenexa",0.02,IF(Table11[[#This Row],[Location]]="Belmont Market",0.02,IF(Table11[[#This Row],[Location]]="Naval Air Station Norfolk",0.02,IF(Table11[[#This Row],[Location]]="Madison",0.01,IF(Table11[[#This Row],[Location]]="Mobile",0.01,IF(Table11[[#This Row],[Location]]="Decatur",0.01,IF(Table11[[#This Row],[Location]]="Woods Cross",0.01,IF(Table11[[#This Row],[Location]]="Park City",0.01,IF(Table11[[#This Row],[Location]]="Riverdale",0.01,IF(Table11[[#This Row],[Location]]="Riverton",0.01,IF(Table11[[#This Row],[Location]]="Layton",0.01,IF(Table11[[#This Row],[Location]]="Bend",0.01,IF(Table11[[#This Row],[Location]]="Bend",0.01,IF(Table11[[#This Row],[Location]]="Oakway",0.01,IF(Table11[[#This Row],[Location]]="North Medford",0.01,IF(Table11[[#This Row],[Location]]="South Eugene",0.01,IF(Table11[[#This Row],[Location]]="American Fork",0.01,IF(Table11[[#This Row],[Location]]="Sugar House",0.01,IF(Table11[[#This Row],[Location]]="Bend North",0.01,IF(Table11[[#This Row],[Location]]="South Medford",0.01,IF(Table11[[#This Row],[Location]]="Saratoga Springs",0.01,IF(Table11[[#This Row],[Location]]="Fort Union",0.01,IF(Table11[[#This Row],[Location]]="South Jordan",0.01,IF(Table11[[#This Row],[Location]]="Grants Pass",0.01,IF(Table11[[#This Row],[Location]]="Pocatello",0.01,IF(Table11[[#This Row],[Location]]="Spanish Fork",0.01,IF(Table11[[#This Row],[Location]]="Downtown Boise",0.01,IF(Table11[[#This Row],[Location]]="Boise Town Square",0.01,IF(Table11[[#This Row],[Location]]="Ammon",0.01,IF(Table11[[#This Row],[Location]]="Roseburg",0.01,IF(Table11[[#This Row],[Location]]="Springfield-Oregon",0.01,0.05))))))))))))))))))))))))))))))))) -> 0.05 | L438: =ROUND(F438*K438,2) -> 112.2 | M438: =J438+L438 -> 157.08
B439: 46266 | C439: 429 | D439: South Jordan | E439: 1608.98 | F439: 1590.58 | G439: =VLOOKUP(Table11[[#This Row],[Store]],'Rates from Tracker'!A:B,2,0) -> South Jordan | H439: =VLOOKUP(D439,'Rates from Tracker'!A:C,3,0) -> SSR Holdings LLC | I439: =VLOOKUP(Table11[[#This Row],[Franchisee]],'Rates from Tracker'!C:D,2,0) -> Bikram | J439: =ROUND(IF(Table11[[#This Row],[Location]]="Belmont Market",Table11[[#This Row],[Column2]]*0.01,IF(Table11[[#This Row],[Location]]="Country Club Centre",Table11[[#This Row],[Column2]]*0.01,IF(Table11[[#This Row],[Location]]="Naval Air Station Norfolk",Table11[[#This Row],[Column2]]*0.005,F439*0.02))),2) -> 31.81 | K439: =IF(Table11[[#This Row],[Location]]="Creekwalk",0.02,IF(Table11[[#This Row],[Location]]="Country Club Centre",0.01,IF(Table11[[#This Row],[Location]]="Lenexa",0.02,IF(Table11[[#This Row],[Location]]="Belmont Market",0.02,IF(Table11[[#This Row],[Location]]="Naval Air Station Norfolk",0.02,IF(Table11[[#This Row],[Location]]="Madison",0.01,IF(Table11[[#This Row],[Location]]="Mobile",0.01,IF(Table11[[#This Row],[Location]]="Decatur",0.01,IF(Table11[[#This Row],[Location]]="Woods Cross",0.01,IF(Table11[[#This Row],[Location]]="Park City",0.01,IF(Table11[[#This Row],[Location]]="Riverdale",0.01,IF(Table11[[#This Row],[Location]]="Riverton",0.01,IF(Table11[[#This Row],[Location]]="Layton",0.01,IF(Table11[[#This Row],[Location]]="Bend",0.01,IF(Table11[[#This Row],[Location]]="Bend",0.01,IF(Table11[[#This Row],[Location]]="Oakway",0.01,IF(Table11[[#This Row],[Location]]="North Medford",0.01,IF(Table11[[#This Row],[Location]]="South Eugene",0.01,IF(Table11[[#This Row],[Location]]="American Fork",0.01,IF(Table11[[#This Row],[Location]]="Sugar House",0.01,IF(Table11[[#This Row],[Location]]="Bend North",0.01,IF(Table11[[#This Row],[Location]]="South Medford",0.01,IF(Table11[[#This Row],[Location]]="Saratoga Springs",0.01,IF(Table11[[#This Row],[Location]]="Fort Union",0.01,IF(Table11[[#This Row],[Location]]="South Jordan",0.01,IF(Table11[[#This Row],[Location]]="Grants Pass",0.01,IF(Table11[[#This Row],[Location]]="Pocatello",0.01,IF(Table11[[#This Row],[Location]]="Spanish Fork",0.01,IF(Table11[[#This Row],[Location]]="Downtown Boise",0.01,IF(Table11[[#This Row],[Location]]="Boise Town Square",0.01,IF(Table11[[#This Row],[Location]]="Ammon",0.01,IF(Table11[[#This Row],[Location]]="Roseburg",0.01,IF(Table11[[#This Row],[Location]]="Springfield-Oregon",0.01,0.05))))))))))))))))))))))))))))))))) -> 0.01 | L439: =ROUND(F439*K439,2) -> 15.91 | M439: =J439+L439 -> 47.72
B440: 46266 | C440: 433 | D440: Grants Pass | E440: 2043.18 | F440: 1944.28 | G440: =VLOOKUP(Table11[[#This Row],[Store]],'Rates from Tracker'!A:B,2,0) -> Grants Pass | H440: =VLOOKUP(D440,'Rates from Tracker'!A:C,3,0) -> SSR Holdings LLC | I440: =VLOOKUP(Table11[[#This Row],[Franchisee]],'Rates from Tracker'!C:D,2,0) -> Bikram | J440: =ROUND(IF(Table11[[#This Row],[Location]]="Belmont Market",Table11[[#This Row],[Column2]]*0.01,IF(Table11[[#This Row],[Location]]="Country Club Centre",Table11[[#This Row],[Column2]]*0.01,IF(Table11[[#This Row],[Location]]="Naval Air Station Norfolk",Table11[[#This Row],[Column2]]*0.005,F440*0.02))),2) -> 38.89 | K440: =IF(Table11[[#This Row],[Location]]="Creekwalk",0.02,IF(Table11[[#This Row],[Location]]="Country Club Centre",0.01,IF(Table11[[#This Row],[Location]]="Lenexa",0.02,IF(Table11[[#This Row],[Location]]="Belmont Market",0.02,IF(Table11[[#This Row],[Location]]="Naval Air Station Norfolk",0.02,IF(Table11[[#This Row],[Location]]="Madison",0.01,IF(Table11[[#This Row],[Location]]="Mobile",0.01,IF(Table11[[#This Row],[Location]]="Decatur",0.01,IF(Table11[[#This Row],[Location]]="Woods Cross",0.01,IF(Table11[[#This Row],[Location]]="Park City",0.01,IF(Table11[[#This Row],[Location]]="Riverdale",0.01,IF(Table11[[#This Row],[Location]]="Riverton",0.01,IF(Table11[[#This Row],[Location]]="Layton",0.01,IF(Table11[[#This Row],[Location]]="Bend",0.01,IF(Table11[[#This Row],[Location]]="Bend",0.01,IF(Table11[[#This Row],[Location]]="Oakway",0.01,IF(Table11[[#This Row],[Location]]="North Medford",0.01,IF(Table11[[#This Row],[Location]]="South Eugene",0.01,IF(Table11[[#This Row],[Location]]="American Fork",0.01,IF(Table11[[#This Row],[Location]]="Sugar House",0.01,IF(Table11[[#This Row],[Location]]="Bend North",0.01,IF(Table11[[#This Row],[Location]]="South Medford",0.01,IF(Table11[[#This Row],[Location]]="Saratoga Springs",0.01,IF(Table11[[#This Row],[Location]]="Fort Union",0.01,IF(Table11[[#This Row],[Location]]="South Jordan",0.01,IF(Table11[[#This Row],[Location]]="Grants Pass",0.01,IF(Table11[[#This Row],[Location]]="Pocatello",0.01,IF(Table11[[#This Row],[Location]]="Spanish Fork",0.01,IF(Table11[[#This Row],[Location]]="Downtown Boise",0.01,IF(Table11[[#This Row],[Location]]="Boise Town Square",0.01,IF(Table11[[#This Row],[Location]]="Ammon",0.01,IF(Table11[[#This Row],[Location]]="Roseburg",0.01,IF(Table11[[#This Row],[Location]]="Springfield-Oregon",0.01,0.05))))))))))))))))))))))))))))))))) -> 0.01 | L440: =ROUND(F440*K440,2) -> 19.44 | M440: =J440+L440 -> 58.33
B441: 46266 | C441: 452 | D441: Mobile | E441: 1111.51 | F441: 1106.11 | G441: =VLOOKUP(Table11[[#This Row],[Store]],'Rates from Tracker'!A:B,2,0) -> Mobile | H441: =VLOOKUP(D441,'Rates from Tracker'!A:C,3,0) -> MAA MELDI 3980 Inc | I441: =VLOOKUP(Table11[[#This Row],[Franchisee]],'Rates from Tracker'!C:D,2,0) -> Neal Patel | J441: =ROUND(IF(Table11[[#This Row],[Location]]="Belmont Market",Table11[[#This Row],[Column2]]*0.01,IF(Table11[[#This Row],[Location]]="Country Club Centre",Table11[[#This Row],[Column2]]*0.01,IF(Table11[[#This Row],[Location]]="Naval Air Station Norfolk",Table11[[#This Row],[Column2]]*0.005,F441*0.02))),2) -> 22.12 | K441: =IF(Table11[[#This Row],[Location]]="Creekwalk",0.02,IF(Table11[[#This Row],[Location]]="Country Club Centre",0.01,IF(Table11[[#This Row],[Location]]="Lenexa",0.02,IF(Table11[[#This Row],[Location]]="Belmont Market",0.02,IF(Table11[[#This Row],[Location]]="Naval Air Station Norfolk",0.02,IF(Table11[[#This Row],[Location]]="Madison",0.01,IF(Table11[[#This Row],[Location]]="Mobile",0.01,IF(Table11[[#This Row],[Location]]="Decatur",0.01,IF(Table11[[#This Row],[Location]]="Woods Cross",0.01,IF(Table11[[#This Row],[Location]]="Park City",0.01,IF(Table11[[#This Row],[Location]]="Riverdale",0.01,IF(Table11[[#This Row],[Location]]="Riverton",0.01,IF(Table11[[#This Row],[Location]]="Layton",0.01,IF(Table11[[#This Row],[Location]]="Bend",0.01,IF(Table11[[#This Row],[Location]]="Bend",0.01,IF(Table11[[#This Row],[Location]]="Oakway",0.01,IF(Table11[[#This Row],[Location]]="North Medford",0.01,IF(Table11[[#This Row],[Location]]="South Eugene",0.01,IF(Table11[[#This Row],[Location]]="American Fork",0.01,IF(Table11[[#This Row],[Location]]="Sugar House",0.01,IF(Table11[[#This Row],[Location]]="Bend North",0.01,IF(Table11[[#This Row],[Location]]="South Medford",0.01,IF(Table11[[#This Row],[Location]]="Saratoga Springs",0.01,IF(Table11[[#This Row],[Location]]="Fort Union",0.01,IF(Table11[[#This Row],[Location]]="South Jordan",0.01,IF(Table11[[#This Row],[Location]]="Grants Pass",0.01,IF(Table11[[#This Row],[Location]]="Pocatello",0.01,IF(Table11[[#This Row],[Location]]="Spanish Fork",0.01,IF(Table11[[#This Row],[Location]]="Downtown Boise",0.01,IF(Table11[[#This Row],[Location]]="Boise Town Square",0.01,IF(Table11[[#This Row],[Location]]="Ammon",0.01,IF(Table11[[#This Row],[Location]]="Roseburg",0.01,IF(Table11[[#This Row],[Location]]="Springfield-Oregon",0.01,0.05))))))))))))))))))))))))))))))))) -> 0.01 | L441: =ROUND(F441*K441,2) -> 11.06 | M441: =J441+L441 -> 33.18
... B590: 46258 | C590: 820 | D590: Churn Creek | E590: 2408.62 | F590: 2369.61 | G590: =VLOOKUP(Table11[[#This Row],[Store]],'Rates from Tracker'!A:B,2,0) -> Churn Creek | H590: =VLOOKUP(D590,'Rates from Tracker'!A:C,3,0) -> Exceed Group Churn Creek | I590: =VLOOKUP(Table11[[#This Row],[Franchisee]],'Rates from Tracker'!C:D,2,0) -> Chawla | J590: =ROUND(IF(Table11[[#This Row],[Location]]="Belmont Market",Table11[[#This Row],[Column2]]*0.01,IF(Table11[[#This Row],[Location]]="Country Club Centre",Table11[[#This Row],[Column2]]*0.01,IF(Table11[[#This Row],[Location]]="Naval Air Station Norfolk",Table11[[#This Row],[Column2]]*0.005,F590*0.02))),2) -> 47.39 | K590: =IF(Table11[[#This Row],[Location]]="Creekwalk",0.02,IF(Table11[[#This Row],[Location]]="Country Club Centre",0.01,IF(Table11[[#This Row],[Location]]="Lenexa",0.02,IF(Table11[[#This Row],[Location]]="Belmont Market",0.02,IF(Table11[[#This Row],[Location]]="Naval Air Station Norfolk",0.02,IF(Table11[[#This Row],[Location]]="Madison",0.01,IF(Table11[[#This Row],[Location]]="Mobile",0.01,IF(Table11[[#This Row],[Location]]="Decatur",0.01,IF(Table11[[#This Row],[Location]]="Woods Cross",0.01,IF(Table11[[#This Row],[Location]]="Park City",0.01,IF(Table11[[#This Row],[Location]]="Riverdale",0.01,IF(Table11[[#This Row],[Location]]="Riverton",0.01,IF(Table11[[#This Row],[Location]]="Layton",0.01,IF(Table11[[#This Row],[Location]]="Bend",0.01,IF(Table11[[#This Row],[Location]]="Bend",0.01,IF(Table11[[#This Row],[Location]]="Oakway",0.01,IF(Table11[[#This Row],[Location]]="North Medford",0.01,IF(Table11[[#This Row],[Location]]="South Eugene",0.01,IF(Table11[[#This Row],[Location]]="American Fork",0.01,IF(Table11[[#This Row],[Location]]="Sugar House",0.01,IF(Table11[[#This Row],[Location]]="Bend North",0.01,IF(Table11[[#This Row],[Location]]="South Medford",0.01,IF(Table11[[#This Row],[Location]]="Saratoga Springs",0.01,IF(Table11[[#This Row],[Location]]="Fort Union",0.01,IF(Table11[[#This Row],[Location]]="South Jordan",0.01,IF(Table11[[#This Row],[Location]]="Grants Pass",0.01,IF(Table11[[#This Row],[Location]]="Pocatello",0.01,IF(Table11[[#This Row],[Location]]="Spanish Fork",0.01,IF(Table11[[#This Row],[Location]]="Downtown Boise",0.01,IF(Table11[[#This Row],[Location]]="Boise Town Square",0.01,IF(Table11[[#This Row],[Location]]="Ammon",0.01,IF(Table11[[#This Row],[Location]]="Roseburg",0.01,IF(Table11[[#This Row],[Location]]="Springfield-Oregon",0.01,0.05))))))))))))))))))))))))))))))))) -> 0.05 | L590: =ROUND(F590*K590,2) -> 118.48 | M590: =J590+L590 -> 165.87

Sheet Summary
A1: MOD Pizza
A2: Franchise Royalty Calculations
A3: Week Ending | B3: 46271
A4: Location | B4: (All)
C6: Values
A7: Franchisee | B7: Principal Name | C7: Sum of Marketing Fee | D7: Sum of Royalty Fee | E7: Sum of Total | F7: Routing # | G7: Account # | H7: Currency | K7: Cash Tie Out (Cash Clearing)
A8: APizza Delight Inc | B8: Patel | C8: 237.86 | D8: 118.94 | E8: 356.8 | F8: =VLOOKUP(A8,'Banking Info'!B:D,2,0) -> #N/A | G8: =VLOOKUP(A8,'Banking Info'!B:D,3,0) -> #N/A | H8: USD | K8: =SUM(E8:E29) -> 83661.99 | L8: Actual Cash in to MOD Franchising
A9: Best Pizza LLC | B9: Merullo | C9: 10942.44 | D9: 26778.56 | E9: 37721 | F9: =VLOOKUP(A9,'Banking Info'!B:D,2,0) -> 124000054 | G9: =VLOOKUP(A9,'Banking Info'!B:D,3,0) -> 427012802 | H9: USD | K9: =K17 -> 626.584 | L9: Actual Cash in to MOD Int Franchising Belmont Market Place
A10: Cool Dough Development, LLC | B10: Denning | C10: 964.81 | D10: 2411.99 | E10: 3376.8 | F10: =VLOOKUP(A10,'Banking Info'!B:D,2,0) -> 083901621 | G10: =VLOOKUP(A10,'Banking Info'!B:D,3,0) -> 1609815 | H10: USD | K10: =K26 -> 204.9824 | L10: Actual Cash in to MOD Int Franchising Countyr Clube Centre
A11: DAZ9 | B11: Neal Patel | C11: 229.12 | D11: 114.56 | E11: 343.68 | F11: =VLOOKUP(A11,'Banking Info'!B:D,2,0) -> #N/A | G11: =VLOOKUP(A11,'Banking Info'!B:D,3,0) -> #N/A | H11: USD
A12: Exceed Group Auburn Village | B12: Chawla | C12: 234.35 | D12: 585.88 | E12: 820.23 | F12: =VLOOKUP(A12,'Banking Info'!B:D,2,0) -> #N/A | G12: =VLOOKUP(A12,'Banking Info'!B:D,3,0) -> #N/A | H12: USD | K12: V. I Pizza
A13: Exceed Group Campus Oaks | B13: Chawla | C13: 442.46 | D13: 1106.14 | E13: 1548.6 | F13: =VLOOKUP(A13,'Banking Info'!B:D,2,0) -> #N/A | G13: =VLOOKUP(A13,'Banking Info'!B:D,3,0) -> #N/A | H13: USD | K13: Belmont Market Place
A14: Exceed Group Chico | B14: Chawla | C14: 569.94 | D14: 1424.83 | E14: 1994.77 | F14: =VLOOKUP(A14,'Banking Info'!B:D,2,0) -> #N/A | G14: =VLOOKUP(A14,'Banking Info'!B:D,3,0) -> #N/A | H14: USD | K14: =$E$30 -> 559.45 | L14: Billing
A15: Exceed Group Churn Creek | B15: Chawla | C15: 517.55 | D15: 1293.91 | E15: 1811.46 | F15: =VLOOKUP(A15,'Banking Info'!B:D,2,0) -> #N/A | G15: =VLOOKUP(A15,'Banking Info'!B:D,3,0) -> #N/A | H15: USD | K15: =$E$30*0.05 -> 27.9725 | L15: GST
A16: Exceed Group Eureka | B16: Chawla | C16: 406.66 | D16: 1016.63 | E16: 1423.29 | F16: =VLOOKUP(A16,'Banking Info'!B:D,2,0) -> #N/A | G16: =VLOOKUP(A16,'Banking Info'!B:D,3,0) -> #N/A | H16: CAD | K16: =$E$30*0.07 -> 39.1615 | L16: PST
A17: Exceed Group Howe Bout Arden | B17: Chawla | C17: 573.21 | D17: 1433.01 | E17: 2006.22 | K17: =SUM(K14:K16) -> 626.584 | L17: Invoice Total (CAD)
A18: Exceed Group Rancho Cordova | B18: Chawla | C18: 291.52 | D18: 728.82 | E18: 1020.34
A19: Exceed Group REDDING | B19: Chawla | C19: 511.72 | D19: 1279.28 | E19: 1791
A20: Exceed Group Redfield Promenade | B20: Chawla | C20: 307.67 | D20: 769.16 | E20: 1076.83
A21: Exceed Group ROCKLIN | B21: Chawla | C21: 344.08 | D21: 860.2 | E21: 1204.28
A22: Exceed Group West Sacramento | B22: Chawla | C22: 324.81 | D22: 811.99 | E22: 1136.8 | L22: Country Club Centre
A23: Exceed Group Woodland | B23: Chawla | C23: 391.36 | D23: 978.4 | E23: 1369.76 | K23: =$E$31 -> 183.02 | L23: Billing
A24: IDAD-5 Inc | B24: Ingenito | C24: 43.66 | D24: 174.64 | E24: 218.3 | K24: =$E$31*0.05 -> 9.151 | L24: GST
A25: MAA MELDI 3980 Inc | B25: Neal Patel | C25: 234.39 | D25: 117.18 | E25: 351.57 | K25: =$E$31*0.07 -> 12.8114 | L25: PST
A26: Rolling Dough LLC | B26: Connolly | C26: 2007.51 | D26: 5018.79 | E26: 7026.3 | K26: =SUM(K23:K25) -> 204.9824 | L26: Invoice Total (CAD)
A27: Southern Pie LLC | B27: Hill/Hayden | C27: 413.33 | D27: 1033.32 | E27: 1446.65 | K27: 205
A28: SSR Holdings LLC | B28: Bikram | C28: 8297.47 | D28: 4148.75 | E28: 12446.22 | I28: 11629.37
A29: TSFR Pizza LLC | B29: Schostak | C29: 906.02 | D29: 2265.07 | E29: 3171.09
A30: V.I. Pizza Belmont | B30: Hayden | C30: 186.48 | D30: 372.97 | E30: 559.45
A31: V.I. Pizza Country Club | B31: Hayden | C31: 91.51 | D31: 91.51 | E31: 183.02
A32: Grand Total | C32: 29469.93 | D32: 54934.53 | E32: 84404.46

Sheet Sheet1
G2: APizza Delight Inc | H2: 356.8 | J2: V.I. Pizza Belmont | K2: 559.45 | M2: 831.59 CAD
G3: Best Pizza LLC | H3: 37721 | J3: V.I. Pizza Country Club | K3: 183.02
G4: Cool Dough Development, LLC | H4: 3376.8
G5: DAZ9 | H5: 343.68
G6: Exceed Group Auburn Village | H6: 820.23
G7: Exceed Group Campus Oaks | H7: 1548.6
G8: Exceed Group Chico | H8: 1994.77
G9: Exceed Group Churn Creek | H9: 1811.46
G10: Exceed Group Eureka | H10: 1423.29
G11: Exceed Group Howe Bout Arden | H11: 2006.22
G12: Exceed Group Rancho Cordova | H12: 1020.34
G13: Exceed Group REDDING | H13: 1791
G14: Exceed Group Redfield Promenade | H14: 1076.83
G15: Exceed Group ROCKLIN | H15: 1204.28
... G23: TSFR Pizza LLC | H23: 3171.09
H24: 82845.14

Sheet Debit Memo Info
D1: Stores | E1: Stores on Tracker | F1: Difference
D2: =COUNTA(B5:B119) -> 115 | E2: 91 | F2: =D2-E2 -> 24
A3: d | D3: *Note: DTW & Northwestern University billed separately
A4: Franchisee | B4: Location | C4: CONTINUINGFEE - Net Value | D4: CONTINUINGFEE - Item Description | E4: MARKETINGFEE - Net Value | F4: MARKETINGFEE - Item Description | G4: Rate Increase? | H4: Total | I4: Comments
A5: =VLOOKUP(B5,'Rates from Tracker'!B:C,2,0) -> Exceed Group Auburn Village | B5: Auburn Village | C5: =SUMIF(Calculations!G:G,B5,Calculations!L:L) -> 585.88 | D5: =IF(Table8[[#This Row],[Rate Increase?]]="Yes","",(VLOOKUP(B5,Calculations!G:K,5,0)*100)&"% of "&DOLLAR(SUMIF(Calculations!G:G,B5,Calculations!F:F),2)&" "&B5) -> 5% of $11,717.50 Auburn Village | E5: =SUMIF(Calculations!G:G,B5,Calculations!J:J) -> 234.35 | F5: =IF(Table8[[#This Row],[Location]]="Belmont Market",1,IF(Table8[[#This Row],[Location]]="Country Club Centre",1,IF(Table8[[#This Row],[Location]]="Naval Air Station Norfolk",0.5,2)))&"% of "&DOLLAR(SUMIF(Calculations!G:G,B5,Calculations!F:F),2)&" "&B5 -> 2% of $11,717.50 Auburn Village | G5: =IF((SUMIF(Calculations!$G:$G,Table8[[#This Row],[Location]],Calculations!$K:$K)/COUNTIF(Calculations!$G:$G,Table8[[#This Row],[Location]]))<>VLOOKUP(Table8[[#This Row],[Location]],Calculations!G:M,5,0),"Yes","") | H5: =Table8[[#This Row],[CONTINUINGFEE - Net Value]]+Table8[[#This Row],[MARKETINGFEE - Net Value]] -> 820.23
A6: =VLOOKUP(B6,'Rates from Tracker'!B:C,2,0) -> Paceline Partners, LLC (KS/MO) | B6: Blue Springs | C6: =SUMIF(Calculations!G:G,B6,Calculations!L:L) -> 0 | D6: =IF(Table8[[#This Row],[Rate Increase?]]="Yes","",(VLOOKUP(B6,Calculations!G:K,5,0)*100)&"% of "&DOLLAR(SUMIF(Calculations!G:G,B6,Calculations!F:F),2)&" "&B6) -> #DIV/0! | E6: =SUMIF(Calculations!G:G,B6,Calculations!J:J) -> 0 | F6: =IF(Table8[[#This Row],[Location]]="Belmont Market",1,IF(Table8[[#This Row],[Location]]="Country Club Centre",1,IF(Table8[[#This Row],[Location]]="Naval Air Station Norfolk",0.5,2)))&"% of "&DOLLAR(SUMIF(Calculations!G:G,B6,Calculations!F:F),2)&" "&B6 -> 2% of $0.00 Blue Springs | G6: =IF((SUMIF(Calculations!$G:$G,Table8[[#This Row],[Location]],Calculations!$K:$K)/COUNTIF(Calculations!$G:$G,Table8[[#This Row],[Location]]))<>VLOOKUP(Table8[[#This Row],[Location]],Calculations!G:M,5,0),"Yes","") -> #DIV/0! | H6: =Table8[[#This Row],[CONTINUINGFEE - Net Value]]+Table8[[#This Row],[MARKETINGFEE - Net Value]] -> 0 | I6: closed
A7: =VLOOKUP(B7,'Rates from Tracker'!B:C,2,0) -> TSFR Pizza LLC | B7: Brighton | C7: =SUMIF(Calculations!G:G,B7,Calculations!L:L) -> 1155.22 | D7: =IF(Table8[[#This Row],[Rate Increase?]]="Yes","",(VLOOKUP(B7,Calculations!G:K,5,0)*100)&"% of "&DOLLAR(SUMIF(Calculations!G:G,B7,Calculations!F:F),2)&" "&B7) -> 5% of $23,104.49 Brighton | E7: =SUMIF(Calculations!G:G,B7,Calculations!J:J) -> 462.08 | F7: =IF(Table8[[#This Row],[Location]]="Belmont Market",1,IF(Table8[[#This Row],[Location]]="Country Club Centre",1,IF(Table8[[#This Row],[Location]]="Naval Air Station Norfolk",0.5,2)))&"% of "&DOLLAR(SUMIF(Calculations!G:G,B7,Calculations!F:F),2)&" "&B7 -> 2% of $23,104.49 Brighton | H7: =Table8[[#This Row],[CONTINUINGFEE - Net Value]]+Table8[[#This Row],[MARKETINGFEE - Net Value]] -> 1617.3
A8: =VLOOKUP(B8,'Rates from Tracker'!B:C,2,0) -> TSFR Pizza LLC | B8: Canton | C8: =SUMIF(Calculations!G:G,B8,Calculations!L:L) -> 0 | D8: =IF(Table8[[#This Row],[Rate Increase?]]="Yes","",(VLOOKUP(B8,Calculations!G:K,5,0)*100)&"% of "&DOLLAR(SUMIF(Calculations!G:G,B8,Calculations!F:F),2)&" "&B8) -> #DIV/0! | E8: =SUMIF(Calculations!G:G,B8,Calculations!J:J) -> 0 | F8: =IF(Table8[[#This Row],[Location]]="Belmont Market",1,IF(Table8[[#This Row],[Location]]="Country Club Centre",1,IF(Table8[[#This Row],[Location]]="Naval Air Station Norfolk",0.5,2)))&"% of "&DOLLAR(SUMIF(Calculations!G:G,B8,Calculations!F:F),2)&" "&B8 -> 2% of $0.00 Canton | G8: =IF((SUMIF(Calculations!$G:$G,Table8[[#This Row],[Location]],Calculations!$K:$K)/COUNTIF(Calculations!$G:$G,Table8[[#This Row],[Location]]))<>VLOOKUP(Table8[[#This Row],[Location]],Calculations!G:M,5,0),"Yes","") -> #DIV/0! | H8: =Table8[[#This Row],[CONTINUINGFEE - Net Value]]+Table8[[#This Row],[MARKETINGFEE - Net Value]] -> 0 | I8: closed
A9: =VLOOKUP(B9,'Rates from Tracker'!B:C,2,0) -> Best Pizza LLC | B9: Castle Rock | C9: =SUMIF(Calculations!G:G,B9,Calculations!L:L) -> 1428.37 | D9: =IF(Table8[[#This Row],[Rate Increase?]]="Yes","",(VLOOKUP(B9,Calculations!G:K,5,0)*100)&"% of "&DOLLAR(SUMIF(Calculations!G:G,B9,Calculations!F:F),2)&" "&B9) -> 5% of $28,567.53 Castle Rock | E9: =SUMIF(Calculations!G:G,B9,Calculations!J:J) -> 571.36 | F9: =IF(Table8[[#This Row],[Location]]="Belmont Market",1,IF(Table8[[#This Row],[Location]]="Country Club Centre",1,IF(Table8[[#This Row],[Location]]="Naval Air Station Norfolk",0.5,2)))&"% of "&DOLLAR(SUMIF(Calculations!G:G,B9,Calculations!F:F),2)&" "&B9 -> 2% of $28,567.53 Castle Rock | G9: =IF((SUMIF(Calculations!$G:$G,Table8[[#This Row],[Location]],Calculations!$K:$K)/COUNTIF(Calculations!$G:$G,Table8[[#This Row],[Location]]))<>VLOOKUP(Table8[[#This Row],[Location]],Calculations!G:M,5,0),"Yes","") | H9: =Table8[[#This Row],[CONTINUINGFEE - Net Value]]+Table8[[#This Row],[MARKETINGFEE - Net Value]] -> 1999.73
A10: =VLOOKUP(B10,'Rates from Tracker'!B:C,2,0) -> Best Pizza LLC | B10: Centre Avenue | C10: =SUMIF(Calculations!G:G,B10,Calculations!L:L) -> 1198.14 | D10: =IF(Table8[[#This Row],[Rate Increase?]]="Yes","",(VLOOKUP(B10,Calculations!G:K,5,0)*100)&"% of "&DOLLAR(SUMIF(Calculations!G:G,B10,Calculations!F:F),2)&" "&B10) -> 5% of $23,962.69 Centre Avenue | E10: =SUMIF(Calculations!G:G,B10,Calculations!J:J) -> 479.26 | F10: =IF(Table8[[#This Row],[Location]]="Belmont Market",1,IF(Table8[[#This Row],[Location]]="Country Club Centre",1,IF(Table8[[#This Row],[Location]]="Naval Air Station Norfolk",0.5,2)))&"% of "&DOLLAR(SUMIF(Calculations!G:G,B10,Calculations!F:F),2)&" "&B10 -> 2% of $23,962.69 Centre Avenue | G10: =IF((SUMIF(Calculations!$G:$G,Table8[[#This Row],[Location]],Calculations!$K:$K)/COUNTIF(Calculations!$G:$G,Table8[[#This Row],[Location]]))<>VLOOKUP(Table8[[#This Row],[Location]],Calculations!G:M,5,0),"Yes","") | H10: =Table8[[#This Row],[CONTINUINGFEE - Net Value]]+Table8[[#This Row],[MARKETINGFEE - Net Value]] -> 1677.4
A11: =VLOOKUP(B11,'Rates from Tracker'!B:C,2,0) -> Cool Dough Development, LLC | B11: Tates Creek #7 | C11: =SUMIF(Calculations!G:G,B11,Calculations!L:L) -> 0 | D11: =IF(Table8[[#This Row],[Rate Increase?]]="Yes","",(VLOOKUP(B11,Calculations!G:K,5,0)*100)&"% of "&DOLLAR(SUMIF(Calculations!G:G,B11,Calculations!F:F),2)&" "&B11) -> #DIV/0! | E11: =SUMIF(Calculations!G:G,B11,Calculations!J:J) -> 0 | F11: =IF(Table8[[#This Row],[Location]]="Belmont Market",1,IF(Table8[[#This Row],[Location]]="Country Club Centre",1,IF(Table8[[#This Row],[Location]]="Naval Air Station Norfolk",0.5,2)))&"% of "&DOLLAR(SUMIF(Calculations!G:G,B11,Calculations!F:F),2)&" "&B11 -> 2% of $0.00 Tates Creek #7 | G11: =IF((SUMIF(Calculations!$G:$G,Table8[[#This Row],[Location]],Calculations!$K:$K)/COUNTIF(Calculations!$G:$G,Table8[[#This Row],[Location]]))<>VLOOKUP(Table8[[#This Row],[Location]],Calculations!G:M,5,0),"Yes","") -> #DIV/0! | H11: =Table8[[#This Row],[CONTINUINGFEE - Net Value]]+Table8[[#This Row],[MARKETINGFEE - Net Value]] -> 0 | I11: do not enter
A12: =VLOOKUP(B12,'Rates from Tracker'!B:C,2,0) -> Exceed Group Chico | B12: Chico | C12: =SUMIF(Calculations!G:G,B12,Calculations!L:L) -> 1424.83 | D12: =IF(Table8[[#This Row],[Rate Increase?]]="Yes","",(VLOOKUP(B12,Calculations!G:K,5,0)*100)&"% of "&DOLLAR(SUMIF(Calculations!G:G,B12,Calculations!F:F),2)&" "&B12) -> 5% of $28,496.67 Chico | E12: ex | F12: =IF(Table8[[#This Row],[Location]]="Belmont Market",1,IF(Table8[[#This Row],[Location]]="Country Club Centre",1,IF(Table8[[#This Row],[Location]]="Naval Air Station Norfolk",0.5,2)))&"% of "&DOLLAR(SUMIF(Calculations!G:G,B12,Calculations!F:F),2)&" "&B12 -> 2% of $28,496.67 Chico | G12: =IF((SUMIF(Calculations!$G:$G,Table8[[#This Row],[Location]],Calculations!$K:$K)/COUNTIF(Calculations!$G:$G,Table8[[#This Row],[Location]]))<>VLOOKUP(Table8[[#This Row],[Location]],Calculations!G:M,5,0),"Yes","") | H12: =Table8[[#This Row],[CONTINUINGFEE - Net Value]]+Table8[[#This Row],[MARKETINGFEE - Net Value]] -> #VALUE!
A13: =VLOOKUP(B13,'Rates from Tracker'!B:C,2,0) -> Best Pizza LLC | B13: Dublin Commons | C13: =SUMIF(Calculations!G:G,B13,Calculations!L:L) -> 1877.66 | D13: =IF(Table8[[#This Row],[Rate Increase?]]="Yes","",(VLOOKUP(B13,Calculations!G:K,5,0)*100)&"% of "&DOLLAR(SUMIF(Calculations!G:G,B13,Calculations!F:F),2)&" "&B13) -> 5% of $37,553.28 Dublin Commons | E13: =SUMIF(Calculations!G:G,B13,Calculations!J:J) -> 751.08 | F13: =IF(Table8[[#This Row],[Location]]="Belmont Market",1,IF(Table8[[#This Row],[Location]]="Country Club Centre",1,IF(Table8[[#This Row],[Location]]="Naval Air Station Norfolk",0.5,2)))&"% of "&DOLLAR(SUMIF(Calculations!G:G,B13,Calculations!F:F),2)&" "&B13 -> 2% of $37,553.28 Dublin Commons | G13: =IF((SUMIF(Calculations!$G:$G,Table8[[#This Row],[Location]],Calculations!$K:$K)/COUNTIF(Calculations!$G:$G,Table8[[#This Row],[Location]]))<>VLOOKUP(Table8[[#This Row],[Location]],Calculations!G:M,5,0),"Yes","") | H13: =Table8[[#This Row],[CONTINUINGFEE - Net Value]]+Table8[[#This Row],[MARKETINGFEE - Net Value]] -> 2628.74
A14: =VLOOKUP(B14,'Rates from Tracker'!B:C,2,0) -> Cool Dough Development, LLC | B14: Evansville #11 | C14: =SUMIF(Calculations!G:G,B14,Calculations!L:L) -> 638.94 | D14: =IF(Table8[[#This Row],[Rate Increase?]]="Yes","",(VLOOKUP(B14,Calculations!G:K,5,0)*100)&"% of "&DOLLAR(SUMIF(Calculations!G:G,B14,Calculations!F:F),2)&" "&B14) -> 5% of $12,778.75 Evansville #11 | E14: =SUMIF(Calculations!G:G,B14,Calculations!J:J) -> 255.58 | F14: =IF(Table8[[#This Row],[Location]]="Belmont Market",1,IF(Table8[[#This Row],[Location]]="Country Club Centre",1,IF(Table8[[#This Row],[Location]]="Naval Air Station Norfolk",0.5,2)))&"% of "&DOLLAR(SUMIF(Calculations!G:G,B14,Calculations!F:F),2)&" "&B14 -> 2% of $12,778.75 Evansville #11 | G14: =IF((SUMIF(Calculations!$G:$G,Table8[[#This Row],[Location]],Calculations!$K:$K)/COUNTIF(Calculations!$G:$G,Table8[[#This Row],[Location]]))<>VLOOKUP(Table8[[#This Row],[Location]],Calculations!G:M,5,0),"Yes","") | H14: =Table8[[#This Row],[CONTINUINGFEE - Net Value]]+Table8[[#This Row],[MARKETINGFEE - Net Value]] -> 894.52
A15: =VLOOKUP(B15,'Rates from Tracker'!B:C,2,0) -> Best Pizza LLC | B15: Falcon Landing | C15: =SUMIF(Calculations!G:G,B15,Calculations!L:L) -> 918.43 | D15: =IF(Table8[[#This Row],[Rate Increase?]]="Yes","",(VLOOKUP(B15,Calculations!G:K,5,0)*100)&"% of "&DOLLAR(SUMIF(Calculations!G:G,B15,Calculations!F:F),2)&" "&B15) -> 5% of $18,368.47 Falcon Landing | E15: =SUMIF(Calculations!G:G,B15,Calculations!J:J) -> 367.38 | F15: =IF(Table8[[#This Row],[Location]]="Belmont Market",1,IF(Table8[[#This Row],[Location]]="Country Club Centre",1,IF(Table8[[#This Row],[Location]]="Naval Air Station Norfolk",0.5,2)))&"% of "&DOLLAR(SUMIF(Calculations!G:G,B15,Calculations!F:F),2)&" "&B15 -> 2% of $18,368.47 Falcon Landing | G15: =IF((SUMIF(Calculations!$G:$G,Table8[[#This Row],[Location]],Calculations!$K:$K)/COUNTIF(Calculations!$G:$G,Table8[[#This Row],[Location]]))<>VLOOKUP(Table8[[#This Row],[Location]],Calculations!G:M,5,0),"Yes","") | H15: =Table8[[#This Row],[CONTINUINGFEE - Net Value]]+Table8[[#This Row],[MARKETINGFEE - Net Value]] -> 1285.81
A16: =VLOOKUP(B16,'Rates from Tracker'!B:C,2,0) -> Best Pizza LLC | B16: Forest Trace | C16: =SUMIF(Calculations!G:G,B16,Calculations!L:L) -> 1378.7 | D16: =IF(Table8[[#This Row],[Rate Increase?]]="Yes","",(VLOOKUP(B16,Calculations!G:K,5,0)*100)&"% of "&DOLLAR(SUMIF(Calculations!G:G,B16,Calculations!F:F),2)&" "&B16) -> 5% of $27,573.77 Forest Trace | E16: =SUMIF(Calculations!G:G,B16,Calculations!J:J) -> 551.47 | F16: =IF(Table8[[#This Row],[Location]]="Belmont Market",1,IF(Table8[[#This Row],[Location]]="Country Club Centre",1,IF(Table8[[#This Row],[Location]]="Naval Air Station Norfolk",0.5,2)))&"% of "&DOLLAR(SUMIF(Calculations!G:G,B16,Calculations!F:F),2)&" "&B16 -> 2% of $27,573.77 Forest Trace | G16: =IF((SUMIF(Calculations!$G:$G,Table8[[#This Row],[Location]],Calculations!$K:$K)/COUNTIF(Calculations!$G:$G,Table8[[#This Row],[Location]]))<>VLOOKUP(Table8[[#This Row],[Location]],Calculations!G:M,5,0),"Yes","") | H16: =Table8[[#This Row],[CONTINUINGFEE - Net Value]]+Table8[[#This Row],[MARKETINGFEE - Net Value]] -> 1930.17
A17: =VLOOKUP(B17,'Rates from Tracker'!B:C,2,0) -> Paceline Partners, LLC (OH) | B17: Gahanna | C17: =SUMIF(Calculations!G:G,B17,Calculations!L:L) -> 0 | D17: =IF(Table8[[#This Row],[Rate Increase?]]="Yes","",(VLOOKUP(B17,Calculations!G:K,5,0)*100)&"% of "&DOLLAR(SUMIF(Calculations!G:G,B17,Calculations!F:F),2)&" "&B17) -> #DIV/0! | E17: =SUMIF(Calculations!G:G,B17,Calculations!J:J) -> 0 | F17: =IF(Table8[[#This Row],[Location]]="Belmont Market",1,IF(Table8[[#This Row],[Location]]="Country Club Centre",1,IF(Table8[[#This Row],[Location]]="Naval Air Station Norfolk",0.5,2)))&"% of "&DOLLAR(SUMIF(Calculations!G:G,B17,Calculations!F:F),2)&" "&B17 -> 2% of $0.00 Gahanna | G17: =IF((SUMIF(Calculations!$G:$G,Table8[[#This Row],[Location]],Calculations!$K:$K)/COUNTIF(Calculations!$G:$G,Table8[[#This Row],[Location]]))<>VLOOKUP(Table8[[#This Row],[Location]],Calculations!G:M,5,0),"Yes","") -> #DIV/0! | H17: =Table8[[#This Row],[CONTINUINGFEE - Net Value]]+Table8[[#This Row],[MARKETINGFEE - Net Value]] -> 0 | I17: closed
A18: =VLOOKUP(B18,'Rates from Tracker'!B:C,2,0) -> Cool Dough Development, LLC | B18: Hamburg #6 | C18: =SUMIF(Calculations!G:G,B18,Calculations!L:L) -> 1076.23 | D18: =IF(Table8[[#This Row],[Rate Increase?]]="Yes","",(VLOOKUP(B18,Calculations!G:K,5,0)*100)&"% of "&DOLLAR(SUMIF(Calculations!G:G,B18,Calculations!F:F),2)&" "&B18) -> 5% of $21,524.58 Hamburg #6 | E18: =SUMIF(Calculations!G:G,B18,Calculations!J:J) -> 430.5 | F18: =IF(Table8[[#This Row],[Location]]="Belmont Market",1,IF(Table8[[#This Row],[Location]]="Country Club Centre",1,IF(Table8[[#This Row],[Location]]="Naval Air Station Norfolk",0.5,2)))&"% of "&DOLLAR(SUMIF(Calculations!G:G,B18,Calculations!F:F),2)&" "&B18 -> 2% of $21,524.58 Hamburg #6 | G18: =IF((SUMIF(Calculations!$G:$G,Table8[[#This Row],[Location]],Calculations!$K:$K)/COUNTIF(Calculations!$G:$G,Table8[[#This Row],[Location]]))<>VLOOKUP(Table8[[#This Row],[Location]],Calculations!G:M,5,0),"Yes","") | H18: =Table8[[#This Row],[CONTINUINGFEE - Net Value]]+Table8[[#This Row],[MARKETINGFEE - Net Value]] -> 1506.73
A19: =VLOOKUP(B19,'Rates from Tracker'!B:C,2,0) -> Exceed Group Howe Bout Arden | B19: Howe Bout Arden | C19: =SUMIF(Calculations!G:G,B19,Calculations!L:L) -> 1433.01 | D19: =IF(Table8[[#This Row],[Rate Increase?]]="Yes","",(VLOOKUP(B19,Calculations!G:K,5,0)*100)&"% of "&DOLLAR(SUMIF(Calculations!G:G,B19,Calculations!F:F),2)&" "&B19) -> 5% of $28,660.17 Howe Bout Arden | E19: =SUMIF(Calculations!G:G,B19,Calculations!J:J) -> 573.21 | F19: =IF(Table8[[#This Row],[Location]]="Belmont Market",1,IF(Table8[[#This Row],[Location]]="Country Club Centre",1,IF(Table8[[#This Row],[Location]]="Naval Air Station Norfolk",0.5,2)))&"% of "&DOLLAR(SUMIF(Calculations!G:G,B19,Calculations!F:F),2)&" "&B19 -> 2% of $28,660.17 Howe Bout Arden | G19: =IF((SUMIF(Calculations!$G:$G,Table8[[#This Row],[Location]],Calculations!$K:$K)/COUNTIF(Calculations!$G:$G,Table8[[#This Row],[Location]]))<>VLOOKUP(Table8[[#This Row],[Location]],Calculations!G:M,5,0),"Yes","") | H19: =Table8[[#This Row],[CONTINUINGFEE - Net Value]]+Table8[[#This Row],[MARKETINGFEE - Net Value]] -> 2006.22
A20: =VLOOKUP(B20,'Rates from Tracker'!B:C,2,0) -> Southern Pie LLC | B20: Kennesaw | C20: =SUMIF(Calculations!G:G,B20,Calculations!L:L) -> 1033.32 | D20: =IF(Table8[[#This Row],[Rate Increase?]]="Yes","",(VLOOKUP(B20,Calculations!G:K,5,0)*100)&"% of "&DOLLAR(SUMIF(Calculations!G:G,B20,Calculations!F:F),2)&" "&B20) -> 5% of $20,666.22 Kennesaw | E20: =SUMIF(Calculations!G:G,B20,Calculations!J:J) -> 413.33 | F20: =IF(Table8[[#This Row],[Location]]="Belmont Market",1,IF(Table8[[#This Row],[Location]]="Country Club Centre",1,IF(Table8[[#This Row],[Location]]="Naval Air Station Norfolk",0.5,2)))&"% of "&DOLLAR(SUMIF(Calculations!G:G,B20,Calculations!F:F),2)&" "&B20 -> 2% of $20,666.22 Kennesaw | G20: =IF((SUMIF(Calculations!$G:$G,Table8[[#This Row],[Location]],Calculations!$K:$K)/COUNTIF(Calculations!$G:$G,Table8[[#This Row],[Location]]))<>VLOOKUP(Table8[[#This Row],[Location]],Calculations!G:M,5,0),"Yes","") | H20: =Table8[[#This Row],[CONTINUINGFEE - Net Value]]+Table8[[#This Row],[MARKETINGFEE - Net Value]] -> 1446.65
A21: =VLOOKUP(B21,'Rates from Tracker'!B:C,2,0) -> Paceline Partners, LLC (KS/MO) | B21: Liberty Triangle | C21: =SUMIF(Calculations!G:G,B21,Calculations!L:L) -> 0 | D21: =IF(Table8[[#This Row],[Rate Increase?]]="Yes","",(VLOOKUP(B21,Calculations!G:K,5,0)*100)&"% of "&DOLLAR(SUMIF(Calculations!G:G,B21,Calculations!F:F),2)&" "&B21) -> #DIV/0! | E21: =SUMIF(Calculations!G:G,B21,Calculations!J:J) -> 0 | F21: =IF(Table8[[#This Row],[Location]]="Belmont Market",1,IF(Table8[[#This Row],[Location]]="Country Club Centre",1,IF(Table8[[#This Row],[Location]]="Naval Air Station Norfolk",0.5,2)))&"% of "&DOLLAR(SUMIF(Calculations!G:G,B21,Calculations!F:F),2)&" "&B21 -> 2% of $0.00 Liberty Triangle | G21: =IF((SUMIF(Calculations!$G:$G,Table8[[#This Row],[Location]],Calculations!$K:$K)/COUNTIF(Calculations!$G:$G,Table8[[#This Row],[Location]]))<>VLOOKUP(Table8[[#This Row],[Location]],Calculations!G:M,5,0),"Yes","") -> #DIV/0! | H21: =Table8[[#This Row],[CONTINUINGFEE - Net Value]]+Table8[[#This Row],[MARKETINGFEE - Net Value]] -> 0 | I21: closed
A22: =VLOOKUP(B22,'Rates from Tracker'!B:C,2,0) -> TSFR Pizza LLC | B22: LIVONIA | C22: =SUMIF(Calculations!G:G,B22,Calculations!L:L) -> 1109.85 | D22: =IF(Table8[[#This Row],[Rate Increase?]]="Yes","",(VLOOKUP(B22,Calculations!G:K,5,0)*100)&"% of "&DOLLAR(SUMIF(Calculations!G:G,B22,Calculations!F:F),2)&" "&B22) -> 5% of $22,197.05 LIVONIA | E22: =SUMIF(Calculations!G:G,B22,Calculations!J:J) -> 443.94 | F22: =IF(Table8[[#This Row],[Location]]="Belmont Market",1,IF(Table8[[#This Row],[Location]]="Country Club Centre",1,IF(Table8[[#This Row],[Location]]="Naval Air Station Norfolk",0.5,2)))&"% of "&DOLLAR(SUMIF(Calculations!G:G,B22,Calculations!F:F),2)&" "&B22 -> 2% of $22,197.05 LIVONIA | G22: =IF((SUMIF(Calculations!$G:$G,Table8[[#This Row],[Location]],Calculations!$K:$K)/COUNTIF(Calculations!$G:$G,Table8[[#This Row],[Location]]))<>VLOOKUP(Table8[[#This Row],[Location]],Calculations!G:M,5,0),"Yes","") | H22: =Table8[[#This Row],[CONTINUINGFEE - Net Value]]+Table8[[#This Row],[MARKETINGFEE - Net Value]] -> 1553.79
A23: =VLOOKUP(B23,'Rates from Tracker'!B:C,2,0) -> Best Pizza LLC | B23: Lowry | C23: =SUMIF(Calculations!G:G,B23,Calculations!L:L) -> 938.57 | D23: =IF(Table8[[#This Row],[Rate Increase?]]="Yes","",(VLOOKUP(B23,Calculations!G:K,5,0)*100)&"% of "&DOLLAR(SUMIF(Calculations!G:G,B23,Calculations!F:F),2)&" "&B23) -> 5% of $18,771.04 Lowry | E23: =SUMIF(Calculations!G:G,B23,Calculations!J:J) -> 375.42 | F23: =IF(Table8[[#This Row],[Location]]="Belmont Market",1,IF(Table8[[#This Row],[Location]]="Country Club Centre",1,IF(Table8[[#This Row],[Location]]="Naval Air Station Norfolk",0.5,2)))&"% of "&DOLLAR(SUMIF(Calculations!G:G,B23,Calculations!F:F),2)&" "&B23 -> 2% of $18,771.04 Lowry | G23: =IF((SUMIF(Calculations!$G:$G,Table8[[#This Row],[Location]],Calculations!$K:$K)/COUNTIF(Calculations!$G:$G,Table8[[#This Row],[Location]]))<>VLOOKUP(Table8[[#This Row],[Location]],Calculations!G:M,5,0),"Yes","") | H23: =Table8[[#This Row],[CONTINUINGFEE - Net Value]]+Table8[[#This Row],[MARKETINGFEE - Net Value]] -> 1313.99
A24: =VLOOKUP(B24,'Rates from Tracker'!B:C,2,0) -> Best Pizza LLC | B24: McCaslin Marketplace | C24: =SUMIF(Calculations!G:G,B24,Calculations!L:L) -> 1099.37 | D24: =IF(Table8[[#This Row],[Rate Increase?]]="Yes","",(VLOOKUP(B24,Calculations!G:K,5,0)*100)&"% of "&DOLLAR(SUMIF(Calculations!G:G,B24,Calculations!F:F),2)&" "&B24) -> 5% of $21,987.26 McCaslin Marketplace | E24: =SUMIF(Calculations!G:G,B24,Calculations!J:J) -> 439.74 | F24: =IF(Table8[[#This Row],[Location]]="Belmont Market",1,IF(Table8[[#This Row],[Location]]="Country Club Centre",1,IF(Table8[[#This Row],[Location]]="Naval Air Station Norfolk",0.5,2)))&"% of "&DOLLAR(SUMIF(Calculations!G:G,B24,Calculations!F:F),2)&" "&B24 -> 2% of $21,987.26 McCaslin Marketplace | G24: =IF((SUMIF(Calculations!$G:$G,Table8[[#This Row],[Location]],Calculations!$K:$K)/COUNTIF(Calculations!$G:$G,Table8[[#This Row],[Location]]))<>VLOOKUP(Table8[[#This Row],[Location]],Calculations!G:M,5,0),"Yes","") | H24: =Table8[[#This Row],[CONTINUINGFEE - Net Value]]+Table8[[#This Row],[MARKETINGFEE - Net Value]] -> 1539.11
A25: =VLOOKUP(B25,'Rates from Tracker'!B:C,2,0) -> Paceline Partners, LLC (OH) | B25: Morse Road | C25: =SUMIF(Calculations!G:G,B25,Calculations!L:L) -> 0 | D25: =IF(Table8[[#This Row],[Rate Increase?]]="Yes","",(VLOOKUP(B25,Calculations!G:K,5,0)*100)&"% of "&DOLLAR(SUMIF(Calculations!G:G,B25,Calculations!F:F),2)&" "&B25) -> #DIV/0! | E25: =SUMIF(Calculations!G:G,B25,Calculations!J:J) -> 0 | F25: =IF(Table8[[#This Row],[Location]]="Belmont Market",1,IF(Table8[[#This Row],[Location]]="Country Club Centre",1,IF(Table8[[#This Row],[Location]]="Naval Air Station Norfolk",0.5,2)))&"% of "&DOLLAR(SUMIF(Calculations!G:G,B25,Calculations!F:F),2)&" "&B25 -> 2% of $0.00 Morse Road | G25: =IF((SUMIF(Calculations!$G:$G,Table8[[#This Row],[Location]],Calculations!$K:$K)/COUNTIF(Calculations!$G:$G,Table8[[#This Row],[Location]]))<>VLOOKUP(Table8[[#This Row],[Location]],Calculations!G:M,5,0),"Yes","") -> #DIV/0! | H25: =Table8[[#This Row],[CONTINUINGFEE - Net Value]]+Table8[[#This Row],[MARKETINGFEE - Net Value]] -> 0 | I25: closed
A26: =VLOOKUP(B26,'Rates from Tracker'!B:C,2,0) -> Rolling Dough LLC | B26: NE Columbia | C26: =SUMIF(Calculations!G:G,B26,Calculations!L:L) -> 861.64 | D26: =IF(Table8[[#This Row],[Rate Increase?]]="Yes","",(VLOOKUP(B26,Calculations!G:K,5,0)*100)&"% of "&DOLLAR(SUMIF(Calculations!G:G,B26,Calculations!F:F),2)&" "&B26) -> 5% of $17,232.81 NE Columbia | E26: =SUMIF(Calculations!G:G,B26,Calculations!J:J) -> 344.65 | F26: =IF(Table8[[#This Row],[Location]]="Belmont Market",1,IF(Table8[[#This Row],[Location]]="Country Club Centre",1,IF(Table8[[#This Row],[Location]]="Naval Air Station Norfolk",0.5,2)))&"% of "&DOLLAR(SUMIF(Calculations!G:G,B26,Calculations!F:F),2)&" "&B26 -> 2% of $17,232.81 NE Columbia | G26: =IF((SUMIF(Calculations!$G:$G,Table8[[#This Row],[Location]],Calculations!$K:$K)/COUNTIF(Calculations!$G:$G,Table8[[#This Row],[Location]]))<>VLOOKUP(Table8[[#This Row],[Location]],Calculations!G:M,5,0),"Yes","") | H26: =Table8[[#This Row],[CONTINUINGFEE - Net Value]]+Table8[[#This Row],[MARKETINGFEE - Net Value]] -> 1206.29
A27: =VLOOKUP(B27,'Rates from Tracker'!B:C,2,0) -> Rolling Dough LLC | B27: North Charleston | C27: =SUMIF(Calculations!G:G,B27,Calculations!L:L) -> 651.74 | D27: =IF(Table8[[#This Row],[Rate Increase?]]="Yes","",(VLOOKUP(B27,Calculations!G:K,5,0)*100)&"% of "&DOLLAR(SUMIF(Calculations!G:G,B27,Calculations!F:F),2)&" "&B27) -> 5% of $13,034.60 North Charleston | E27: =SUMIF(Calculations!G:G,B27,Calculations!J:J) -> 260.68 | F27: =IF(Table8[[#This Row],[Location]]="Belmont Market",1,IF(Table8[[#This Row],[Location]]="Country Club Centre",1,IF(Table8[[#This Row],[Location]]="Naval Air Station Norfolk",0.5,2)))&"% of "&DOLLAR(SUMIF(Calculations!G:G,B27,Calculations!F:F),2)&" "&B27 -> 2% of $13,034.60 North Charleston | G27: =IF((SUMIF(Calculations!$G:$G,Table8[[#This Row],[Location]],Calculations!$K:$K)/COUNTIF(Calculations!$G:$G,Table8[[#This Row],[Location]]))<>VLOOKUP(Table8[[#This Row],[Location]],Calculations!G:M,5,0),"Yes","") | H27: =Table8[[#This Row],[CONTINUINGFEE - Net Value]]+Table8[[#This Row],[MARKETINGFEE - Net Value]] -> 912.42
A28: =VLOOKUP(B28,'Rates from Tracker'!B:C,2,0) -> Rolling Dough LLC | B28: North Myrtle Beach | C28: =SUMIF(Calculations!G:G,B28,Calculations!L:L) -> 0 | D28: =IF(Table8[[#This Row],[Rate Increase?]]="Yes","",(VLOOKUP(B28,Calculations!G:K,5,0)*100)&"% of "&DOLLAR(SUMIF(Calculations!G:G,B28,Calculations!F:F),2)&" "&B28) -> #DIV/0! | E28: =SUMIF(Calculations!G:G,B28,Calculations!J:J) -> 0 | F28: =IF(Table8[[#This Row],[Location]]="Belmont Market",1,IF(Table8[[#This Row],[Location]]="Country Club Centre",1,IF(Table8[[#This Row],[Location]]="Naval Air Station Norfolk",0.5,2)))&"% of "&DOLLAR(SUMIF(Calculations!G:G,B28,Calculations!F:F),2)&" "&B28 -> 2% of $0.00 North Myrtle Beach | G28: =IF((SUMIF(Calculations!$G:$G,Table8[[#This Row],[Location]],Calculations!$K:$K)/COUNTIF(Calculations!$G:$G,Table8[[#This Row],[Location]]))<>VLOOKUP(Table8[[#This Row],[Location]],Calculations!G:M,5,0),"Yes","") -> #DIV/0! | H28: =Table8[[#This Row],[CONTINUINGFEE - Net Value]]+Table8[[#This Row],[MARKETINGFEE - Net Value]] -> 0
A29: =VLOOKUP(B29,'Rates from Tracker'!B:C,2,0) -> TSFR Pizza LLC | B29: Northville | C29: =SUMIF(Calculations!G:G,B29,Calculations!L:L) -> 0 | D29: =IF(Table8[[#This Row],[Rate Increase?]]="Yes","",(VLOOKUP(B29,Calculations!G:K,5,0)*100)&"% of "&DOLLAR(SUMIF(Calculations!G:G,B29,Calculations!F:F),2)&" "&B29) -> #DIV/0! | E29: =SUMIF(Calculations!G:G,B29,Calculations!J:J) -> 0 | F29: =IF(Table8[[#This Row],[Location]]="Belmont Market",1,IF(Table8[[#This Row],[Location]]="Country Club Centre",1,IF(Table8[[#This Row],[Location]]="Naval Air Station Norfolk",0.5,2)))&"% of "&DOLLAR(SUMIF(Calculations!G:G,B29,Calculations!F:F),2)&" "&B29 -> 2% of $0.00 Northville | G29: =IF((SUMIF(Calculations!$G:$G,Table8[[#This Row],[Location]],Calculations!$K:$K)/COUNTIF(Calculations!$G:$G,Table8[[#This Row],[Location]]))<>VLOOKUP(Table8[[#This Row],[Location]],Calculations!G:M,5,0),"Yes","") -> #DIV/0! | H29: =Table8[[#This Row],[CONTINUINGFEE - Net Value]]+Table8[[#This Row],[MARKETINGFEE - Net Value]] -> 0 | I29: Closed
A30: =VLOOKUP(B30,'Rates from Tracker'!B:C,2,0) -> Cool Dough Development, LLC | B30: Oakley #2 | C30: =SUMIF(Calculations!G:G,B30,Calculations!L:L) -> 0 | D30: =IF(Table8[[#This Row],[Rate Increase?]]="Yes","",(VLOOKUP(B30,Calculations!G:K,5,0)*100)&"% of "&DOLLAR(SUMIF(Calculations!G:G,B30,Calculations!F:F),2)&" "&B30) -> #DIV/0! | E30: =SUMIF(Calculations!G:G,B30,Calculations!J:J) -> 0 | F30: =IF(Table8[[#This Row],[Location]]="Belmont Market",1,IF(Table8[[#This Row],[Location]]="Country Club Centre",1,IF(Table8[[#This Row],[Location]]="Naval Air Station Norfolk",0.5,2)))&"% of "&DOLLAR(SUMIF(Calculations!G:G,B30,Calculations!F:F),2)&" "&B30 -> 2% of $0.00 Oakley #2 | G30: =IF((SUMIF(Calculations!$G:$G,Table8[[#This Row],[Location]],Calculations!$K:$K)/COUNTIF(Calculations!$G:$G,Table8[[#This Row],[Location]]))<>VLOOKUP(Table8[[#This Row],[Location]],Calculations!G:M,5,0),"Yes","") -> #DIV/0! | H30: =Table8[[#This Row],[CONTINUINGFEE - Net Value]]+Table8[[#This Row],[MARKETINGFEE - Net Value]] -> 0 | I30: closed
A31: =VLOOKUP(B31,'Rates from Tracker'!B:C,2,0) -> Cool Dough Development, LLC | B31: Owensboro #8 | C31: =SUMIF(Calculations!G:G,B31,Calculations!L:L) -> 0 | D31: =IF(Table8[[#This Row],[Rate Increase?]]="Yes","",(VLOOKUP(B31,Calculations!G:K,5,0)*100)&"% of "&DOLLAR(SUMIF(Calculations!G:G,B31,Calculations!F:F),2)&" "&B31) -> #DIV/0! | E31: =SUMIF(Calculations!G:G,B31,Calculations!J:J) -> 0 | F31: =IF(Table8[[#This Row],[Location]]="Belmont Market",1,IF(Table8[[#This Row],[Location]]="Country Club Centre",1,IF(Table8[[#This Row],[Location]]="Naval Air Station Norfolk",0.5,2)))&"% of "&DOLLAR(SUMIF(Calculations!G:G,B31,Calculations!F:F),2)&" "&B31 -> 2% of $0.00 Owensboro #8 | G31: =IF((SUMIF(Calculations!$G:$G,Table8[[#This Row],[Location]],Calculations!$K:$K)/COUNTIF(Calculations!$G:$G,Table8[[#This Row],[Location]]))<>VLOOKUP(Table8[[#This Row],[Location]],Calculations!G:M,5,0),"Yes","") -> #DIV/0! | H31: =Table8[[#This Row],[CONTINUINGFEE - Net Value]]+Table8[[#This Row],[MARKETINGFEE - Net Value]] -> 0
A32: =VLOOKUP(B32,'Rates from Tracker'!B:C,2,0) -> Best Pizza LLC | B32: Park Meadows | C32: =SUMIF(Calculations!G:G,B32,Calculations!L:L) -> 1113.72 | D32: =IF(Table8[[#This Row],[Rate Increase?]]="Yes","",(VLOOKUP(B32,Calculations!G:K,5,0)*100)&"% of "&DOLLAR(SUMIF(Calculations!G:G,B32,Calculations!F:F),2)&" "&B32) -> 5% of $22,274.18 Park Meadows | E32: =SUMIF(Calculations!G:G,B32,Calculations!J:J) -> 445.47 | F32: =IF(Table8[[#This Row],[Location]]="Belmont Market",1,IF(Table8[[#This Row],[Location]]="Country Club Centre",1,IF(Table8[[#This Row],[Location]]="Naval Air Station Norfolk",0.5,2)))&"% of "&DOLLAR(SUMIF(Calculations!G:G,B32,Calculations!F:F),2)&" "&B32 -> 2% of $22,274.18 Park Meadows | G32: =IF((SUMIF(Calculations!$G:$G,Table8[[#This Row],[Location]],Calculations!$K:$K)/COUNTIF(Calculations!$G:$G,Table8[[#This Row],[Location]]))<>VLOOKUP(Table8[[#This Row],[Location]],Calculations!G:M,5,0),"Yes","") | H32: =Table8[[#This Row],[CONTINUINGFEE - Net Value]]+Table8[[#This Row],[MARKETINGFEE - Net Value]] -> 1559.19
A33: =VLOOKUP(B33,'Rates from Tracker'!B:C,2,0) -> Paceline Partners, LLC (KS/MO) | B33: Raymore | C33: =SUMIF(Calculations!G:G,B33,Calculations!L:L) -> 0 | D33: =IF(Table8[[#This Row],[Rate Increase?]]="Yes","",(VLOOKUP(B33,Calculations!G:K,5,0)*100)&"% of "&DOLLAR(SUMIF(Calculations!G:G,B33,Calculations!F:F),2)&" "&B33) -> #DIV/0! | E33: =SUMIF(Calculations!G:G,B33,Calculations!J:J) -> 0 | F33: =IF(Table8[[#This Row],[Location]]="Belmont Market",1,IF(Table8[[#This Row],[Location]]="Country Club Centre",1,IF(Table8[[#This Row],[Location]]="Naval Air Station Norfolk",0.5,2)))&"% of "&DOLLAR(SUMIF(Calculations!G:G,B33,Calculations!F:F),2)&" "&B33 -> 2% of $0.00 Raymore | G33: =IF((SUMIF(Calculations!$G:$G,Table8[[#This Row],[Location]],Calculations!$K:$K)/COUNTIF(Calculations!$G:$G,Table8[[#This Row],[Location]]))<>VLOOKUP(Table8[[#This Row],[Location]],Calculations!G:M,5,0),"Yes","") -> #DIV/0! | H33: =Table8[[#This Row],[CONTINUINGFEE - Net Value]]+Table8[[#This Row],[MARKETINGFEE - Net Value]] -> 0 | I33: closed
A34: =VLOOKUP(B34,'Rates from Tracker'!B:C,2,0) -> Exceed Group REDDING | B34: REDDING | C34: =SUMIF(Calculations!G:G,B34,Calculations!L:L) -> 1279.28 | D34: =IF(Table8[[#This Row],[Rate Increase?]]="Yes","",(VLOOKUP(B34,Calculations!G:K,5,0)*100)&"% of "&DOLLAR(SUMIF(Calculations!G:G,B34,Calculations!F:F),2)&" "&B34) -> 5% of $25,585.68 REDDING | E34: =SUMIF(Calculations!G:G,B34,Calculations!J:J) -> 511.72 | F34: =IF(Table8[[#This Row],[Location]]="Belmont Market",1,IF(Table8[[#This Row],[Location]]="Country Club Centre",1,IF(Table8[[#This Row],[Location]]="Naval Air Station Norfolk",0.5,2)))&"% of "&DOLLAR(SUMIF(Calculations!G:G,B34,Calculations!F:F),2)&" "&B34 -> 2% of $25,585.68 REDDING | H34: =Table8[[#This Row],[CONTINUINGFEE - Net Value]]+Table8[[#This Row],[MARKETINGFEE - Net Value]] -> 1791
A35: =VLOOKUP(B35,'Rates from Tracker'!B:C,2,0) -> Exceed Group Redfield Promenade | B35: Redfield Promenade | C35: =SUMIF(Calculations!G:G,B35,Calculations!L:L) -> 769.16 | D35: =IF(Table8[[#This Row],[Rate Increase?]]="Yes","",(VLOOKUP(B35,Calculations!G:K,5,0)*100)&"% of "&DOLLAR(SUMIF(Calculations!G:G,B35,Calculations!F:F),2)&" "&B35) -> 5% of $15,383.16 Redfield Promenade | E35: =SUMIF(Calculations!G:G,B35,Calculations!J:J) -> 307.67 | F35: =IF(Table8[[#This Row],[Location]]="Belmont Market",1,IF(Table8[[#This Row],[Location]]="Country Club Centre",1,IF(Table8[[#This Row],[Location]]="Naval Air Station Norfolk",0.5,2)))&"% of "&DOLLAR(SUMIF(Calculations!G:G,B35,Calculations!F:F),2)&" "&B35 -> 2% of $15,383.16 Redfield Promenade | G35: =IF((SUMIF(Calculations!$G:$G,Table8[[#This Row],[Location]],Calculations!$K:$K)/COUNTIF(Calculations!$G:$G,Table8[[#This Row],[Location]]))<>VLOOKUP(Table8[[#This Row],[Location]],Calculations!G:M,5,0),"Yes","") | H35: =Table8[[#This Row],[CONTINUINGFEE - Net Value]]+Table8[[#This Row],[MARKETINGFEE - Net Value]] -> 1076.83
A36: =VLOOKUP(B36,'Rates from Tracker'!B:C,2,0) -> TSFR Pizza LLC | B36: Rochester Hills | C36: =SUMIF(Calculations!G:G,B36,Calculations!L:L) -> 0 | D36: =IF(Table8[[#This Row],[Rate Increase?]]="Yes","",(VLOOKUP(B36,Calculations!G:K,5,0)*100)&"% of "&DOLLAR(SUMIF(Calculations!G:G,B36,Calculations!F:F),2)&" "&B36) -> #DIV/0! | E36: =SUMIF(Calculations!G:G,B36,Calculations!J:J) -> 0 | F36: =IF(Table8[[#This Row],[Location]]="Belmont Market",1,IF(Table8[[#This Row],[Location]]="Country Club Centre",1,IF(Table8[[#This Row],[Location]]="Naval Air Station Norfolk",0.5,2)))&"% of "&DOLLAR(SUMIF(Calculations!G:G,B36,Calculations!F:F),2)&" "&B36 -> 2% of $0.00 Rochester Hills | G36: =IF((SUMIF(Calculations!$G:$G,Table8[[#This Row],[Location]],Calculations!$K:$K)/COUNTIF(Calculations!$G:$G,Table8[[#This Row],[Location]]))<>VLOOKUP(Table8[[#This Row],[Location]],Calculations!G:M,5,0),"Yes","") -> #DIV/0! | H36: =Table8[[#This Row],[CONTINUINGFEE - Net Value]]+Table8[[#This Row],[MARKETINGFEE - Net Value]] -> 0 | I36: Closed
A37: =VLOOKUP(B37,'Rates from Tracker'!B:C,2,0) -> Exceed Group ROCKLIN | B37: ROCKLIN | C37: =SUMIF(Calculations!G:G,B37,Calculations!L:L) -> 860.2 | D37: =IF(Table8[[#This Row],[Rate Increase?]]="Yes","",(VLOOKUP(B37,Calculations!G:K,5,0)*100)&"% of "&DOLLAR(SUMIF(Calculations!G:G,B37,Calculations!F:F),2)&" "&B37) -> 5% of $17,204.09 ROCKLIN | E37: =SUMIF(Calculations!G:G,B37,Calculations!J:J) -> 344.08 | F37: =IF(Table8[[#This Row],[Location]]="Belmont Market",1,IF(Table8[[#This Row],[Location]]="Country Club Centre",1,IF(Table8[[#This Row],[Location]]="Naval Air Station Norfolk",0.5,2)))&"% of "&DOLLAR(SUMIF(Calculations!G:G,B37,Calculations!F:F),2)&" "&B37 -> 2% of $17,204.09 ROCKLIN | G37: =IF((SUMIF(Calculations!$G:$G,Table8[[#This Row],[Location]],Calculations!$K:$K)/COUNTIF(Calculations!$G:$G,Table8[[#This Row],[Location]]))<>VLOOKUP(Table8[[#This Row],[Location]],Calculations!G:M,5,0),"Yes","") | H37: =Table8[[#This Row],[CONTINUINGFEE - Net Value]]+Table8[[#This Row],[MARKETINGFEE - Net Value]] -> 1204.28
A38: =VLOOKUP(B38,'Rates from Tracker'!B:C,2,0) -> Best Pizza LLC | B38: S Academy Highlands | C38: =SUMIF(Calculations!G:G,B38,Calculations!L:L) -> 1259.32 | D38: =IF(Table8[[#This Row],[Rate Increase?]]="Yes","",(VLOOKUP(B38,Calculations!G:K,5,0)*100)&"% of "&DOLLAR(SUMIF(Calculations!G:G,B38,Calculations!F:F),2)&" "&B38) -> 5% of $25,186.63 S Academy Highlands | E38: =SUMIF(Calculations!G:G,B38,Calculations!J:J) -> 503.73 | F38: =IF(Table8[[#This Row],[Location]]="Belmont Market",1,IF(Table8[[#This Row],[Location]]="Country Club Centre",1,IF(Table8[[#This Row],[Location]]="Naval Air Station Norfolk",0.5,2)))&"% of "&DOLLAR(SUMIF(Calculations!G:G,B38,Calculations!F:F),2)&" "&B38 -> 2% of $25,186.63 S Academy Highlands | G38: =IF((SUMIF(Calculations!$G:$G,Table8[[#This Row],[Location]],Calculations!$K:$K)/COUNTIF(Calculations!$G:$G,Table8[[#This Row],[Location]]))<>VLOOKUP(Table8[[#This Row],[Location]],Calculations!G:M,5,0),"Yes","") | H38: =Table8[[#This Row],[CONTINUINGFEE - Net Value]]+Table8[[#This Row],[MARKETINGFEE - Net Value]] -> 1763.05
A39: =VLOOKUP(B39,'Rates from Tracker'!B:C,2,0) -> Paceline Partners, LLC (OH) | B39: Sawmill Road | C39: =SUMIF(Calculations!G:G,B39,Calculations!L:L) -> 0 | D39: =IF(Table8[[#This Row],[Rate Increase?]]="Yes","",(VLOOKUP(B39,Calculations!G:K,5,0)*100)&"% of "&DOLLAR(SUMIF(Calculations!G:G,B39,Calculations!F:F),2)&" "&B39) -> #DIV/0! | E39: =SUMIF(Calculations!G:G,B39,Calculations!J:J) -> 0 | F39: =IF(Table8[[#This Row],[Location]]="Belmont Market",1,IF(Table8[[#This Row],[Location]]="Country Club Centre",1,IF(Table8[[#This Row],[Location]]="Naval Air Station Norfolk",0.5,2)))&"% of "&DOLLAR(SUMIF(Calculations!G:G,B39,Calculations!F:F),2)&" "&B39 -> 2% of $0.00 Sawmill Road | G39: =IF((SUMIF(Calculations!$G:$G,Table8[[#This Row],[Location]],Calculations!$K:$K)/COUNTIF(Calculations!$G:$G,Table8[[#This Row],[Location]]))<>VLOOKUP(Table8[[#This Row],[Location]],Calculations!G:M,5,0),"Yes","") -> #DIV/0! | H39: =Table8[[#This Row],[CONTINUINGFEE - Net Value]]+Table8[[#This Row],[MARKETINGFEE - Net Value]] -> 0 | I39: closed
A40: =VLOOKUP(B40,'Rates from Tracker'!B:C,2,0) -> Rolling Dough LLC | B40: South Myrtle Beach | C40: =SUMIF(Calculations!G:G,B40,Calculations!L:L) -> 0 | D40: =IF(Table8[[#This Row],[Rate Increase?]]="Yes","",(VLOOKUP(B40,Calculations!G:K,5,0)*100)&"% of "&DOLLAR(SUMIF(Calculations!G:G,B40,Calculations!F:F),2)&" "&B40) -> #DIV/0! | E40: =SUMIF(Calculations!G:G,B40,Calculations!J:J) -> 0 | F40: =IF(Table8[[#This Row],[Location]]="Belmont Market",1,IF(Table8[[#This Row],[Location]]="Country Club Centre",1,IF(Table8[[#This Row],[Location]]="Naval Air Station Norfolk",0.5,2)))&"% of "&DOLLAR(SUMIF(Calculations!G:G,B40,Calculations!F:F),2)&" "&B40 -> 2% of $0.00 South Myrtle Beach | G40: =IF((SUMIF(Calculations!$G:$G,Table8[[#This Row],[Location]],Calculations!$K:$K)/COUNTIF(Calculations!$G:$G,Table8[[#This Row],[Location]]))<>VLOOKUP(Table8[[#This Row],[Location]],Calculations!G:M,5,0),"Yes","") -> #DIV/0! | H40: =Table8[[#This Row],[CONTINUINGFEE - Net Value]]+Table8[[#This Row],[MARKETINGFEE - Net Value]] -> 0
A41: =VLOOKUP(B41,'Rates from Tracker'!B:C,2,0) -> Paceline Partners, LLC (KS/MO) | B41: Olathe | C41: =SUMIF(Calculations!G:G,B41,Calculations!L:L) -> 0 | D41: =IF(Table8[[#This Row],[Rate Increase?]]="Yes","",(VLOOKUP(B41,Calculations!G:K,5,0)*100)&"% of "&DOLLAR(SUMIF(Calculations!G:G,B41,Calculations!F:F),2)&" "&B41) -> #DIV/0! | E41: =SUMIF(Calculations!G:G,B41,Calculations!J:J) -> 0 | F41: =IF(Table8[[#This Row],[Location]]="Belmont Market",1,IF(Table8[[#This Row],[Location]]="Country Club Centre",1,IF(Table8[[#This Row],[Location]]="Naval Air Station Norfolk",0.5,2)))&"% of "&DOLLAR(SUMIF(Calculations!G:G,B41,Calculations!F:F),2)&" "&B41 -> 2% of $0.00 Olathe | G41: =IF((SUMIF(Calculations!$G:$G,Table8[[#This Row],[Location]],Calculations!$K:$K)/COUNTIF(Calculations!$G:$G,Table8[[#This Row],[Location]]))<>VLOOKUP(Table8[[#This Row],[Location]],Calculations!G:M,5,0),"Yes","") -> #DIV/0! | H41: =Table8[[#This Row],[CONTINUINGFEE - Net Value]]+Table8[[#This Row],[MARKETINGFEE - Net Value]] -> 0 | I41: closed
A42: =VLOOKUP(B42,'Rates from Tracker'!B:C,2,0) -> Rolling Dough LLC | B42: Carolina Forest | C42: =SUMIF(Calculations!G:G,B42,Calculations!L:L) -> 0 | D42: =IF(Table8[[#This Row],[Rate Increase?]]="Yes","",(VLOOKUP(B42,Calculations!G:K,5,0)*100)&"% of "&DOLLAR(SUMIF(Calculations!G:G,B42,Calculations!F:F),2)&" "&B42) -> #DIV/0! | E42: =SUMIF(Calculations!G:G,B42,Calculations!J:J) -> 0 | F42: =IF(Table8[[#This Row],[Location]]="Belmont Market",1,IF(Table8[[#This Row],[Location]]="Country Club Centre",1,IF(Table8[[#This Row],[Location]]="Naval Air Station Norfolk",0.5,2)))&"% of "&DOLLAR(SUMIF(Calculations!G:G,B42,Calculations!F:F),2)&" "&B42 -> 2% of $0.00 Carolina Forest | G42: =IF((SUMIF(Calculations!$G:$G,Table8[[#This Row],[Location]],Calculations!$K:$K)/COUNTIF(Calculations!$G:$G,Table8[[#This Row],[Location]]))<>VLOOKUP(Table8[[#This Row],[Location]],Calculations!G:M,5,0),"Yes","") -> #DIV/0! | H42: =Table8[[#This Row],[CONTINUINGFEE - Net Value]]+Table8[[#This Row],[MARKETINGFEE - Net Value]] -> 0
A43: =VLOOKUP(B43,'Rates from Tracker'!B:C,2,0) -> Cool Dough Development, LLC | B43: West Chester #3 | C43: =SUMIF(Calculations!G:G,B43,Calculations!L:L) -> 0 | D43: =IF(Table8[[#This Row],[Rate Increase?]]="Yes","",(VLOOKUP(B43,Calculations!G:K,5,0)*100)&"% of "&DOLLAR(SUMIF(Calculations!G:G,B43,Calculations!F:F),2)&" "&B43) -> #DIV/0! | E43: =SUMIF(Calculations!G:G,B43,Calculations!J:J) -> 0 | F43: =IF(Table8[[#This Row],[Location]]="Belmont Market",1,IF(Table8[[#This Row],[Location]]="Country Club Centre",1,IF(Table8[[#This Row],[Location]]="Naval Air Station Norfolk",0.5,2)))&"% of "&DOLLAR(SUMIF(Calculations!G:G,B43,Calculations!F:F),2)&" "&B43 -> 2% of $0.00 West Chester #3 | G43: =IF((SUMIF(Calculations!$G:$G,Table8[[#This Row],[Location]],Calculations!$K:$K)/COUNTIF(Calculations!$G:$G,Table8[[#This Row],[Location]]))<>VLOOKUP(Table8[[#This Row],[Location]],Calculations!G:M,5,0),"Yes","") -> #DIV/0! | H43: =Table8[[#This Row],[CONTINUINGFEE - Net Value]]+Table8[[#This Row],[MARKETINGFEE - Net Value]] -> 0 | I43: Closed
A44: =VLOOKUP(B44,'Rates from Tracker'!B:C,2,0) -> Best Pizza LLC | B44: Westminster Promenade | C44: =SUMIF(Calculations!G:G,B44,Calculations!L:L) -> 1616.21 | D44: =IF(Table8[[#This Row],[Rate Increase?]]="Yes","",(VLOOKUP(B44,Calculations!G:K,5,0)*100)&"% of "&DOLLAR(SUMIF(Calculations!G:G,B44,Calculations!F:F),2)&" "&B44) -> 5% of $32,324.13 Westminster Promenade | E44: =SUMIF(Calculations!G:G,B44,Calculations!J:J) -> 646.49 | F44: =IF(Table8[[#This Row],[Location]]="Belmont Market",1,IF(Table8[[#This Row],[Location]]="Country Club Centre",1,IF(Table8[[#This Row],[Location]]="Naval Air Station Norfolk",0.5,2)))&"% of "&DOLLAR(SUMIF(Calculations!G:G,B44,Calculations!F:F),2)&" "&B44 -> 2% of $32,324.13 Westminster Promenade | G44: =IF((SUMIF(Calculations!$G:$G,Table8[[#This Row],[Location]],Calculations!$K:$K)/COUNTIF(Calculations!$G:$G,Table8[[#This Row],[Location]]))<>VLOOKUP(Table8[[#This Row],[Location]],Calculations!G:M,5,0),"Yes","") | H44: =Table8[[#This Row],[CONTINUINGFEE - Net Value]]+Table8[[#This Row],[MARKETINGFEE - Net Value]] -> 2262.7
A45: =VLOOKUP(B45,'Rates from Tracker'!B:C,2,0) -> Rolling Dough LLC | B45: Westwood Plaza | C45: =SUMIF(Calculations!G:G,B45,Calculations!L:L) -> 769.59 | D45: =IF(Table8[[#This Row],[Rate Increase?]]="Yes","",(VLOOKUP(B45,Calculations!G:K,5,0)*100)&"% of "&DOLLAR(SUMIF(Calculations!G:G,B45,Calculations!F:F),2)&" "&B45) -> 5% of $15,391.73 Westwood Plaza | E45: =SUMIF(Calculations!G:G,B45,Calculations!J:J) -> 307.83 | F45: =IF(Table8[[#This Row],[Location]]="Belmont Market",1,IF(Table8[[#This Row],[Location]]="Country Club Centre",1,IF(Table8[[#This Row],[Location]]="Naval Air Station Norfolk",0.5,2)))&"% of "&DOLLAR(SUMIF(Calculations!G:G,B45,Calculations!F:F),2)&" "&B45 -> 2% of $15,391.73 Westwood Plaza | G45: =IF((SUMIF(Calculations!$G:$G,Table8[[#This Row],[Location]],Calculations!$K:$K)/COUNTIF(Calculations!$G:$G,Table8[[#This Row],[Location]]))<>VLOOKUP(Table8[[#This Row],[Location]],Calculations!G:M,5,0),"Yes","") | H45: =Table8[[#This Row],[CONTINUINGFEE - Net Value]]+Table8[[#This Row],[MARKETINGFEE - Net Value]] -> 1077.42
A46: =VLOOKUP(B46,'Rates from Tracker'!B:C,2,0) -> TSFR Pizza LLC | B46: Woodhaven | C46: =SUMIF(Calculations!G:G,B46,Calculations!L:L) -> 0 | D46: =IF(Table8[[#This Row],[Rate Increase?]]="Yes","",(VLOOKUP(B46,Calculations!G:K,5,0)*100)&"% of "&DOLLAR(SUMIF(Calculations!G:G,B46,Calculations!F:F),2)&" "&B46) -> #DIV/0! | E46: =SUMIF(Calculations!G:G,B46,Calculations!J:J) -> 0 | F46: =IF(Table8[[#This Row],[Location]]="Belmont Market",1,IF(Table8[[#This Row],[Location]]="Country Club Centre",1,IF(Table8[[#This Row],[Location]]="Naval Air Station Norfolk",0.5,2)))&"% of "&DOLLAR(SUMIF(Calculations!G:G,B46,Calculations!F:F),2)&" "&B46 -> 2% of $0.00 Woodhaven | G46: =IF((SUMIF(Calculations!$G:$G,Table8[[#This Row],[Location]],Calculations!$K:$K)/COUNTIF(Calculations!$G:$G,Table8[[#This Row],[Location]]))<>VLOOKUP(Table8[[#This Row],[Location]],Calculations!G:M,5,0),"Yes","") -> #DIV/0! | H46: =Table8[[#This Row],[CONTINUINGFEE - Net Value]]+Table8[[#This Row],[MARKETINGFEE - Net Value]] -> 0 | I46: closed
A47: =VLOOKUP(B47,'Rates from Tracker'!B:C,2,0) -> Rolling Dough LLC | B47: Woodhill | C47: =SUMIF(Calculations!G:G,B47,Calculations!L:L) -> 954.4 | D47: =IF(Table8[[#This Row],[Rate Increase?]]="Yes","",(VLOOKUP(B47,Calculations!G:K,5,0)*100)&"% of "&DOLLAR(SUMIF(Calculations!G:G,B47,Calculations!F:F),2)&" "&B47) -> 5% of $19,087.62 Woodhill | E47: =SUMIF(Calculations!G:G,B47,Calculations!J:J) -> 381.76 | F47: =IF(Table8[[#This Row],[Location]]="Belmont Market",1,IF(Table8[[#This Row],[Location]]="Country Club Centre",1,IF(Table8[[#This Row],[Location]]="Naval Air Station Norfolk",0.5,2)))&"% of "&DOLLAR(SUMIF(Calculations!G:G,B47,Calculations!F:F),2)&" "&B47 -> 2% of $19,087.62 Woodhill | G47: =IF((SUMIF(Calculations!$G:$G,Table8[[#This Row],[Location]],Calculations!$K:$K)/COUNTIF(Calculations!$G:$G,Table8[[#This Row],[Location]]))<>VLOOKUP(Table8[[#This Row],[Location]],Calculations!G:M,5,0),"Yes","") | H47: =Table8[[#This Row],[CONTINUINGFEE - Net Value]]+Table8[[#This Row],[MARKETINGFEE - Net Value]] -> 1336.16
A48: =VLOOKUP(B48,'Rates from Tracker'!B:C,2,0) -> Exceed Group Woodland | B48: Woodland | C48: =SUMIF(Calculations!G:G,B48,Calculations!L:L) -> 978.4 | D48: =IF(Table8[[#This Row],[Rate Increase?]]="Yes","",(VLOOKUP(B48,Calculations!G:K,5,0)*100)&"% of "&DOLLAR(SUMIF(Calculations!G:G,B48,Calculations!F:F),2)&" "&B48) -> 5% of $19,567.78 Woodland | E48: =SUMIF(Calculations!G:G,B48,Calculations!J:J) -> 391.36 | F48: =IF(Table8[[#This Row],[Location]]="Belmont Market",1,IF(Table8[[#This Row],[Location]]="Country Club Centre",1,IF(Table8[[#This Row],[Location]]="Naval Air Station Norfolk",0.5,2)))&"% of "&DOLLAR(SUMIF(Calculations!G:G,B48,Calculations!F:F),2)&" "&B48 -> 2% of $19,567.78 Woodland | G48: =IF((SUMIF(Calculations!$G:$G,Table8[[#This Row],[Location]],Calculations!$K:$K)/COUNTIF(Calculations!$G:$G,Table8[[#This Row],[Location]]))<>VLOOKUP(Table8[[#This Row],[Location]],Calculations!G:M,5,0),"Yes","") | H48: =Table8[[#This Row],[CONTINUINGFEE - Net Value]]+Table8[[#This Row],[MARKETINGFEE - Net Value]] -> 1369.76
A49: =VLOOKUP(B49,'Rates from Tracker'!B:C,2,0) -> Paceline Partners, LLC (OH) | B49: Pickerington | C49: =SUMIF(Calculations!G:G,B49,Calculations!L:L) -> 0 | D49: =IF(Table8[[#This Row],[Rate Increase?]]="Yes","",(VLOOKUP(B49,Calculations!G:K,5,0)*100)&"% of "&DOLLAR(SUMIF(Calculations!G:G,B49,Calculations!F:F),2)&" "&B49) -> #DIV/0! | E49: =SUMIF(Calculations!G:G,B49,Calculations!J:J) -> 0 | F49: =IF(Table8[[#This Row],[Location]]="Belmont Market",1,IF(Table8[[#This Row],[Location]]="Country Club Centre",1,IF(Table8[[#This Row],[Location]]="Naval Air Station Norfolk",0.5,2)))&"% of "&DOLLAR(SUMIF(Calculations!G:G,B49,Calculations!F:F),2)&" "&B49 -> 2% of $0.00 Pickerington | G49: =IF((SUMIF(Calculations!$G:$G,Table8[[#This Row],[Location]],Calculations!$K:$K)/COUNTIF(Calculations!$G:$G,Table8[[#This Row],[Location]]))<>VLOOKUP(Table8[[#This Row],[Location]],Calculations!G:M,5,0),"Yes","") -> #DIV/0! | H49: =Table8[[#This Row],[CONTINUINGFEE - Net Value]]+Table8[[#This Row],[MARKETINGFEE - Net Value]] -> 0 | I49: closed
A50: =VLOOKUP(B50,'Rates from Tracker'!B:C,2,0) -> Best Pizza LLC | B50: Highlands Ranch | C50: =SUMIF(Calculations!G:G,B50,Calculations!L:L) -> 1473.09 | D50: =IF(Table8[[#This Row],[Rate Increase?]]="Yes","",(VLOOKUP(B50,Calculations!G:K,5,0)*100)&"% of "&DOLLAR(SUMIF(Calculations!G:G,B50,Calculations!F:F),2)&" "&B50) -> 5% of $29,461.80 Highlands Ranch | E50: =SUMIF(Calculations!G:G,B50,Calculations!J:J) -> 589.25 | F50: =IF(Table8[[#This Row],[Location]]="Belmont Market",1,IF(Table8[[#This Row],[Location]]="Country Club Centre",1,IF(Table8[[#This Row],[Location]]="Naval Air Station Norfolk",0.5,2)))&"% of "&DOLLAR(SUMIF(Calculations!G:G,B50,Calculations!F:F),2)&" "&B50 -> 2% of $29,461.80 Highlands Ranch | G50: =IF((SUMIF(Calculations!$G:$G,Table8[[#This Row],[Location]],Calculations!$K:$K)/COUNTIF(Calculations!$G:$G,Table8[[#This Row],[Location]]))<>VLOOKUP(Table8[[#This Row],[Location]],Calculations!G:M,5,0),"Yes","") | H50: =Table8[[#This Row],[CONTINUINGFEE - Net Value]]+Table8[[#This Row],[MARKETINGFEE - Net Value]] -> 2062.34
A51: =VLOOKUP(B51,'Rates from Tracker'!B:C,2,0) -> DAZ9 | B51: Decatur | C51: =SUMIF(Calculations!G:G,B51,Calculations!L:L) -> 114.56 | D51: =IF(Table8[[#This Row],[Rate Increase?]]="Yes","",(VLOOKUP(B51,Calculations!G:K,5,0)*100)&"% of "&DOLLAR(SUMIF(Calculations!G:G,B51,Calculations!F:F),2)&" "&B51) -> 1% of $11,456.24 Decatur | E51: =SUMIF(Calculations!G:G,B51,Calculations!J:J) -> 229.12 | F51: =IF(Table8[[#This Row],[Location]]="Belmont Market",1,IF(Table8[[#This Row],[Location]]="Country Club Centre",1,IF(Table8[[#This Row],[Location]]="Naval Air Station Norfolk",0.5,2)))&"% of "&DOLLAR(SUMIF(Calculations!G:G,B51,Calculations!F:F),2)&" "&B51 -> 2% of $11,456.24 Decatur | H51: =Table8[[#This Row],[CONTINUINGFEE - Net Value]]+Table8[[#This Row],[MARKETINGFEE - Net Value]] -> 343.68
A52: =VLOOKUP(B52,'Rates from Tracker'!B:C,2,0) -> Paceline Partners, LLC (KS/MO) | B52: Antioch Crossing | C52: =SUMIF(Calculations!G:G,B52,Calculations!L:L) -> 0 | D52: =IF(Table8[[#This Row],[Rate Increase?]]="Yes","",(VLOOKUP(B52,Calculations!G:K,5,0)*100)&"% of "&DOLLAR(SUMIF(Calculations!G:G,B52,Calculations!F:F),2)&" "&B52) -> #DIV/0! | E52: =SUMIF(Calculations!G:G,B52,Calculations!J:J) -> 0 | F52: =IF(Table8[[#This Row],[Location]]="Belmont Market",1,IF(Table8[[#This Row],[Location]]="Country Club Centre",1,IF(Table8[[#This Row],[Location]]="Naval Air Station Norfolk",0.5,2)))&"% of "&DOLLAR(SUMIF(Calculations!G:G,B52,Calculations!F:F),2)&" "&B52 -> 2% of $0.00 Antioch Crossing | G52: =IF((SUMIF(Calculations!$G:$G,Table8[[#This Row],[Location]],Calculations!$K:$K)/COUNTIF(Calculations!$G:$G,Table8[[#This Row],[Location]]))<>VLOOKUP(Table8[[#This Row],[Location]],Calculations!G:M,5,0),"Yes","") -> #DIV/0! | H52: =Table8[[#This Row],[CONTINUINGFEE - Net Value]]+Table8[[#This Row],[MARKETINGFEE - Net Value]] -> 0 | I52: closed
A53: =VLOOKUP(B53,'Rates from Tracker'!B:C,2,0) -> Best Pizza LLC | B53: Diamond Circle | C53: =SUMIF(Calculations!G:G,B53,Calculations!L:L) -> 880.67 | D53: =IF(Table8[[#This Row],[Rate Increase?]]="Yes","",(VLOOKUP(B53,Calculations!G:K,5,0)*100)&"% of "&DOLLAR(SUMIF(Calculations!G:G,B53,Calculations!F:F),2)&" "&B53) -> 5% of $17,613.37 Diamond Circle | E53: =SUMIF(Calculations!G:G,B53,Calculations!J:J) -> 352.28 | F53: =IF(Table8[[#This Row],[Location]]="Belmont Market",1,IF(Table8[[#This Row],[Location]]="Country Club Centre",1,IF(Table8[[#This Row],[Location]]="Naval Air Station Norfolk",0.5,2)))&"% of "&DOLLAR(SUMIF(Calculations!G:G,B53,Calculations!F:F),2)&" "&B53 -> 2% of $17,613.37 Diamond Circle | G53: =IF((SUMIF(Calculations!$G:$G,Table8[[#This Row],[Location]],Calculations!$K:$K)/COUNTIF(Calculations!$G:$G,Table8[[#This Row],[Location]]))<>VLOOKUP(Table8[[#This Row],[Location]],Calculations!G:M,5,0),"Yes","") | H53: =Table8[[#This Row],[CONTINUINGFEE - Net Value]]+Table8[[#This Row],[MARKETINGFEE - Net Value]] -> 1232.95
A54: =VLOOKUP(B54,'Rates from Tracker'!B:C,2,0) -> Best Pizza LLC | B54: Polaris Pointe | C54: =SUMIF(Calculations!G:G,B54,Calculations!L:L) -> 1477.65 | D54: =IF(Table8[[#This Row],[Rate Increase?]]="Yes","",(VLOOKUP(B54,Calculations!G:K,5,0)*100)&"% of "&DOLLAR(SUMIF(Calculations!G:G,B54,Calculations!F:F),2)&" "&B54) -> 5% of $29,553.11 Polaris Pointe | E54: =SUMIF(Calculations!G:G,B54,Calculations!J:J) -> 591.07 | F54: =IF(Table8[[#This Row],[Location]]="Belmont Market",1,IF(Table8[[#This Row],[Location]]="Country Club Centre",1,IF(Table8[[#This Row],[Location]]="Naval Air Station Norfolk",0.5,2)))&"% of "&DOLLAR(SUMIF(Calculations!G:G,B54,Calculations!F:F),2)&" "&B54 -> 2% of $29,553.11 Polaris Pointe | G54: =IF((SUMIF(Calculations!$G:$G,Table8[[#This Row],[Location]],Calculations!$K:$K)/COUNTIF(Calculations!$G:$G,Table8[[#This Row],[Location]]))<>VLOOKUP(Table8[[#This Row],[Location]],Calculations!G:M,5,0),"Yes","") | H54: =Table8[[#This Row],[CONTINUINGFEE - Net Value]]+Table8[[#This Row],[MARKETINGFEE - Net Value]] -> 2068.72
A55: =VLOOKUP(B55,'Rates from Tracker'!B:C,2,0) -> Best Pizza LLC | B55: Northfield Commons | C55: =SUMIF(Calculations!G:G,B55,Calculations!L:L) -> 1167.34 | D55: =IF(Table8[[#This Row],[Rate Increase?]]="Yes","",(VLOOKUP(B55,Calculations!G:K,5,0)*100)&"% of "&DOLLAR(SUMIF(Calculations!G:G,B55,Calculations!F:F),2)&" "&B55) -> 5% of $23,346.32 Northfield Commons | E55: =SUMIF(Calculations!G:G,B55,Calculations!J:J) -> 466.93 | F55: =IF(Table8[[#This Row],[Location]]="Belmont Market",1,IF(Table8[[#This Row],[Location]]="Country Club Centre",1,IF(Table8[[#This Row],[Location]]="Naval Air Station Norfolk",0.5,2)))&"% of "&DOLLAR(SUMIF(Calculations!G:G,B55,Calculations!F:F),2)&" "&B55 -> 2% of $23,346.32 Northfield Commons | G55: =IF((SUMIF(Calculations!$G:$G,Table8[[#This Row],[Location]],Calculations!$K:$K)/COUNTIF(Calculations!$G:$G,Table8[[#This Row],[Location]]))<>VLOOKUP(Table8[[#This Row],[Location]],Calculations!G:M,5,0),"Yes","") | H55: =Table8[[#This Row],[CONTINUINGFEE - Net Value]]+Table8[[#This Row],[MARKETINGFEE - Net Value]] -> 1634.27
A56: =VLOOKUP(B56,'Rates from Tracker'!B:C,2,0) -> Paceline Partners, LLC (OH) | B56: Keystone | C56: =SUMIF(Calculations!G:G,B56,Calculations!L:L) -> 0 | D56: =IF(Table8[[#This Row],[Rate Increase?]]="Yes","",(VLOOKUP(B56,Calculations!G:K,5,0)*100)&"% of "&DOLLAR(SUMIF(Calculations!G:G,B56,Calculations!F:F),2)&" "&B56) -> #DIV/0! | E56: =SUMIF(Calculations!G:G,B56,Calculations!J:J) -> 0 | F56: =IF(Table8[[#This Row],[Location]]="Belmont Market",1,IF(Table8[[#This Row],[Location]]="Country Club Centre",1,IF(Table8[[#This Row],[Location]]="Naval Air Station Norfolk",0.5,2)))&"% of "&DOLLAR(SUMIF(Calculations!G:G,B56,Calculations!F:F),2)&" "&B56 -> 2% of $0.00 Keystone | G56: =IF((SUMIF(Calculations!$G:$G,Table8[[#This Row],[Location]],Calculations!$K:$K)/COUNTIF(Calculations!$G:$G,Table8[[#This Row],[Location]]))<>VLOOKUP(Table8[[#This Row],[Location]],Calculations!G:M,5,0),"Yes","") -> #DIV/0! | H56: =Table8[[#This Row],[CONTINUINGFEE - Net Value]]+Table8[[#This Row],[MARKETINGFEE - Net Value]] -> 0 | I56: closed
A57: =VLOOKUP(B57,'Rates from Tracker'!B:C,2,0) -> Exceed Group Rancho Cordova | B57: Rancho Cordova | C57: =SUMIF(Calculations!G:G,B57,Calculations!L:L) -> 728.82 | D57: =IF(Table8[[#This Row],[Rate Increase?]]="Yes","",(VLOOKUP(B57,Calculations!G:K,5,0)*100)&"% of "&DOLLAR(SUMIF(Calculations!G:G,B57,Calculations!F:F),2)&" "&B57) -> 5% of $14,576.59 Rancho Cordova | E57: =SUMIF(Calculations!G:G,B57,Calculations!J:J) -> 291.52 | F57: =IF(Table8[[#This Row],[Location]]="Belmont Market",1,IF(Table8[[#This Row],[Location]]="Country Club Centre",1,IF(Table8[[#This Row],[Location]]="Naval Air Station Norfolk",0.5,2)))&"% of "&DOLLAR(SUMIF(Calculations!G:G,B57,Calculations!F:F),2)&" "&B57 -> 2% of $14,576.59 Rancho Cordova | G57: =IF((SUMIF(Calculations!$G:$G,Table8[[#This Row],[Location]],Calculations!$K:$K)/COUNTIF(Calculations!$G:$G,Table8[[#This Row],[Location]]))<>VLOOKUP(Table8[[#This Row],[Location]],Calculations!G:M,5,0),"Yes","") | H57: =Table8[[#This Row],[CONTINUINGFEE - Net Value]]+Table8[[#This Row],[MARKETINGFEE - Net Value]] -> 1020.34
A58: =VLOOKUP(B58,'Rates from Tracker'!B:C,2,0) -> Southern Pie LLC | B58: Dawsonville | C58: =SUMIF(Calculations!G:G,B58,Calculations!L:L) -> 0 | D58: =IF(Table8[[#This Row],[Rate Increase?]]="Yes","",(VLOOKUP(B58,Calculations!G:K,5,0)*100)&"% of "&DOLLAR(SUMIF(Calculations!G:G,B58,Calculations!F:F),2)&" "&B58) -> #DIV/0! | E58: =SUMIF(Calculations!G:G,B58,Calculations!J:J) -> 0 | F58: =IF(Table8[[#This Row],[Location]]="Belmont Market",1,IF(Table8[[#This Row],[Location]]="Country Club Centre",1,IF(Table8[[#This Row],[Location]]="Naval Air Station Norfolk",0.5,2)))&"% of "&DOLLAR(SUMIF(Calculations!G:G,B58,Calculations!F:F),2)&" "&B58 -> 2% of $0.00 Dawsonville | G58: =IF((SUMIF(Calculations!$G:$G,Table8[[#This Row],[Location]],Calculations!$K:$K)/COUNTIF(Calculations!$G:$G,Table8[[#This Row],[Location]]))<>VLOOKUP(Table8[[#This Row],[Location]],Calculations!G:M,5,0),"Yes","") -> #DIV/0! | H58: =Table8[[#This Row],[CONTINUINGFEE - Net Value]]+Table8[[#This Row],[MARKETINGFEE - Net Value]] -> 0
A59: =VLOOKUP(B59,'Rates from Tracker'!B:C,2,0) -> Best Pizza LLC | B59: Greeley | C59: =SUMIF(Calculations!G:G,B59,Calculations!L:L) -> 1046.88 | D59: =IF(Table8[[#This Row],[Rate Increase?]]="Yes","",(VLOOKUP(B59,Calculations!G:K,5,0)*100)&"% of "&DOLLAR(SUMIF(Calculations!G:G,B59,Calculations!F:F),2)&" "&B59) -> 5% of $20,937.55 Greeley | E59: =SUMIF(Calculations!G:G,B59,Calculations!J:J) -> 418.75 | F59: =IF(Table8[[#This Row],[Location]]="Belmont Market",1,IF(Table8[[#This Row],[Location]]="Country Club Centre",1,IF(Table8[[#This Row],[Location]]="Naval Air Station Norfolk",0.5,2)))&"% of "&DOLLAR(SUMIF(Calculations!G:G,B59,Calculations!F:F),2)&" "&B59 -> 2% of $20,937.55 Greeley | G59: =IF((SUMIF(Calculations!$G:$G,Table8[[#This Row],[Location]],Calculations!$K:$K)/COUNTIF(Calculations!$G:$G,Table8[[#This Row],[Location]]))<>VLOOKUP(Table8[[#This Row],[Location]],Calculations!G:M,5,0),"Yes","") | H59: =Table8[[#This Row],[CONTINUINGFEE - Net Value]]+Table8[[#This Row],[MARKETINGFEE - Net Value]] -> 1465.63
A60: =VLOOKUP(B60,'Rates from Tracker'!B:C,2,0) -> Rolling Dough LLC | B60: Lexington | C60: =SUMIF(Calculations!G:G,B60,Calculations!L:L) -> 940.42 | D60: =IF(Table8[[#This Row],[Rate Increase?]]="Yes","",(VLOOKUP(B60,Calculations!G:K,5,0)*100)&"% of "&DOLLAR(SUMIF(Calculations!G:G,B60,Calculations!F:F),2)&" "&B60) -> 5% of $18,808.62 Lexington | E60: =SUMIF(Calculations!G:G,B60,Calculations!J:J) -> 376.18 | F60: =IF(Table8[[#This Row],[Location]]="Belmont Market",1,IF(Table8[[#This Row],[Location]]="Country Club Centre",1,IF(Table8[[#This Row],[Location]]="Naval Air Station Norfolk",0.5,2)))&"% of "&DOLLAR(SUMIF(Calculations!G:G,B60,Calculations!F:F),2)&" "&B60 -> 2% of $18,808.62 Lexington | G60: =IF((SUMIF(Calculations!$G:$G,Table8[[#This Row],[Location]],Calculations!$K:$K)/COUNTIF(Calculations!$G:$G,Table8[[#This Row],[Location]]))<>VLOOKUP(Table8[[#This Row],[Location]],Calculations!G:M,5,0),"Yes","") | H60: =Table8[[#This Row],[CONTINUINGFEE - Net Value]]+Table8[[#This Row],[MARKETINGFEE - Net Value]] -> 1316.6
A61: =VLOOKUP(B61,'Rates from Tracker'!B:C,2,0) -> Southern Pie LLC | B61: Sandy Springs | C61: =SUMIF(Calculations!G:G,B61,Calculations!L:L) -> 0 | D61: =IF(Table8[[#This Row],[Rate Increase?]]="Yes","",(VLOOKUP(B61,Calculations!G:K,5,0)*100)&"% of "&DOLLAR(SUMIF(Calculations!G:G,B61,Calculations!F:F),2)&" "&B61) -> #DIV/0! | E61: =SUMIF(Calculations!G:G,B61,Calculations!J:J) -> 0 | F61: =IF(Table8[[#This Row],[Location]]="Belmont Market",1,IF(Table8[[#This Row],[Location]]="Country Club Centre",1,IF(Table8[[#This Row],[Location]]="Naval Air Station Norfolk",0.5,2)))&"% of "&DOLLAR(SUMIF(Calculations!G:G,B61,Calculations!F:F),2)&" "&B61 -> 2% of $0.00 Sandy Springs | G61: =IF((SUMIF(Calculations!$G:$G,Table8[[#This Row],[Location]],Calculations!$K:$K)/COUNTIF(Calculations!$G:$G,Table8[[#This Row],[Location]]))<>VLOOKUP(Table8[[#This Row],[Location]],Calculations!G:M,5,0),"Yes","") -> #DIV/0! | H61: =Table8[[#This Row],[CONTINUINGFEE - Net Value]]+Table8[[#This Row],[MARKETINGFEE - Net Value]] -> 0 | I61: closed
A62: =VLOOKUP(B62,'Rates from Tracker'!B:C,2,0) -> Rolling Dough LLC | B62: Augusta Exchange | C62: =SUMIF(Calculations!G:G,B62,Calculations!L:L) -> 841 | D62: =IF(Table8[[#This Row],[Rate Increase?]]="Yes","",(VLOOKUP(B62,Calculations!G:K,5,0)*100)&"% of "&DOLLAR(SUMIF(Calculations!G:G,B62,Calculations!F:F),2)&" "&B62) -> 5% of $16,819.99 Augusta Exchange | E62: =SUMIF(Calculations!G:G,B62,Calculations!J:J) -> 336.41 | F62: =IF(Table8[[#This Row],[Location]]="Belmont Market",1,IF(Table8[[#This Row],[Location]]="Country Club Centre",1,IF(Table8[[#This Row],[Location]]="Naval Air Station Norfolk",0.5,2)))&"% of "&DOLLAR(SUMIF(Calculations!G:G,B62,Calculations!F:F),2)&" "&B62 -> 2% of $16,819.99 Augusta Exchange | G62: =IF((SUMIF(Calculations!$G:$G,Table8[[#This Row],[Location]],Calculations!$K:$K)/COUNTIF(Calculations!$G:$G,Table8[[#This Row],[Location]]))<>VLOOKUP(Table8[[#This Row],[Location]],Calculations!G:M,5,0),"Yes","") | H62: =Table8[[#This Row],[CONTINUINGFEE - Net Value]]+Table8[[#This Row],[MARKETINGFEE - Net Value]] -> 1177.41
A63: =VLOOKUP(B63,'Rates from Tracker'!B:C,2,0) -> TSFR Pizza LLC | B63: Hall Road | C63: =SUMIF(Calculations!G:G,B63,Calculations!L:L) -> 0 | D63: =IF(Table8[[#This Row],[Rate Increase?]]="Yes","",(VLOOKUP(B63,Calculations!G:K,5,0)*100)&"% of "&DOLLAR(SUMIF(Calculations!G:G,B63,Calculations!F:F),2)&" "&B63) -> #DIV/0! | E63: =SUMIF(Calculations!G:G,B63,Calculations!J:J) -> 0 | F63: =IF(Table8[[#This Row],[Location]]="Belmont Market",1,IF(Table8[[#This Row],[Location]]="Country Club Centre",1,IF(Table8[[#This Row],[Location]]="Naval Air Station Norfolk",0.5,2)))&"% of "&DOLLAR(SUMIF(Calculations!G:G,B63,Calculations!F:F),2)&" "&B63 -> 2% of $0.00 Hall Road | G63: =IF((SUMIF(Calculations!$G:$G,Table8[[#This Row],[Location]],Calculations!$K:$K)/COUNTIF(Calculations!$G:$G,Table8[[#This Row],[Location]]))<>VLOOKUP(Table8[[#This Row],[Location]],Calculations!G:M,5,0),"Yes","") -> #DIV/0! | H63: =Table8[[#This Row],[CONTINUINGFEE - Net Value]]+Table8[[#This Row],[MARKETINGFEE - Net Value]] -> 0 | I63: Closed
A64: =VLOOKUP(B64,'Rates from Tracker'!B:C,2,0) -> Exceed Group West Sacramento | B64: West Sacramento | C64: =SUMIF(Calculations!G:G,B64,Calculations!L:L) -> 811.99 | D64: =IF(Table8[[#This Row],[Rate Increase?]]="Yes","",(VLOOKUP(B64,Calculations!G:K,5,0)*100)&"% of "&DOLLAR(SUMIF(Calculations!G:G,B64,Calculations!F:F),2)&" "&B64) -> 5% of $16,240.00 West Sacramento | E64: =SUMIF(Calculations!G:G,B64,Calculations!J:J) -> 324.81 | F64: =IF(Table8[[#This Row],[Location]]="Belmont Market",1,IF(Table8[[#This Row],[Location]]="Country Club Centre",1,IF(Table8[[#This Row],[Location]]="Naval Air Station Norfolk",0.5,2)))&"% of "&DOLLAR(SUMIF(Calculations!G:G,B64,Calculations!F:F),2)&" "&B64 -> 2% of $16,240.00 West Sacramento | G64: =IF((SUMIF(Calculations!$G:$G,Table8[[#This Row],[Location]],Calculations!$K:$K)/COUNTIF(Calculations!$G:$G,Table8[[#This Row],[Location]]))<>VLOOKUP(Table8[[#This Row],[Location]],Calculations!G:M,5,0),"Yes","") | H64: =Table8[[#This Row],[CONTINUINGFEE - Net Value]]+Table8[[#This Row],[MARKETINGFEE - Net Value]] -> 1136.8
A65: =VLOOKUP(B65,'Rates from Tracker'!B:C,2,0) -> APizza Delight Inc | B65: Madison | C65: =SUMIF(Calculations!G:G,B65,Calculations!L:L) -> 118.94 | D65: =IF(Table8[[#This Row],[Rate Increase?]]="Yes","",(VLOOKUP(B65,Calculations!G:K,5,0)*100)&"% of "&DOLLAR(SUMIF(Calculations!G:G,B65,Calculations!F:F),2)&" "&B65) -> 1% of $11,892.77 Madison | E65: =SUMIF(Calculations!G:G,B65,Calculations!J:J) -> 237.86 | F65: =IF(Table8[[#This Row],[Location]]="Belmont Market",1,IF(Table8[[#This Row],[Location]]="Country Club Centre",1,IF(Table8[[#This Row],[Location]]="Naval Air Station Norfolk",0.5,2)))&"% of "&DOLLAR(SUMIF(Calculations!G:G,B65,Calculations!F:F),2)&" "&B65 -> 2% of $11,892.77 Madison | G65: =IF((SUMIF(Calculations!$G:$G,Table8[[#This Row],[Location]],Calculations!$K:$K)/COUNTIF(Calculations!$G:$G,Table8[[#This Row],[Location]]))<>VLOOKUP(Table8[[#This Row],[Location]],Calculations!G:M,5,0),"Yes","") | H65: =Table8[[#This Row],[CONTINUINGFEE - Net Value]]+Table8[[#This Row],[MARKETINGFEE - Net Value]] -> 356.8
A66: =VLOOKUP(B66,'Rates from Tracker'!B:C,2,0) -> TSFR Pizza LLC | B66: Troy | C66: =SUMIF(Calculations!G:G,B66,Calculations!L:L) -> 0 | D66: =IF(Table8[[#This Row],[Rate Increase?]]="Yes","",(VLOOKUP(B66,Calculations!G:K,5,0)*100)&"% of "&DOLLAR(SUMIF(Calculations!G:G,B66,Calculations!F:F),2)&" "&B66) -> #DIV/0! | E66: =SUMIF(Calculations!G:G,B66,Calculations!J:J) -> 0 | F66: =IF(Table8[[#This Row],[Location]]="Belmont Market",1,IF(Table8[[#This Row],[Location]]="Country Club Centre",1,IF(Table8[[#This Row],[Location]]="Naval Air Station Norfolk",0.5,2)))&"% of "&DOLLAR(SUMIF(Calculations!G:G,B66,Calculations!F:F),2)&" "&B66 -> 2% of $0.00 Troy | G66: =IF((SUMIF(Calculations!$G:$G,Table8[[#This Row],[Location]],Calculations!$K:$K)/COUNTIF(Calculations!$G:$G,Table8[[#This Row],[Location]]))<>VLOOKUP(Table8[[#This Row],[Location]],Calculations!G:M,5,0),"Yes","") -> #DIV/0! | H66: =Table8[[#This Row],[CONTINUINGFEE - Net Value]]+Table8[[#This Row],[MARKETINGFEE - Net Value]] -> 0
A67: =VLOOKUP(B67,'Rates from Tracker'!B:C,2,0) -> Southern Pie LLC | B67: Chamblee | C67: =SUMIF(Calculations!G:G,B67,Calculations!L:L) -> 0 | D67: =IF(Table8[[#This Row],[Rate Increase?]]="Yes","",(VLOOKUP(B67,Calculations!G:K,5,0)*100)&"% of "&DOLLAR(SUMIF(Calculations!G:G,B67,Calculations!F:F),2)&" "&B67) -> #DIV/0! | E67: =SUMIF(Calculations!G:G,B67,Calculations!J:J) -> 0 | F67: =IF(Table8[[#This Row],[Location]]="Belmont Market",1,IF(Table8[[#This Row],[Location]]="Country Club Centre",1,IF(Table8[[#This Row],[Location]]="Naval Air Station Norfolk",0.5,2)))&"% of "&DOLLAR(SUMIF(Calculations!G:G,B67,Calculations!F:F),2)&" "&B67 -> 2% of $0.00 Chamblee | G67: =IF((SUMIF(Calculations!$G:$G,Table8[[#This Row],[Location]],Calculations!$K:$K)/COUNTIF(Calculations!$G:$G,Table8[[#This Row],[Location]]))<>VLOOKUP(Table8[[#This Row],[Location]],Calculations!G:M,5,0),"Yes","") -> #DIV/0! | H67: =Table8[[#This Row],[CONTINUINGFEE - Net Value]]+Table8[[#This Row],[MARKETINGFEE - Net Value]] -> 0 | I67: Closed
A68: =VLOOKUP(B68,'Rates from Tracker'!B:C,2,0) -> Best Pizza LLC | B68: Ralston Creek | C68: =SUMIF(Calculations!G:G,B68,Calculations!L:L) -> 1196.97 | D68: =IF(Table8[[#This Row],[Rate Increase?]]="Yes","",(VLOOKUP(B68,Calculations!G:K,5,0)*100)&"% of "&DOLLAR(SUMIF(Calculations!G:G,B68,Calculations!F:F),2)&" "&B68) -> 5% of $23,939.38 Ralston Creek | E68: =SUMIF(Calculations!G:G,B68,Calculations!J:J) -> 478.78 | F68: =IF(Table8[[#This Row],[Location]]="Belmont Market",1,IF(Table8[[#This Row],[Location]]="Country Club Centre",1,IF(Table8[[#This Row],[Location]]="Naval Air Station Norfolk",0.5,2)))&"% of "&DOLLAR(SUMIF(Calculations!G:G,B68,Calculations!F:F),2)&" "&B68 -> 2% of $23,939.38 Ralston Creek | G68: =IF((SUMIF(Calculations!$G:$G,Table8[[#This Row],[Location]],Calculations!$K:$K)/COUNTIF(Calculations!$G:$G,Table8[[#This Row],[Location]]))<>VLOOKUP(Table8[[#This Row],[Location]],Calculations!G:M,5,0),"Yes","") | H68: =Table8[[#This Row],[CONTINUINGFEE - Net Value]]+Table8[[#This Row],[MARKETINGFEE - Net Value]] -> 1675.75
A69: =VLOOKUP(B69,'Rates from Tracker'!B:C,2,0) -> MAA MELDI 3980 Inc | B69: Mobile | C69: =SUMIF(Calculations!G:G,B69,Calculations!L:L) -> 117.18 | D69: =IF(Table8[[#This Row],[Rate Increase?]]="Yes","",(VLOOKUP(B69,Calculations!G:K,5,0)*100)&"% of "&DOLLAR(SUMIF(Calculations!G:G,B69,Calculations!F:F),2)&" "&B69) -> 1% of $11,718.78 Mobile | E69: =SUMIF(Calculations!G:G,B69,Calculations!J:J) -> 234.39 | F69: =IF(Table8[[#This Row],[Location]]="Belmont Market",1,IF(Table8[[#This Row],[Location]]="Country Club Centre",1,IF(Table8[[#This Row],[Location]]="Naval Air Station Norfolk",0.5,2)))&"% of "&DOLLAR(SUMIF(Calculations!G:G,B69,Calculations!F:F),2)&" "&B69 -> 2% of $11,718.78 Mobile | G69: =IF((SUMIF(Calculations!$G:$G,Table8[[#This Row],[Location]],Calculations!$K:$K)/COUNTIF(Calculations!$G:$G,Table8[[#This Row],[Location]]))<>VLOOKUP(Table8[[#This Row],[Location]],Calculations!G:M,5,0),"Yes","") | H69: =Table8[[#This Row],[CONTINUINGFEE - Net Value]]+Table8[[#This Row],[MARKETINGFEE - Net Value]] -> 351.57
A70: =VLOOKUP(B70,'Rates from Tracker'!B:C,2,0) -> Cool Dough Development, LLC | B70: Georgetown | C70: =SUMIF(Calculations!G:G,B70,Calculations!L:L) -> 696.82 | D70: =IF(Table8[[#This Row],[Rate Increase?]]="Yes","",(VLOOKUP(B70,Calculations!G:K,5,0)*100)&"% of "&DOLLAR(SUMIF(Calculations!G:G,B70,Calculations!F:F),2)&" "&B70) -> 5% of $13,936.25 Georgetown | E70: =SUMIF(Calculations!G:G,B70,Calculations!J:J) -> 278.73 | F70: =IF(Table8[[#This Row],[Location]]="Belmont Market",1,IF(Table8[[#This Row],[Location]]="Country Club Centre",1,IF(Table8[[#This Row],[Location]]="Naval Air Station Norfolk",0.5,2)))&"% of "&DOLLAR(SUMIF(Calculations!G:G,B70,Calculations!F:F),2)&" "&B70 -> 2% of $13,936.25 Georgetown | G70: =IF((SUMIF(Calculations!$G:$G,Table8[[#This Row],[Location]],Calculations!$K:$K)/COUNTIF(Calculations!$G:$G,Table8[[#This Row],[Location]]))<>VLOOKUP(Table8[[#This Row],[Location]],Calculations!G:M,5,0),"Yes","") | H70: =Table8[[#This Row],[CONTINUINGFEE - Net Value]]+Table8[[#This Row],[MARKETINGFEE - Net Value]] -> 975.55
A71: =VLOOKUP(B71,'Rates from Tracker'!B:C,2,0) -> Compass Group USA, Inc. | B71: Northwestern University | C71: =SUMIF(Calculations!G:G,B71,Calculations!L:L) -> 0 | D71: =IF(Table8[[#This Row],[Rate Increase?]]="Yes","",(VLOOKUP(B71,Calculations!G:K,5,0)*100)&"% of "&DOLLAR(SUMIF(Calculations!G:G,B71,Calculations!F:F),2)&" "&B71) -> #DIV/0! | E71: =SUMIF(Calculations!G:G,B71,Calculations!J:J) -> 0 | F71: =IF(Table8[[#This Row],[Location]]="Belmont Market",1,IF(Table8[[#This Row],[Location]]="Country Club Centre",1,IF(Table8[[#This Row],[Location]]="Naval Air Station Norfolk",0.5,2)))&"% of "&DOLLAR(SUMIF(Calculations!G:G,B71,Calculations!F:F),2)&" "&B71 -> 2% of $0.00 Northwestern University | G71: =IF((SUMIF(Calculations!$G:$G,Table8[[#This Row],[Location]],Calculations!$K:$K)/COUNTIF(Calculations!$G:$G,Table8[[#This Row],[Location]]))<>VLOOKUP(Table8[[#This Row],[Location]],Calculations!G:M,5,0),"Yes","") -> #DIV/0! | H71: =Table8[[#This Row],[CONTINUINGFEE - Net Value]]+Table8[[#This Row],[MARKETINGFEE - Net Value]] -> 0 | I71: Billed separately
A72: =VLOOKUP(B72,'Rates from Tracker'!B:C,2,0) -> TSFR Pizza LLC | B72: Kalamazoo | C72: =SUMIF(Calculations!G:G,B72,Calculations!L:L) -> 0 | D72: =IF(Table8[[#This Row],[Rate Increase?]]="Yes","",(VLOOKUP(B72,Calculations!G:K,5,0)*100)&"% of "&DOLLAR(SUMIF(Calculations!G:G,B72,Calculations!F:F),2)&" "&B72) -> #DIV/0! | E72: =SUMIF(Calculations!G:G,B72,Calculations!J:J) -> 0 | F72: =IF(Table8[[#This Row],[Location]]="Belmont Market",1,IF(Table8[[#This Row],[Location]]="Country Club Centre",1,IF(Table8[[#This Row],[Location]]="Naval Air Station Norfolk",0.5,2)))&"% of "&DOLLAR(SUMIF(Calculations!G:G,B72,Calculations!F:F),2)&" "&B72 -> 2% of $0.00 Kalamazoo | G72: =IF((SUMIF(Calculations!$G:$G,Table8[[#This Row],[Location]],Calculations!$K:$K)/COUNTIF(Calculations!$G:$G,Table8[[#This Row],[Location]]))<>VLOOKUP(Table8[[#This Row],[Location]],Calculations!G:M,5,0),"Yes","") -> #DIV/0! | H72: =Table8[[#This Row],[CONTINUINGFEE - Net Value]]+Table8[[#This Row],[MARKETINGFEE - Net Value]] -> 0 | I72: Closed
A73: =VLOOKUP(B73,'Rates from Tracker'!B:C,2,0) -> Best Pizza LLC | B73: Crown Point | C73: =SUMIF(Calculations!G:G,B73,Calculations!L:L) -> 1307.1 | D73: =IF(Table8[[#This Row],[Rate Increase?]]="Yes","",(VLOOKUP(B73,Calculations!G:K,5,0)*100)&"% of "&DOLLAR(SUMIF(Calculations!G:G,B73,Calculations!F:F),2)&" "&B73) -> 5% of $26,141.91 Crown Point | E73: =SUMIF(Calculations!G:G,B73,Calculations!J:J) -> 522.84 | F73: =IF(Table8[[#This Row],[Location]]="Belmont Market",1,IF(Table8[[#This Row],[Location]]="Country Club Centre",1,IF(Table8[[#This Row],[Location]]="Naval Air Station Norfolk",0.5,2)))&"% of "&DOLLAR(SUMIF(Calculations!G:G,B73,Calculations!F:F),2)&" "&B73 -> 2% of $26,141.91 Crown Point | G73: =IF((SUMIF(Calculations!$G:$G,Table8[[#This Row],[Location]],Calculations!$K:$K)/COUNTIF(Calculations!$G:$G,Table8[[#This Row],[Location]]))<>VLOOKUP(Table8[[#This Row],[Location]],Calculations!G:M,5,0),"Yes","") | H73: =Table8[[#This Row],[CONTINUINGFEE - Net Value]]+Table8[[#This Row],[MARKETINGFEE - Net Value]] -> 1829.94
A74: =VLOOKUP(B74,'Rates from Tracker'!B:C,2,0) -> TSFR Pizza LLC | B74: Alpine | C74: =SUMIF(Calculations!G:G,B74,Calculations!L:L) -> 0 | D74: =IF(Table8[[#This Row],[Rate Increase?]]="Yes","",(VLOOKUP(B74,Calculations!G:K,5,0)*100)&"% of "&DOLLAR(SUMIF(Calculations!G:G,B74,Calculations!F:F),2)&" "&B74) -> #DIV/0! | E74: =SUMIF(Calculations!G:G,B74,Calculations!J:J) -> 0 | F74: =IF(Table8[[#This Row],[Location]]="Belmont Market",1,IF(Table8[[#This Row],[Location]]="Country Club Centre",1,IF(Table8[[#This Row],[Location]]="Naval Air Station Norfolk",0.5,2)))&"% of "&DOLLAR(SUMIF(Calculations!G:G,B74,Calculations!F:F),2)&" "&B74 -> 2% of $0.00 Alpine | G74: =IF((SUMIF(Calculations!$G:$G,Table8[[#This Row],[Location]],Calculations!$K:$K)/COUNTIF(Calculations!$G:$G,Table8[[#This Row],[Location]]))<>VLOOKUP(Table8[[#This Row],[Location]],Calculations!G:M,5,0),"Yes","") -> #DIV/0! | H74: =Table8[[#This Row],[CONTINUINGFEE - Net Value]]+Table8[[#This Row],[MARKETINGFEE - Net Value]] -> 0 | I74: closed
A75: =VLOOKUP(B75,'Rates from Tracker'!B:C,2,0) -> DTW North Partners LLC | B75: DTW Airport | C75: =SUMIF(Calculations!G:G,B75,Calculations!L:L) -> 0 | D75: =IF(Table8[[#This Row],[Rate Increase?]]="Yes","",(VLOOKUP(B75,Calculations!G:K,5,0)*100)&"% of "&DOLLAR(SUMIF(Calculations!G:G,B75,Calculations!F:F),2)&" "&B75) -> #DIV/0! | E75: =SUMIF(Calculations!G:G,B75,Calculations!J:J) -> 0 | F75: =IF(Table8[[#This Row],[Location]]="Belmont Market",1,IF(Table8[[#This Row],[Location]]="Country Club Centre",1,IF(Table8[[#This Row],[Location]]="Naval Air Station Norfolk",0.5,2)))&"% of "&DOLLAR(SUMIF(Calculations!G:G,B75,Calculations!F:F),2)&" "&B75 -> 2% of $0.00 DTW Airport | G75: =IF((SUMIF(Calculations!$G:$G,Table8[[#This Row],[Location]],Calculations!$K:$K)/COUNTIF(Calculations!$G:$G,Table8[[#This Row],[Location]]))<>VLOOKUP(Table8[[#This Row],[Location]],Calculations!G:M,5,0),"Yes","") -> #DIV/0! | H75: =Table8[[#This Row],[CONTINUINGFEE - Net Value]]+Table8[[#This Row],[MARKETINGFEE - Net Value]] -> 0 | I75: Billed separately
A76: =VLOOKUP(B76,'Rates from Tracker'!B:C,2,0) -> TSFR Pizza LLC | B76: Grand Rapids | C76: =SUMIF(Calculations!G:G,B76,Calculations!L:L) -> 0 | D76: =IF(Table8[[#This Row],[Rate Increase?]]="Yes","",(VLOOKUP(B76,Calculations!G:K,5,0)*100)&"% of "&DOLLAR(SUMIF(Calculations!G:G,B76,Calculations!F:F),2)&" "&B76) -> #DIV/0! | E76: =SUMIF(Calculations!G:G,B76,Calculations!J:J) -> 0 | F76: =IF(Table8[[#This Row],[Location]]="Belmont Market",1,IF(Table8[[#This Row],[Location]]="Country Club Centre",1,IF(Table8[[#This Row],[Location]]="Naval Air Station Norfolk",0.5,2)))&"% of "&DOLLAR(SUMIF(Calculations!G:G,B76,Calculations!F:F),2)&" "&B76 -> 2% of $0.00 Grand Rapids | G76: =IF((SUMIF(Calculations!$G:$G,Table8[[#This Row],[Location]],Calculations!$K:$K)/COUNTIF(Calculations!$G:$G,Table8[[#This Row],[Location]]))<>VLOOKUP(Table8[[#This Row],[Location]],Calculations!G:M,5,0),"Yes","") -> #DIV/0! | H76: =Table8[[#This Row],[CONTINUINGFEE - Net Value]]+Table8[[#This Row],[MARKETINGFEE - Net Value]] -> 0 | I76: closed
